Workbook

Sheet MASTER-2025
A1: DONOR | B1: {KG DECREASE IN THE MONTH} | C1: {KG DONATED IN THE MONTH} | D1: {KG YOU PROFIT IN THE MONTH} | E1: {FEED FORMULA % USED} | F1: {FOOD FORMULA % MERMA} | G1: {FORMULA CONVERSION TO FOOD PLATES} | H1: SIN AREA Obs/PRO | I1: NO ASSIGNED KG AREA | J1: SIN AREA BENEFICIARIOS | K1: P CENTRO Obs/PRO | L1: P CENTRO KG ASIGNADOS | M1: P CENTRO BENEFICIARIOS | N1: ESTE Obs/PRO | O1: ESTE KG ASIGNADOS | P1: ESTE BENEFICIARIOS | Q1: NORTE Obs/PRO | R1: NORTE KG ASIGNADOS | S1: NORTE BENEFICIARIOS | T1: SAN MIGUELITO Obs/PRO | U1: SAN MIGUELITO KG ASIGNADOS | V1: SAN MIGUELITO BENEFICIARIOS | W1: OESTE Obs/PRO | X1: OESTE KG ASIGNADOS | Y1: OESTE BENEFICIARIOS | Z1: COCLE Obs/PRO | AA1: COCLE KG ASIGNADOS | AB1: COCLE BENEFICIARIOS | AC1: COLON Obs/PRO | AD1: COLON KG ASIGNADOS | AE1: COLON BENEFICIARIOS | AF1: DARIÉN Obs/PRO | AG1: DARIÉN KG ASIGNADOS | AH1: DARIÉN BENEFICIARIOS | AI1: HERRERA Obs/PRO | AJ1: HERRERA KG ASIGNADOS | AK1: HERRERA BENEFICIARIOS | AL1: LOS SANTOS Obs/PRO | AM1: LOS SANTOS KG ASIGNADOS | AN1: LOS SANTOS BENEFICIARIOS | AO1: VERAGUAS Obs/PRO | AP1: VERAGUAS KG ASIGNADOS | AQ1: VERAGUAS BENEFICIARIOS | AR1: CHIRIQUI Obs/PRO | AS1: CHIRIQUI KG ASIGNADOS | AT1: CHIRIQUI BENEFICIARIOS | AU1: BOCAS Obs/PRO | AV1: BOCAS KG ASIGNADOS | AW1: BOCAS BENEFICIARIOS | AX1: Comarca Ngabe Bugle Obs/PRO | AY1: Comarca Ngabe Bugle KG ASIGNADOS | AZ1: Comarca Ngabe Bugle BENEFICIARIOS | BA1: Total Obs/PRO | BB1: Total KG ASIGNADOS | BC1: Total_Prov_Pma | BD1: Total BENEFICIARIOS | BE1: Sin Edad | BF1: Niños 0-5 | BG1: Niños 6-10 | BH1: Niños 11-18 | BI1: Total NIÑOS | BJ1: Total ADULTOS | BK1: Benefeciarios en Total | BL1: OB_Ene | BM1: OB_Feb | BN1: OB_Mar | BO1: OB_Abr | BP1: OB_May | BQ1: OB_Jun | BR1: OB_Jul | BS1: OB_Ago | BT1: OB_Sep | BU1: OB_Oct | BV1: OB_Nov | BW1: OB_Dic | BX1: OB_Total | BY1: Kilos_Ene | BZ1: Kilos_Feb | CA1: Kilos_Mar | CB1: Kilos_Abr | CC1: Kilos_May | CD1: Kilos_Jun | CE1: Kilos_Jul | CF1: Kilos_Ago | CG1: Kilos_Sep | CH1: Kilos_Oct | CI1: Kilos_Nov | CJ1: Kilos_Dic | CK1: Kilos_Total | CL1: Poblacion_Ene | CM1: Poblacion_Feb | CN1: Poblacion_Mar | CO1: Poblacion_Abr | CP1: Poblacion_May | CQ1: Poblacion_Jun | CR1: Poblacion_Jul | CS1: Poblacion_Ago | CT1: Poblacion_Sep | CU1: Poblacion_Oct | CV1: Poblacion_Nov | CW1: Poblacion_Dic | CX1: Poblacion_Total | CY1: Contacto principal | CZ1: Correo Electrónico | DA1: Telefono | DB1: File Name
A2: FEDURO AGENCIES | B2: =INT(IFERROR(VLOOKUP(A2,'[1]Donor Summary'!C:F,3,0),0)) -> 0 | C2: =INT(ROUND(IFERROR(VLOOKUP(A2,'[1]Donor Summary'!C:F,4,0),0),1)) -> 0 | D2: =INT(ROUND(C2-B2,1)) -> 0 | E2: =IF(A2=0,"",TEXT((IFERROR(D2/C2,0)),"0.00%")) -> 0.00% | F2: =IF(A2=0,"",TEXT((IFERROR(B2/C2,0)),"0.0%")) -> 0.0% | G2: =INT(D2*3) -> 0 | I2: =IFERROR(VLOOKUP(A2,'[1]Lot All by Part'!T:Y,6,0),0) -> 0 | K2: =IFERROR(VLOOKUP($A2,'[1]Donor-Served OBs'!A:N,3,0),0) -> 0 | L2: =ROUNDUP(IF(A2=0,0,IFERROR(VLOOKUP($A2,'[1]Donor''s Assigned Kilos'!A:O,3,0),0)),0) -> 0 | M2: =IF(A2=0,0,IFERROR(SUMIFS([1]Population!M:M,[1]Population!J:J,'MASTER-2025'!A2),0)) -> 0 | N2: =IFERROR(VLOOKUP($A2,'[1]Donor-Served OBs'!A:N,4,0),0) -> 0 | O2: =ROUNDUP(IF(A2=0,0,IFERROR(VLOOKUP($A2,'[1]Donor''s Assigned Kilos'!A:O,4,0),0)),0) -> 0 | P2: =IF(A2=0,0,IFERROR(SUMIFS([1]Population!N:N,[1]Population!J:J,'MASTER-2025'!A2),0)) -> 0 | Q2: =IFERROR(VLOOKUP($A2,'[1]Donor-Served OBs'!A:N,2,0),0) -> 0 | R2: =ROUNDUP(ROUND(IF(A2=0,0,IFERROR(VLOOKUP($A2,'[1]Donor''s Assigned Kilos'!A:O,9,0),0)),1),0) -> 0 | S2: =IF(A2=0,0,IFERROR(SUMIFS([1]Population!S:S,[1]Population!J:J,'MASTER-2025'!A2),0)) -> 0 | T2: =IFERROR(VLOOKUP($A2,'[1]Donor-Served OBs'!A:N,12,0),0) -> 0 | U2: =ROUNDUP(IF(A2=0,0,IF(A2=0,0,IFERROR(VLOOKUP($A2,'[1]Donor''s Assigned Kilos'!A:O,7,0),0))),0) -> 0 | V2: =IF(A2=0,0,IFERROR(SUMIFS([1]Population!Q:Q,[1]Population!J:J,'MASTER-2025'!A2),0)) -> 0 | W2: =IFERROR(VLOOKUP($A2,'[1]Donor-Served OBs'!A:N,10,0),0) -> 0 | X2: =ROUNDUP(IF(A2=0,0,IFERROR(VLOOKUP($A2,'[1]Donor''s Assigned Kilos'!A:N,5,0),0)),0) -> 0 | Y2: =IF(A2=0,0,IFERROR(SUMIFS([1]Population!O:O,[1]Population!J:J,'MASTER-2025'!A2),0)) -> 0 | Z2: =IFERROR(VLOOKUP($A2,'[1]Donor-Served OBs'!A:N,6,0),0) -> 0 | AA2: =ROUNDUP(IF(A2=0,0,IFERROR(VLOOKUP($A2,'[1]Donor''s Assigned Kilos'!A:N,11,0),0)),0) -> 0 | AB2: =IF(A2=0,0,IFERROR(SUMIFS([1]Population!U:U,[1]Population!J:J,'MASTER-2025'!A2),0)) -> 0 | AC2: =IFERROR(VLOOKUP($A2,'[1]Donor-Served OBs'!A:N,7,0),0) -> 0 | AD2: =ROUNDUP(IF(A2=0,0,IFERROR(VLOOKUP($A2,'[1]Donor''s Assigned Kilos'!A:N,8,0),0)),0) -> 0 | AE2: =IF(A2=0,0,IFERROR(SUMIFS([1]Population!R:R,[1]Population!J:J,'MASTER-2025'!A2),0)) -> 0 | AF2: =IFERROR(VLOOKUP($A2,'[1]Donor-Served OBs'!A:N,8,0),0) -> 0 | AG2: =ROUNDUP(IF(A2=0,0,IFERROR(VLOOKUP($A2,'[1]Donor''s Assigned Kilos'!A:N,6,0),0)),0) -> 0 | AH2: =IF(A2=0,0,IFERROR(SUMIFS([1]Population!P:P,[1]Population!J:J,'MASTER-2025'!A2),0)) -> 0 | AI2: =IFERROR(VLOOKUP($A2,'[1]Donor-Served OBs'!A:N,9,0),0) -> 0 | AJ2: =ROUNDUP(IF(A2=0,0,IFERROR(VLOOKUP($A2,'[1]Donor''s Assigned Kilos'!A:N,12,0),0)),0) -> 0 | AK2: =IF(A2=0,0,IFERROR(SUMIFS([1]Population!V:V,[1]Population!J:J,'MASTER-2025'!A2),0)) -> 0 | AL2: =IFERROR(VLOOKUP($A2,'[1]Donor-Served OBs'!A:N,16,0),0) -> 0 | AM2: =ROUNDUP(IF(A2=0,0,IFERROR(VLOOKUP($A2,'[1]Donor''s Assigned Kilos'!A:O,16,0),0)),0) -> 0 | AN2: =IF(A2=0,0,IFERROR(SUMIFS([1]Population!Z:Z,[1]Population!J:J,'MASTER-2025'!A2),0)) -> 0 | AO2: =IFERROR(VLOOKUP($A2,'[1]Donor-Served OBs'!A:N,11,0),0) -> 0 | AP2: =ROUNDUP(IF(A2=0,0,IFERROR(VLOOKUP($A2,'[1]Donor''s Assigned Kilos'!A:N,13,0),0)),0) -> 0 | AQ2: =IF(A2=0,0,IFERROR(SUMIFS([1]Population!W:W,[1]Population!J:J,'MASTER-2025'!A2),0)) -> 0 | AR2: =IFERROR(VLOOKUP($A2,'[1]Donor-Served OBs'!A:N,5,0),0) -> 0 | AS2: =ROUNDUP(IF(A2=0,0,IFERROR(VLOOKUP($A2,'[1]Donor''s Assigned Kilos'!A:N,10,0),0)),0) -> 0 | AT2: =IF(A2=0,0,IFERROR(SUMIFS([1]Population!T:T,[1]Population!J:J,'MASTER-2025'!A2),0)) -> 0 | AU2: =IFERROR(VLOOKUP($A2,'[1]Donor-Served OBs'!A:N,13,0),0) -> 0 | AV2: =ROUNDUP(IF(A2=0,0,IFERROR(VLOOKUP($A2,'[1]Donor''s Assigned Kilos'!A:N,14,0),0)),0) -> 0 | AW2: =IF(A2=0,0,IFERROR(SUMIFS([1]Population!X:X,[1]Population!J:J,'MASTER-2025'!A2),0)) -> 0 | AX2: =IFERROR(VLOOKUP($A2,'[1]Donor-Served OBs'!A:N,16,0),0) -> 0 | AY2: =ROUNDUP(IF(A2=0,0,IFERROR(VLOOKUP($A2,'[1]Donor''s Assigned Kilos'!A:O,16,0),0)),0) -> 0 | AZ2: =IF(A2=0,0,IFERROR(SUMIFS([1]Population!Y:Y,[1]Population!J:J,'MASTER-2025'!A2),0)) -> 0 | BA2: =+H2+K2+N2+Q2+T2+W2+Z2+AC2+AF2+AI2+AL2+AO2+AR2+AU2+AX2 -> 0 | BB2: =INT(I2+L2+O2+R2+U2+X2+AA2+AD2+AG2+AJ2+AM2+AP2+AS2+AV2+AY2) -> 0 | BC2: =ROUND(I2+L2+O2+R2+U2,0) -> 0 | BD2: =IF(A2=0,0,(+J2+M2+P2+S2+V2+Y2+AB2+AE2+AH2+AK2+AN2+AQ2+AT2+AW2+AZ2)) -> 0 | BE2: =IF(A2=0,0,SUMIFS([1]Population!C:C,[1]Population!A:A,'MASTER-2025'!A2)) -> #VALUE! | BF2: =IF(A2=0,0,SUMIFS([1]Population!D:D,[1]Population!A:A,'MASTER-2025'!A2)) -> #VALUE! | BG2: =IF(A2=0,0,SUMIFS([1]Population!E:E,[1]Population!A:A,'MASTER-2025'!A2)) -> #VALUE! | BH2: =IF(A2=0,0,SUMIFS([1]Population!F:F,[1]Population!A:A,'MASTER-2025'!A2)) -> #VALUE! | BI2: =+BF2+BG2+BH2 -> #VALUE! | BJ2: =+BK2-BI2-BH2-BG2-BF2-BE2 -> #VALUE! | BK2: =IF(A2=0,0,SUMIFS([1]Population!G:G,[1]Population!A:A,'MASTER-2025'!A2)) -> #VALUE! | BL2: {=IFERROR(VLOOKUP(A2,'[1]Now-OB-kg-POB-25'!A:AQ,{3,4,5,6,7,8,9,10,11,12,13,14},0),0)} -> 60 | BM2: 53 | BN2: 88 | BO2: 0 | BP2: 0 | BQ2: 0 | BR2: 0 | BS2: 0 | BT2: 0 | BU2: 0 | BV2: 0 | BW2: 0 | BX2: =SUM(BL2:BW2) -> 201 | BY2: {=IFERROR(VLOOKUP(A2,'[1]Now-OB-kg-POB-25'!A:AQ,{17,18,19,20,21,22,23,24,25,26,27,28},0),0)} -> 6112 | BZ2: 752 | CA2: 2508 | CB2: 0 | CC2: 0 | CD2: 0 | CE2: 0 | CF2: 0 | CG2: 0 | CH2: 0 | CI2: 0 | CJ2: 0 | CK2: =SUM(BY2:CJ2) -> 9372 | CL2: {=IFERROR(VLOOKUP(A2,'[1]Now-OB-kg-POB-25'!A:AQ,{31,32,33,34,35,36,37,38,39,40,41,42},0),0)} -> 19341 | CM2: 16959 | CN2: 26002 | CO2: 0 | CP2: 0 | CQ2: 0 | CR2: 0 | CS2: 0 | CT2: 0 | CU2: 0 | CV2: 0 | CW2: 0 | CX2: =SUM(CL2:CW2) -> 62302 | CY2: =IF(A2=0,0,IFERROR(VLOOKUP(A2,'[1]Info Donantes'!C:F,2,0),"Sin Contacto")) -> Sin Contacto | CZ2: =IF(A2=0,0,IFERROR(VLOOKUP(A2,'[1]Info Donantes'!C:F,3,0),"Sin Correo")) -> Sin Correo | DA2: =IF(A2=0,0,IFERROR(VLOOKUP(A2,'[1]Info Donantes'!C:F,4,0),"Sin Telefono")) -> Sin Telefono | DB2: Traceability Report - - FEDURO AGENCIES
A3: ALIMENTOS CÁRNICOS DE PANAMA, S.A | B3: =INT(IFERROR(VLOOKUP(A3,'[1]Donor Summary'!C:F,3,0),0)) -> 0 | C3: =INT(ROUND(IFERROR(VLOOKUP(A3,'[1]Donor Summary'!C:F,4,0),0),1)) -> 0 | D3: =INT(ROUND(C3-B3,1)) -> 0 | E3: =IF(A3=0,"",TEXT((IFERROR(D3/C3,0)),"0.00%")) -> 0.00% | F3: =IF(A3=0,"",TEXT((IFERROR(B3/C3,0)),"0.0%")) -> 0.0% | G3: =INT(D3*3) -> 0 | I3: =IFERROR(VLOOKUP(A3,'[1]Lot All by Part'!T:Y,6,0),0) -> 0 | K3: =IFERROR(VLOOKUP($A3,'[1]Donor-Served OBs'!A:N,3,0),0) -> 0 | L3: =ROUNDUP(IF(A3=0,0,IFERROR(VLOOKUP($A3,'[1]Donor''s Assigned Kilos'!A:O,3,0),0)),0) -> 0 | M3: =IF(A3=0,0,IFERROR(SUMIFS([1]Population!M:M,[1]Population!J:J,'MASTER-2025'!A3),0)) -> 0 | N3: =IFERROR(VLOOKUP($A3,'[1]Donor-Served OBs'!A:N,4,0),0) -> 0 | O3: =ROUNDUP(IF(A3=0,0,IFERROR(VLOOKUP($A3,'[1]Donor''s Assigned Kilos'!A:O,4,0),0)),0) -> 0 | P3: =IF(A3=0,0,IFERROR(SUMIFS([1]Population!N:N,[1]Population!J:J,'MASTER-2025'!A3),0)) -> 0 | Q3: =IFERROR(VLOOKUP($A3,'[1]Donor-Served OBs'!A:N,2,0),0) -> 0 | R3: =ROUNDUP(ROUND(IF(A3=0,0,IFERROR(VLOOKUP($A3,'[1]Donor''s Assigned Kilos'!A:O,9,0),0)),1),0) -> 0 | S3: =IF(A3=0,0,IFERROR(SUMIFS([1]Population!S:S,[1]Population!J:J,'MASTER-2025'!A3),0)) -> 0 | T3: =IFERROR(VLOOKUP($A3,'[1]Donor-Served OBs'!A:N,12,0),0) -> 0 | U3: =ROUNDUP(IF(A3=0,0,IF(A3=0,0,IFERROR(VLOOKUP($A3,'[1]Donor''s Assigned Kilos'!A:O,7,0),0))),0) -> 0 | V3: =IF(A3=0,0,IFERROR(SUMIFS([1]Population!Q:Q,[1]Population!J:J,'MASTER-2025'!A3),0)) -> 0 | W3: =IFERROR(VLOOKUP($A3,'[1]Donor-Served OBs'!A:N,10,0),0) -> 0 | X3: =ROUNDUP(IF(A3=0,0,IFERROR(VLOOKUP($A3,'[1]Donor''s Assigned Kilos'!A:N,5,0),0)),0) -> 0 | Y3: =IF(A3=0,0,IFERROR(SUMIFS([1]Population!O:O,[1]Population!J:J,'MASTER-2025'!A3),0)) -> 0 | Z3: =IFERROR(VLOOKUP($A3,'[1]Donor-Served OBs'!A:N,6,0),0) -> 0 | AA3: =ROUNDUP(IF(A3=0,0,IFERROR(VLOOKUP($A3,'[1]Donor''s Assigned Kilos'!A:N,11,0),0)),0) -> 0 | AB3: =IF(A3=0,0,IFERROR(SUMIFS([1]Population!U:U,[1]Population!J:J,'MASTER-2025'!A3),0)) -> 0 | AC3: =IFERROR(VLOOKUP($A3,'[1]Donor-Served OBs'!A:N,7,0),0) -> 0 | AD3: =ROUNDUP(IF(A3=0,0,IFERROR(VLOOKUP($A3,'[1]Donor''s Assigned Kilos'!A:N,8,0),0)),0) -> 0 | AE3: =IF(A3=0,0,IFERROR(SUMIFS([1]Population!R:R,[1]Population!J:J,'MASTER-2025'!A3),0)) -> 0 | AF3: =IFERROR(VLOOKUP($A3,'[1]Donor-Served OBs'!A:N,8,0),0) -> 0 | AG3: =ROUNDUP(IF(A3=0,0,IFERROR(VLOOKUP($A3,'[1]Donor''s Assigned Kilos'!A:N,6,0),0)),0) -> 0 | AH3: =IF(A3=0,0,IFERROR(SUMIFS([1]Population!P:P,[1]Population!J:J,'MASTER-2025'!A3),0)) -> 0 | AI3: =IFERROR(VLOOKUP($A3,'[1]Donor-Served OBs'!A:N,9,0),0) -> 0 | AJ3: =ROUNDUP(IF(A3=0,0,IFERROR(VLOOKUP($A3,'[1]Donor''s Assigned Kilos'!A:N,12,0),0)),0) -> 0 | AK3: =IF(A3=0,0,IFERROR(SUMIFS([1]Population!V:V,[1]Population!J:J,'MASTER-2025'!A3),0)) -> 0 | AL3: =IFERROR(VLOOKUP($A3,'[1]Donor-Served OBs'!A:N,16,0),0) -> 0 | AM3: =ROUNDUP(IF(A3=0,0,IFERROR(VLOOKUP($A3,'[1]Donor''s Assigned Kilos'!A:O,16,0),0)),0) -> 0 | AN3: =IF(A3=0,0,IFERROR(SUMIFS([1]Population!Z:Z,[1]Population!J:J,'MASTER-2025'!A3),0)) -> 0 | AO3: =IFERROR(VLOOKUP($A3,'[1]Donor-Served OBs'!A:N,11,0),0) -> 0 | AP3: =ROUNDUP(IF(A3=0,0,IFERROR(VLOOKUP($A3,'[1]Donor''s Assigned Kilos'!A:N,13,0),0)),0) -> 0 | AQ3: =IF(A3=0,0,IFERROR(SUMIFS([1]Population!W:W,[1]Population!J:J,'MASTER-2025'!A3),0)) -> 0 | AR3: =IFERROR(VLOOKUP($A3,'[1]Donor-Served OBs'!A:N,5,0),0) -> 0 | AS3: =ROUNDUP(IF(A3=0,0,IFERROR(VLOOKUP($A3,'[1]Donor''s Assigned Kilos'!A:N,10,0),0)),0) -> 0 | AT3: =IF(A3=0,0,IFERROR(SUMIFS([1]Population!T:T,[1]Population!J:J,'MASTER-2025'!A3),0)) -> 0 | AU3: =IFERROR(VLOOKUP($A3,'[1]Donor-Served OBs'!A:N,13,0),0) -> 0 | AV3: =ROUNDUP(IF(A3=0,0,IFERROR(VLOOKUP($A3,'[1]Donor''s Assigned Kilos'!A:N,14,0),0)),0) -> 0 | AW3: =IF(A3=0,0,IFERROR(SUMIFS([1]Population!X:X,[1]Population!J:J,'MASTER-2025'!A3),0)) -> 0 | AX3: =IFERROR(VLOOKUP($A3,'[1]Donor-Served OBs'!A:N,16,0),0) -> 0 | AY3: =ROUNDUP(IF(A3=0,0,IFERROR(VLOOKUP($A3,'[1]Donor''s Assigned Kilos'!A:O,16,0),0)),0) -> 0 | AZ3: =IF(A3=0,0,IFERROR(SUMIFS([1]Population!Y:Y,[1]Population!J:J,'MASTER-2025'!A3),0)) -> 0 | BA3: =+H3+K3+N3+Q3+T3+W3+Z3+AC3+AF3+AI3+AL3+AO3+AR3+AU3+AX3 -> 0 | BB3: =INT(I3+L3+O3+R3+U3+X3+AA3+AD3+AG3+AJ3+AM3+AP3+AS3+AV3+AY3) -> 0 | BC3: =ROUND(I3+L3+O3+R3+U3,0) -> 0 | BD3: =IF(A3=0,0,(+J3+M3+P3+S3+V3+Y3+AB3+AE3+AH3+AK3+AN3+AQ3+AT3+AW3+AZ3)) -> 0 | BE3: =IF(A3=0,0,SUMIFS([1]Population!C:C,[1]Population!A:A,'MASTER-2025'!A3)) -> #VALUE! | BF3: =IF(A3=0,0,SUMIFS([1]Population!D:D,[1]Population!A:A,'MASTER-2025'!A3)) -> #VALUE! | BG3: =IF(A3=0,0,SUMIFS([1]Population!E:E,[1]Population!A:A,'MASTER-2025'!A3)) -> #VALUE! | BH3: =IF(A3=0,0,SUMIFS([1]Population!F:F,[1]Population!A:A,'MASTER-2025'!A3)) -> #VALUE! | BI3: =+BF3+BG3+BH3 -> #VALUE! | BJ3: =+BK3-BI3-BH3-BG3-BF3-BE3 -> #VALUE! | BK3: =IF(A3=0,0,SUMIFS([1]Population!G:G,[1]Population!A:A,'MASTER-2025'!A3)) -> #VALUE! | BL3: {=IFERROR(VLOOKUP(A3,'[1]Now-OB-kg-POB-25'!A:AQ,{3,4,5,6,7,8,9,10,11,12,13,14},0),0)} -> 34 | BM3: 0 | BN3: 13 | BO3: 0 | BP3: 0 | BQ3: 0 | BR3: 0 | BS3: 0 | BT3: 0 | BU3: 0 | BV3: 0 | BW3: 0 | BX3: =SUM(BL3:BW3) -> 47 | BY3: {=IFERROR(VLOOKUP(A3,'[1]Now-OB-kg-POB-25'!A:AQ,{17,18,19,20,21,22,23,24,25,26,27,28},0),0)} -> 1045 | BZ3: 0 | CA3: 108 | CB3: 0 | CC3: 0 | CD3: 0 | CE3: 0 | CF3: 0 | CG3: 0 | CH3: 0 | CI3: 0 | CJ3: 0 | CK3: =SUM(BY3:CJ3) -> 1153 | CL3: {=IFERROR(VLOOKUP(A3,'[1]Now-OB-kg-POB-25'!A:AQ,{31,32,33,34,35,36,37,38,39,40,41,42},0),0)} -> 11762 | CM3: 0 | CN3: 3455 | CO3: 0 | CP3: 0 | CQ3: 0 | CR3: 0 | CS3: 0 | CT3: 0 | CU3: 0 | CV3: 0 | CW3: 0 | CX3: =SUM(CL3:CW3) -> 15217 | CY3: =IF(A3=0,0,IFERROR(VLOOKUP(A3,'[1]Info Donantes'!C:F,2,0),"Sin Contacto")) -> Sin Contacto | CZ3: =IF(A3=0,0,IFERROR(VLOOKUP(A3,'[1]Info Donantes'!C:F,3,0),"Sin Correo")) -> Sin Correo | DA3: =IF(A3=0,0,IFERROR(VLOOKUP(A3,'[1]Info Donantes'!C:F,4,0),"Sin Telefono")) -> Sin Telefono | DB3: Traceability Report - - ALIMENTOS CÁRNICOS DE PANAMA, S.A
A4: ALIMENTOS NICO, S.A, (ANICSA) | B4: =INT(IFERROR(VLOOKUP(A4,'[1]Donor Summary'!C:F,3,0),0)) -> 0 | C4: =INT(ROUND(IFERROR(VLOOKUP(A4,'[1]Donor Summary'!C:F,4,0),0),1)) -> 0 | D4: =INT(ROUND(C4-B4,1)) -> 0 | E4: =IF(A4=0,"",TEXT((IFERROR(D4/C4,0)),"0.00%")) -> 0.00% | F4: =IF(A4=0,"",TEXT((IFERROR(B4/C4,0)),"0.0%")) -> 0.0% | G4: =INT(D4*3) -> 0 | I4: =IFERROR(VLOOKUP(A4,'[1]Lot All by Part'!T:Y,6,0),0) -> 0 | K4: =IFERROR(VLOOKUP($A4,'[1]Donor-Served OBs'!A:N,3,0),0) -> 0 | L4: =ROUNDUP(IF(A4=0,0,IFERROR(VLOOKUP($A4,'[1]Donor''s Assigned Kilos'!A:O,3,0),0)),0) -> 0 | M4: =IF(A4=0,0,IFERROR(SUMIFS([1]Population!M:M,[1]Population!J:J,'MASTER-2025'!A4),0)) -> 0 | N4: =IFERROR(VLOOKUP($A4,'[1]Donor-Served OBs'!A:N,4,0),0) -> 0 | O4: =ROUNDUP(IF(A4=0,0,IFERROR(VLOOKUP($A4,'[1]Donor''s Assigned Kilos'!A:O,4,0),0)),0) -> 0 | P4: =IF(A4=0,0,IFERROR(SUMIFS([1]Population!N:N,[1]Population!J:J,'MASTER-2025'!A4),0)) -> 0 | Q4: =IFERROR(VLOOKUP($A4,'[1]Donor-Served OBs'!A:N,2,0),0) -> 0 | R4: =ROUNDUP(ROUND(IF(A4=0,0,IFERROR(VLOOKUP($A4,'[1]Donor''s Assigned Kilos'!A:O,9,0),0)),1),0) -> 0 | S4: =IF(A4=0,0,IFERROR(SUMIFS([1]Population!S:S,[1]Population!J:J,'MASTER-2025'!A4),0)) -> 0 | T4: =IFERROR(VLOOKUP($A4,'[1]Donor-Served OBs'!A:N,12,0),0) -> 0 | U4: =ROUNDUP(IF(A4=0,0,IF(A4=0,0,IFERROR(VLOOKUP($A4,'[1]Donor''s Assigned Kilos'!A:O,7,0),0))),0) -> 0 | V4: =IF(A4=0,0,IFERROR(SUMIFS([1]Population!Q:Q,[1]Population!J:J,'MASTER-2025'!A4),0)) -> 0 | W4: =IFERROR(VLOOKUP($A4,'[1]Donor-Served OBs'!A:N,10,0),0) -> 0 | X4: =ROUNDUP(IF(A4=0,0,IFERROR(VLOOKUP($A4,'[1]Donor''s Assigned Kilos'!A:N,5,0),0)),0) -> 0 | Y4: =IF(A4=0,0,IFERROR(SUMIFS([1]Population!O:O,[1]Population!J:J,'MASTER-2025'!A4),0)) -> 0 | Z4: =IFERROR(VLOOKUP($A4,'[1]Donor-Served OBs'!A:N,6,0),0) -> 0 | AA4: =ROUNDUP(IF(A4=0,0,IFERROR(VLOOKUP($A4,'[1]Donor''s Assigned Kilos'!A:N,11,0),0)),0) -> 0 | AB4: =IF(A4=0,0,IFERROR(SUMIFS([1]Population!U:U,[1]Population!J:J,'MASTER-2025'!A4),0)) -> 0 | AC4: =IFERROR(VLOOKUP($A4,'[1]Donor-Served OBs'!A:N,7,0),0) -> 0 | AD4: =ROUNDUP(IF(A4=0,0,IFERROR(VLOOKUP($A4,'[1]Donor''s Assigned Kilos'!A:N,8,0),0)),0) -> 0 | AE4: =IF(A4=0,0,IFERROR(SUMIFS([1]Population!R:R,[1]Population!J:J,'MASTER-2025'!A4),0)) -> 0 | AF4: =IFERROR(VLOOKUP($A4,'[1]Donor-Served OBs'!A:N,8,0),0) -> 0 | AG4: =ROUNDUP(IF(A4=0,0,IFERROR(VLOOKUP($A4,'[1]Donor''s Assigned Kilos'!A:N,6,0),0)),0) -> 0 | AH4: =IF(A4=0,0,IFERROR(SUMIFS([1]Population!P:P,[1]Population!J:J,'MASTER-2025'!A4),0)) -> 0 | AI4: =IFERROR(VLOOKUP($A4,'[1]Donor-Served OBs'!A:N,9,0),0) -> 0 | AJ4: =ROUNDUP(IF(A4=0,0,IFERROR(VLOOKUP($A4,'[1]Donor''s Assigned Kilos'!A:N,12,0),0)),0) -> 0 | AK4: =IF(A4=0,0,IFERROR(SUMIFS([1]Population!V:V,[1]Population!J:J,'MASTER-2025'!A4),0)) -> 0 | AL4: =IFERROR(VLOOKUP($A4,'[1]Donor-Served OBs'!A:N,16,0),0) -> 0 | AM4: =ROUNDUP(IF(A4=0,0,IFERROR(VLOOKUP($A4,'[1]Donor''s Assigned Kilos'!A:O,16,0),0)),0) -> 0 | AN4: =IF(A4=0,0,IFERROR(SUMIFS([1]Population!Z:Z,[1]Population!J:J,'MASTER-2025'!A4),0)) -> 0 | AO4: =IFERROR(VLOOKUP($A4,'[1]Donor-Served OBs'!A:N,11,0),0) -> 0 | AP4: =ROUNDUP(IF(A4=0,0,IFERROR(VLOOKUP($A4,'[1]Donor''s Assigned Kilos'!A:N,13,0),0)),0) -> 0 | AQ4: =IF(A4=0,0,IFERROR(SUMIFS([1]Population!W:W,[1]Population!J:J,'MASTER-2025'!A4),0)) -> 0 | AR4: =IFERROR(VLOOKUP($A4,'[1]Donor-Served OBs'!A:N,5,0),0) -> 0 | AS4: =ROUNDUP(IF(A4=0,0,IFERROR(VLOOKUP($A4,'[1]Donor''s Assigned Kilos'!A:N,10,0),0)),0) -> 0 | AT4: =IF(A4=0,0,IFERROR(SUMIFS([1]Population!T:T,[1]Population!J:J,'MASTER-2025'!A4),0)) -> 0 | AU4: =IFERROR(VLOOKUP($A4,'[1]Donor-Served OBs'!A:N,13,0),0) -> 0 | AV4: =ROUNDUP(IF(A4=0,0,IFERROR(VLOOKUP($A4,'[1]Donor''s Assigned Kilos'!A:N,14,0),0)),0) -> 0 | AW4: =IF(A4=0,0,IFERROR(SUMIFS([1]Population!X:X,[1]Population!J:J,'MASTER-2025'!A4),0)) -> 0 | AX4: =IFERROR(VLOOKUP($A4,'[1]Donor-Served OBs'!A:N,16,0),0) -> 0 | AY4: =ROUNDUP(IF(A4=0,0,IFERROR(VLOOKUP($A4,'[1]Donor''s Assigned Kilos'!A:O,16,0),0)),0) -> 0 | AZ4: =IF(A4=0,0,IFERROR(SUMIFS([1]Population!Y:Y,[1]Population!J:J,'MASTER-2025'!A4),0)) -> 0 | BA4: =+H4+K4+N4+Q4+T4+W4+Z4+AC4+AF4+AI4+AL4+AO4+AR4+AU4+AX4 -> 0 | BB4: =INT(I4+L4+O4+R4+U4+X4+AA4+AD4+AG4+AJ4+AM4+AP4+AS4+AV4+AY4) -> 0 | BC4: =ROUND(I4+L4+O4+R4+U4,0) -> 0 | BD4: =IF(A4=0,0,(+J4+M4+P4+S4+V4+Y4+AB4+AE4+AH4+AK4+AN4+AQ4+AT4+AW4+AZ4)) -> 0 | BE4: =IF(A4=0,0,SUMIFS([1]Population!C:C,[1]Population!A:A,'MASTER-2025'!A4)) -> #VALUE! | BF4: =IF(A4=0,0,SUMIFS([1]Population!D:D,[1]Population!A:A,'MASTER-2025'!A4)) -> #VALUE! | BG4: =IF(A4=0,0,SUMIFS([1]Population!E:E,[1]Population!A:A,'MASTER-2025'!A4)) -> #VALUE! | BH4: =IF(A4=0,0,SUMIFS([1]Population!F:F,[1]Population!A:A,'MASTER-2025'!A4)) -> #VALUE! | BI4: =+BF4+BG4+BH4 -> #VALUE! | BJ4: =+BK4-BI4-BH4-BG4-BF4-BE4 -> #VALUE! | BK4: =IF(A4=0,0,SUMIFS([1]Population!G:G,[1]Population!A:A,'MASTER-2025'!A4)) -> #VALUE! | BL4: {=IFERROR(VLOOKUP(A4,'[1]Now-OB-kg-POB-25'!A:AQ,{3,4,5,6,7,8,9,10,11,12,13,14},0),0)} -> 0 | BM4: 0 | BN4: 0 | BO4: 0 | BP4: 0 | BQ4: 0 | BR4: 0 | BS4: 0 | BT4: 0 | BU4: 0 | BV4: 0 | BW4: 0 | BX4: =SUM(BL4:BW4) -> 0 | BY4: {=IFERROR(VLOOKUP(A4,'[1]Now-OB-kg-POB-25'!A:AQ,{17,18,19,20,21,22,23,24,25,26,27,28},0),0)} -> 0 | BZ4: 0 | CA4: 0 | CB4: 0 | CC4: 0 | CD4: 0 | CE4: 0 | CF4: 0 | CG4: 0 | CH4: 0 | CI4: 0 | CJ4: 0 | CK4: =SUM(BY4:CJ4) -> 0 | CL4: {=IFERROR(VLOOKUP(A4,'[1]Now-OB-kg-POB-25'!A:AQ,{31,32,33,34,35,36,37,38,39,40,41,42},0),0)} -> 0 | CM4: 0 | CN4: 0 | CO4: 0 | CP4: 0 | CQ4: 0 | CR4: 0 | CS4: 0 | CT4: 0 | CU4: 0 | CV4: 0 | CW4: 0 | CX4: =SUM(CL4:CW4) -> 0 | CY4: =IF(A4=0,0,IFERROR(VLOOKUP(A4,'[1]Info Donantes'!C:F,2,0),"Sin Contacto")) -> David Yanguez | CZ4: =IF(A4=0,0,IFERROR(VLOOKUP(A4,'[1]Info Donantes'!C:F,3,0),"Sin Correo")) -> cafe.don.tino@hotmail.com | DA4: =IF(A4=0,0,IFERROR(VLOOKUP(A4,'[1]Info Donantes'!C:F,4,0),"Sin Telefono")) -> 851 0138 | DB4: Traceability Report - - ALIMENTOS NICO, S.A, (ANICSA)
A5: Bienes y Raices Metalicas S.A. | B5: =INT(IFERROR(VLOOKUP(A5,'[1]Donor Summary'!C:F,3,0),0)) -> 0 | C5: =INT(ROUND(IFERROR(VLOOKUP(A5,'[1]Donor Summary'!C:F,4,0),0),1)) -> 45 | D5: =INT(ROUND(C5-B5,1)) -> 45 | E5: =IF(A5=0,"",TEXT((IFERROR(D5/C5,0)),"0.00%")) -> 100.00% | F5: =IF(A5=0,"",TEXT((IFERROR(B5/C5,0)),"0.0%")) -> 0.0% | G5: =INT(D5*3) -> 135 | I5: =IFERROR(VLOOKUP(A5,'[1]Lot All by Part'!T:Y,6,0),0) -> 0 | K5: =IFERROR(VLOOKUP($A5,'[1]Donor-Served OBs'!A:N,3,0),0) -> 0 | L5: =ROUNDUP(IF(A5=0,0,IFERROR(VLOOKUP($A5,'[1]Donor''s Assigned Kilos'!A:O,3,0),0)),0) -> 0 | M5: =IF(A5=0,0,IFERROR(SUMIFS([1]Population!M:M,[1]Population!J:J,'MASTER-2025'!A5),0)) -> 0 | N5: =IFERROR(VLOOKUP($A5,'[1]Donor-Served OBs'!A:N,4,0),0) -> 0 | O5: =ROUNDUP(IF(A5=0,0,IFERROR(VLOOKUP($A5,'[1]Donor''s Assigned Kilos'!A:O,4,0),0)),0) -> 0 | P5: =IF(A5=0,0,IFERROR(SUMIFS([1]Population!N:N,[1]Population!J:J,'MASTER-2025'!A5),0)) -> 0 | Q5: =IFERROR(VLOOKUP($A5,'[1]Donor-Served OBs'!A:N,2,0),0) -> 0 | R5: =ROUNDUP(ROUND(IF(A5=0,0,IFERROR(VLOOKUP($A5,'[1]Donor''s Assigned Kilos'!A:O,9,0),0)),1),0) -> 0 | S5: =IF(A5=0,0,IFERROR(SUMIFS([1]Population!S:S,[1]Population!J:J,'MASTER-2025'!A5),0)) -> 0 | T5: =IFERROR(VLOOKUP($A5,'[1]Donor-Served OBs'!A:N,12,0),0) -> 0 | U5: =ROUNDUP(IF(A5=0,0,IF(A5=0,0,IFERROR(VLOOKUP($A5,'[1]Donor''s Assigned Kilos'!A:O,7,0),0))),0) -> 0 | V5: =IF(A5=0,0,IFERROR(SUMIFS([1]Population!Q:Q,[1]Population!J:J,'MASTER-2025'!A5),0)) -> 0 | W5: =IFERROR(VLOOKUP($A5,'[1]Donor-Served OBs'!A:N,10,0),0) -> 0 | X5: =ROUNDUP(IF(A5=0,0,IFERROR(VLOOKUP($A5,'[1]Donor''s Assigned Kilos'!A:N,5,0),0)),0) -> 0 | Y5: =IF(A5=0,0,IFERROR(SUMIFS([1]Population!O:O,[1]Population!J:J,'MASTER-2025'!A5),0)) -> 0 | Z5: =IFERROR(VLOOKUP($A5,'[1]Donor-Served OBs'!A:N,6,0),0) -> 1 | AA5: =ROUNDUP(IF(A5=0,0,IFERROR(VLOOKUP($A5,'[1]Donor''s Assigned Kilos'!A:N,11,0),0)),0) -> 3 | AB5: =IF(A5=0,0,IFERROR(SUMIFS([1]Population!U:U,[1]Population!J:J,'MASTER-2025'!A5),0)) -> 0 | AC5: =IFERROR(VLOOKUP($A5,'[1]Donor-Served OBs'!A:N,7,0),0) -> 0 | AD5: =ROUNDUP(IF(A5=0,0,IFERROR(VLOOKUP($A5,'[1]Donor''s Assigned Kilos'!A:N,8,0),0)),0) -> 0 | AE5: =IF(A5=0,0,IFERROR(SUMIFS([1]Population!R:R,[1]Population!J:J,'MASTER-2025'!A5),0)) -> 0 | AF5: =IFERROR(VLOOKUP($A5,'[1]Donor-Served OBs'!A:N,8,0),0) -> 0 | AG5: =ROUNDUP(IF(A5=0,0,IFERROR(VLOOKUP($A5,'[1]Donor''s Assigned Kilos'!A:N,6,0),0)),0) -> 0 | AH5: =IF(A5=0,0,IFERROR(SUMIFS([1]Population!P:P,[1]Population!J:J,'MASTER-2025'!A5),0)) -> 0 | AI5: =IFERROR(VLOOKUP($A5,'[1]Donor-Served OBs'!A:N,9,0),0) -> 1 | AJ5: =ROUNDUP(IF(A5=0,0,IFERROR(VLOOKUP($A5,'[1]Donor''s Assigned Kilos'!A:N,12,0),0)),0) -> 3 | AK5: =IF(A5=0,0,IFERROR(SUMIFS([1]Population!V:V,[1]Population!J:J,'MASTER-2025'!A5),0)) -> 0 | AL5: =IFERROR(VLOOKUP($A5,'[1]Donor-Served OBs'!A:N,16,0),0) -> 0 | AM5: =ROUNDUP(IF(A5=0,0,IFERROR(VLOOKUP($A5,'[1]Donor''s Assigned Kilos'!A:O,16,0),0)),0) -> 0 | AN5: =IF(A5=0,0,IFERROR(SUMIFS([1]Population!Z:Z,[1]Population!J:J,'MASTER-2025'!A5),0)) -> 0 | AO5: =IFERROR(VLOOKUP($A5,'[1]Donor-Served OBs'!A:N,11,0),0) -> 0 | AP5: =ROUNDUP(IF(A5=0,0,IFERROR(VLOOKUP($A5,'[1]Donor''s Assigned Kilos'!A:N,13,0),0)),0) -> 0 | AQ5: =IF(A5=0,0,IFERROR(SUMIFS([1]Population!W:W,[1]Population!J:J,'MASTER-2025'!A5),0)) -> 0 | AR5: =IFERROR(VLOOKUP($A5,'[1]Donor-Served OBs'!A:N,5,0),0) -> 0 | AS5: =ROUNDUP(IF(A5=0,0,IFERROR(VLOOKUP($A5,'[1]Donor''s Assigned Kilos'!A:N,10,0),0)),0) -> 0 | AT5: =IF(A5=0,0,IFERROR(SUMIFS([1]Population!T:T,[1]Population!J:J,'MASTER-2025'!A5),0)) -> 0 | AU5: =IFERROR(VLOOKUP($A5,'[1]Donor-Served OBs'!A:N,13,0),0) -> 0 | AV5: =ROUNDUP(IF(A5=0,0,IFERROR(VLOOKUP($A5,'[1]Donor''s Assigned Kilos'!A:N,14,0),0)),0) -> 0 | AW5: =IF(A5=0,0,IFERROR(SUMIFS([1]Population!X:X,[1]Population!J:J,'MASTER-2025'!A5),0)) -> 0 | AX5: =IFERROR(VLOOKUP($A5,'[1]Donor-Served OBs'!A:N,16,0),0) -> 0 | AY5: =ROUNDUP(IF(A5=0,0,IFERROR(VLOOKUP($A5,'[1]Donor''s Assigned Kilos'!A:O,16,0),0)),0) -> 0 | AZ5: =IF(A5=0,0,IFERROR(SUMIFS([1]Population!Y:Y,[1]Population!J:J,'MASTER-2025'!A5),0)) -> 0 | BA5: =+H5+K5+N5+Q5+T5+W5+Z5+AC5+AF5+AI5+AL5+AO5+AR5+AU5+AX5 -> 2 | BB5: =INT(I5+L5+O5+R5+U5+X5+AA5+AD5+AG5+AJ5+AM5+AP5+AS5+AV5+AY5) -> 6 | BC5: =ROUND(I5+L5+O5+R5+U5,0) -> 0 | BD5: =IF(A5=0,0,(+J5+M5+P5+S5+V5+Y5+AB5+AE5+AH5+AK5+AN5+AQ5+AT5+AW5+AZ5)) -> 0 | BE5: =IF(A5=0,0,SUMIFS([1]Population!C:C,[1]Population!A:A,'MASTER-2025'!A5)) -> #VALUE! | BF5: =IF(A5=0,0,SUMIFS([1]Population!D:D,[1]Population!A:A,'MASTER-2025'!A5)) -> #VALUE! | BG5: =IF(A5=0,0,SUMIFS([1]Population!E:E,[1]Population!A:A,'MASTER-2025'!A5)) -> #VALUE! | BH5: =IF(A5=0,0,SUMIFS([1]Population!F:F,[1]Population!A:A,'MASTER-2025'!A5)) -> #VALUE! | BI5: =+BF5+BG5+BH5 -> #VALUE! | BJ5: =+BK5-BI5-BH5-BG5-BF5-BE5 -> #VALUE! | BK5: =IF(A5=0,0,SUMIFS([1]Population!G:G,[1]Population!A:A,'MASTER-2025'!A5)) -> #VALUE! | BL5: {=IFERROR(VLOOKUP(A5,'[1]Now-OB-kg-POB-25'!A:AQ,{3,4,5,6,7,8,9,10,11,12,13,14},0),0)} -> 0 | BM5: 3 | BN5: 2 | BO5: 0 | BP5: 0 | BQ5: 0 | BR5: 0 | BS5: 0 | BT5: 0 | BU5: 0 | BV5: 0 | BW5: 0 | BX5: =SUM(BL5:BW5) -> 5 | BY5: {=IFERROR(VLOOKUP(A5,'[1]Now-OB-kg-POB-25'!A:AQ,{17,18,19,20,21,22,23,24,25,26,27,28},0),0)} -> 45 | BZ5: 45 | CA5: 45 | CB5: 0 | CC5: 0 | CD5: 0 | CE5: 0 | CF5: 0 | CG5: 0 | CH5: 0 | CI5: 0 | CJ5: 0 | CK5: =SUM(BY5:CJ5) -> 135 | CL5: {=IFERROR(VLOOKUP(A5,'[1]Now-OB-kg-POB-25'!A:AQ,{31,32,33,34,35,36,37,38,39,40,41,42},0),0)} -> 0 | CM5: 333 | CN5: 340 | CO5: 0 | CP5: 0 | CQ5: 0 | CR5: 0 | CS5: 0 | CT5: 0 | CU5: 0 | CV5: 0 | CW5: 0 | CX5: =SUM(CL5:CW5) -> 673 | CY5: =IF(A5=0,0,IFERROR(VLOOKUP(A5,'[1]Info Donantes'!C:F,2,0),"Sin Contacto")) -> Jose Tello | CZ5: =IF(A5=0,0,IFERROR(VLOOKUP(A5,'[1]Info Donantes'!C:F,3,0),"Sin Correo")) -> tmj1929@hotmail.com | DA5: =IF(A5=0,0,IFERROR(VLOOKUP(A5,'[1]Info Donantes'!C:F,4,0),"Sin Telefono")) -> 6675-0897 | DB5: Traceability Report - - Bienes y Raices Metalicas S.A.
A6: NATIONAL BREWERY | B6: =INT(IFERROR(VLOOKUP(A6,'[1]Donor Summary'!C:F,3,0),0)) -> 0 | C6: =INT(ROUND(IFERROR(VLOOKUP(A6,'[1]Donor Summary'!C:F,4,0),0),1)) -> 0 | D6: =INT(ROUND(C6-B6,1)) -> 0 | E6: =IF(A6=0,"",TEXT((IFERROR(D6/C6,0)),"0.00%")) -> 0.00% | F6: =IF(A6=0,"",TEXT((IFERROR(B6/C6,0)),"0.0%")) -> 0.0% | G6: =INT(D6*3) -> 0 | I6: =IFERROR(VLOOKUP(A6,'[1]Lot All by Part'!T:Y,6,0),0) -> 0 | K6: =IFERROR(VLOOKUP($A6,'[1]Donor-Served OBs'!A:N,3,0),0) -> 0 | L6: =ROUNDUP(IF(A6=0,0,IFERROR(VLOOKUP($A6,'[1]Donor''s Assigned Kilos'!A:O,3,0),0)),0) -> 0 | M6: =IF(A6=0,0,IFERROR(SUMIFS([1]Population!M:M,[1]Population!J:J,'MASTER-2025'!A6),0)) -> 0 | N6: =IFERROR(VLOOKUP($A6,'[1]Donor-Served OBs'!A:N,4,0),0) -> 0 | O6: =ROUNDUP(IF(A6=0,0,IFERROR(VLOOKUP($A6,'[1]Donor''s Assigned Kilos'!A:O,4,0),0)),0) -> 0 | P6: =IF(A6=0,0,IFERROR(SUMIFS([1]Population!N:N,[1]Population!J:J,'MASTER-2025'!A6),0)) -> 0 | Q6: =IFERROR(VLOOKUP($A6,'[1]Donor-Served OBs'!A:N,2,0),0) -> 0 | R6: =ROUNDUP(ROUND(IF(A6=0,0,IFERROR(VLOOKUP($A6,'[1]Donor''s Assigned Kilos'!A:O,9,0),0)),1),0) -> 0 | S6: =IF(A6=0,0,IFERROR(SUMIFS([1]Population!S:S,[1]Population!J:J,'MASTER-2025'!A6),0)) -> 0 | T6: =IFERROR(VLOOKUP($A6,'[1]Donor-Served OBs'!A:N,12,0),0) -> 0 | U6: =ROUNDUP(IF(A6=0,0,IF(A6=0,0,IFERROR(VLOOKUP($A6,'[1]Donor''s Assigned Kilos'!A:O,7,0),0))),0) -> 0 | V6: =IF(A6=0,0,IFERROR(SUMIFS([1]Population!Q:Q,[1]Population!J:J,'MASTER-2025'!A6),0)) -> 0 | W6: =IFERROR(VLOOKUP($A6,'[1]Donor-Served OBs'!A:N,10,0),0) -> 0 | X6: =ROUNDUP(IF(A6=0,0,IFERROR(VLOOKUP($A6,'[1]Donor''s Assigned Kilos'!A:N,5,0),0)),0) -> 0 | Y6: =IF(A6=0,0,IFERROR(SUMIFS([1]Population!O:O,[1]Population!J:J,'MASTER-2025'!A6),0)) -> 0 | Z6: =IFERROR(VLOOKUP($A6,'[1]Donor-Served OBs'!A:N,6,0),0) -> 0 | AA6: =ROUNDUP(IF(A6=0,0,IFERROR(VLOOKUP($A6,'[1]Donor''s Assigned Kilos'!A:N,11,0),0)),0) -> 0 | AB6: =IF(A6=0,0,IFERROR(SUMIFS([1]Population!U:U,[1]Population!J:J,'MASTER-2025'!A6),0)) -> 0 | AC6: =IFERROR(VLOOKUP($A6,'[1]Donor-Served OBs'!A:N,7,0),0) -> 0 | AD6: =ROUNDUP(IF(A6=0,0,IFERROR(VLOOKUP($A6,'[1]Donor''s Assigned Kilos'!A:N,8,0),0)),0) -> 0 | AE6: =IF(A6=0,0,IFERROR(SUMIFS([1]Population!R:R,[1]Population!J:J,'MASTER-2025'!A6),0)) -> 0 | AF6: =IFERROR(VLOOKUP($A6,'[1]Donor-Served OBs'!A:N,8,0),0) -> 0 | AG6: =ROUNDUP(IF(A6=0,0,IFERROR(VLOOKUP($A6,'[1]Donor''s Assigned Kilos'!A:N,6,0),0)),0) -> 0 | AH6: =IF(A6=0,0,IFERROR(SUMIFS([1]Population!P:P,[1]Population!J:J,'MASTER-2025'!A6),0)) -> 0 | AI6: =IFERROR(VLOOKUP($A6,'[1]Donor-Served OBs'!A:N,9,0),0) -> 0 | AJ6: =ROUNDUP(IF(A6=0,0,IFERROR(VLOOKUP($A6,'[1]Donor''s Assigned Kilos'!A:N,12,0),0)),0) -> 0 | AK6: =IF(A6=0,0,IFERROR(SUMIFS([1]Population!V:V,[1]Population!J:J,'MASTER-2025'!A6),0)) -> 0 | AL6: =IFERROR(VLOOKUP($A6,'[1]Donor-Served OBs'!A:N,16,0),0) -> 0 | AM6: =ROUNDUP(IF(A6=0,0,IFERROR(VLOOKUP($A6,'[1]Donor''s Assigned Kilos'!A:O,16,0),0)),0) -> 0 | AN6: =IF(A6=0,0,IFERROR(SUMIFS([1]Population!Z:Z,[1]Population!J:J,'MASTER-2025'!A6),0)) -> 0 | AO6: =IFERROR(VLOOKUP($A6,'[1]Donor-Served OBs'!A:N,11,0),0) -> 0 | AP6: =ROUNDUP(IF(A6=0,0,IFERROR(VLOOKUP($A6,'[1]Donor''s Assigned Kilos'!A:N,13,0),0)),0) -> 0 | AQ6: =IF(A6=0,0,IFERROR(SUMIFS([1]Population!W:W,[1]Population!J:J,'MASTER-2025'!A6),0)) -> 0 | AR6: =IFERROR(VLOOKUP($A6,'[1]Donor-Served OBs'!A:N,5,0),0) -> 0 | AS6: =ROUNDUP(IF(A6=0,0,IFERROR(VLOOKUP($A6,'[1]Donor''s Assigned Kilos'!A:N,10,0),0)),0) -> 0 | AT6: =IF(A6=0,0,IFERROR(SUMIFS([1]Population!T:T,[1]Population!J:J,'MASTER-2025'!A6),0)) -> 0 | AU6: =IFERROR(VLOOKUP($A6,'[1]Donor-Served OBs'!A:N,13,0),0) -> 0 | AV6: =ROUNDUP(IF(A6=0,0,IFERROR(VLOOKUP($A6,'[1]Donor''s Assigned Kilos'!A:N,14,0),0)),0) -> 0 | AW6: =IF(A6=0,0,IFERROR(SUMIFS([1]Population!X:X,[1]Population!J:J,'MASTER-2025'!A6),0)) -> 0 | AX6: =IFERROR(VLOOKUP($A6,'[1]Donor-Served OBs'!A:N,16,0),0) -> 0 | AY6: =ROUNDUP(IF(A6=0,0,IFERROR(VLOOKUP($A6,'[1]Donor''s Assigned Kilos'!A:O,16,0),0)),0) -> 0 | AZ6: =IF(A6=0,0,IFERROR(SUMIFS([1]Population!Y:Y,[1]Population!J:J,'MASTER-2025'!A6),0)) -> 0 | BA6: =+H6+K6+N6+Q6+T6+W6+Z6+AC6+AF6+AI6+AL6+AO6+AR6+AU6+AX6 -> 0 | BB6: =INT(I6+L6+O6+R6+U6+X6+AA6+AD6+AG6+AJ6+AM6+AP6+AS6+AV6+AY6) -> 0 | BC6: =ROUND(I6+L6+O6+R6+U6,0) -> 0 | BD6: =IF(A6=0,0,(+J6+M6+P6+S6+V6+Y6+AB6+AE6+AH6+AK6+AN6+AQ6+AT6+AW6+AZ6)) -> 0 | BE6: =IF(A6=0,0,SUMIFS([1]Population!C:C,[1]Population!A:A,'MASTER-2025'!A6)) -> #VALUE! | BF6: =IF(A6=0,0,SUMIFS([1]Population!D:D,[1]Population!A:A,'MASTER-2025'!A6)) -> #VALUE! | BG6: =IF(A6=0,0,SUMIFS([1]Population!E:E,[1]Population!A:A,'MASTER-2025'!A6)) -> #VALUE! | BH6: =IF(A6=0,0,SUMIFS([1]Population!F:F,[1]Population!A:A,'MASTER-2025'!A6)) -> #VALUE! | BI6: =+BF6+BG6+BH6 -> #VALUE! | BJ6: =+BK6-BI6-BH6-BG6-BF6-BE6 -> #VALUE! | BK6: =IF(A6=0,0,SUMIFS([1]Population!G:G,[1]Population!A:A,'MASTER-2025'!A6)) -> #VALUE! | BL6: {=IFERROR(VLOOKUP(A6,'[1]Now-OB-kg-POB-25'!A:AQ,{3,4,5,6,7,8,9,10,11,12,13,14},0),0)} -> 0 | BM6: 0 | BN6: 0 | BO6: 0 | BP6: 0 | BQ6: 0 | BR6: 0 | BS6: 0 | BT6: 0 | BU6: 0 | BV6: 0 | BW6: 0 | BX6: =SUM(BL6:BW6) -> 0 | BY6: {=IFERROR(VLOOKUP(A6,'[1]Now-OB-kg-POB-25'!A:AQ,{17,18,19,20,21,22,23,24,25,26,27,28},0),0)} -> 0 | BZ6: 0 | CA6: 0 | CB6: 0 | CC6: 0 | CD6: 0 | CE6: 0 | CF6: 0 | CG6: 0 | CH6: 0 | CI6: 0 | CJ6: 0 | CK6: =SUM(BY6:CJ6) -> 0 | CL6: {=IFERROR(VLOOKUP(A6,'[1]Now-OB-kg-POB-25'!A:AQ,{31,32,33,34,35,36,37,38,39,40,41,42},0),0)} -> 0 | CM6: 0 | CN6: 0 | CO6: 0 | CP6: 0 | CQ6: 0 | CR6: 0 | CS6: 0 | CT6: 0 | CU6: 0 | CV6: 0 | CW6: 0 | CX6: =SUM(CL6:CW6) -> 0 | CY6: =IF(A6=0,0,IFERROR(VLOOKUP(A6,'[1]Info Donantes'!C:F,2,0),"Sin Contacto")) -> Sin Contacto | CZ6: =IF(A6=0,0,IFERROR(VLOOKUP(A6,'[1]Info Donantes'!C:F,3,0),"Sin Correo")) -> Sin Correo | DA6: =IF(A6=0,0,IFERROR(VLOOKUP(A6,'[1]Info Donantes'!C:F,4,0),"Sin Telefono")) -> Sin Telefono | DB6: Traceability Report - - NATIONAL BREWERY
A7: KOL SHEARITH ISRAEL BROTHERHOOD CONGREGATION | B7: =INT(IFERROR(VLOOKUP(A7,'[1]Donor Summary'!C:F,3,0),0)) -> 0 | C7: =INT(ROUND(IFERROR(VLOOKUP(A7,'[1]Donor Summary'!C:F,4,0),0),1)) -> 0 | D7: =INT(ROUND(C7-B7,1)) -> 0 | E7: =IF(A7=0,"",TEXT((IFERROR(D7/C7,0)),"0.00%")) -> 0.00% | F7: =IF(A7=0,"",TEXT((IFERROR(B7/C7,0)),"0.0%")) -> 0.0% | G7: =INT(D7*3) -> 0 | I7: =IFERROR(VLOOKUP(A7,'[1]Lot All by Part'!T:Y,6,0),0) -> 0 | K7: =IFERROR(VLOOKUP($A7,'[1]Donor-Served OBs'!A:N,3,0),0) -> 0 | L7: =ROUNDUP(IF(A7=0,0,IFERROR(VLOOKUP($A7,'[1]Donor''s Assigned Kilos'!A:O,3,0),0)),0) -> 0 | M7: =IF(A7=0,0,IFERROR(SUMIFS([1]Population!M:M,[1]Population!J:J,'MASTER-2025'!A7),0)) -> 0 | N7: =IFERROR(VLOOKUP($A7,'[1]Donor-Served OBs'!A:N,4,0),0) -> 0 | O7: =ROUNDUP(IF(A7=0,0,IFERROR(VLOOKUP($A7,'[1]Donor''s Assigned Kilos'!A:O,4,0),0)),0) -> 0 | P7: =IF(A7=0,0,IFERROR(SUMIFS([1]Population!N:N,[1]Population!J:J,'MASTER-2025'!A7),0)) -> 0 | Q7: =IFERROR(VLOOKUP($A7,'[1]Donor-Served OBs'!A:N,2,0),0) -> 0 | R7: =ROUNDUP(ROUND(IF(A7=0,0,IFERROR(VLOOKUP($A7,'[1]Donor''s Assigned Kilos'!A:O,9,0),0)),1),0) -> 0 | S7: =IF(A7=0,0,IFERROR(SUMIFS([1]Population!S:S,[1]Population!J:J,'MASTER-2025'!A7),0)) -> 0 | T7: =IFERROR(VLOOKUP($A7,'[1]Donor-Served OBs'!A:N,12,0),0) -> 0 | U7: =ROUNDUP(IF(A7=0,0,IF(A7=0,0,IFERROR(VLOOKUP($A7,'[1]Donor''s Assigned Kilos'!A:O,7,0),0))),0) -> 0 | V7: =IF(A7=0,0,IFERROR(SUMIFS([1]Population!Q:Q,[1]Population!J:J,'MASTER-2025'!A7),0)) -> 0 | W7: =IFERROR(VLOOKUP($A7,'[1]Donor-Served OBs'!A:N,10,0),0) -> 0 | X7: =ROUNDUP(IF(A7=0,0,IFERROR(VLOOKUP($A7,'[1]Donor''s Assigned Kilos'!A:N,5,0),0)),0) -> 0 | Y7: =IF(A7=0,0,IFERROR(SUMIFS([1]Population!O:O,[1]Population!J:J,'MASTER-2025'!A7),0)) -> 0 | Z7: =IFERROR(VLOOKUP($A7,'[1]Donor-Served OBs'!A:N,6,0),0) -> 0 | AA7: =ROUNDUP(IF(A7=0,0,IFERROR(VLOOKUP($A7,'[1]Donor''s Assigned Kilos'!A:N,11,0),0)),0) -> 0 | AB7: =IF(A7=0,0,IFERROR(SUMIFS([1]Population!U:U,[1]Population!J:J,'MASTER-2025'!A7),0)) -> 0 | AC7: =IFERROR(VLOOKUP($A7,'[1]Donor-Served OBs'!A:N,7,0),0) -> 0 | AD7: =ROUNDUP(IF(A7=0,0,IFERROR(VLOOKUP($A7,'[1]Donor''s Assigned Kilos'!A:N,8,0),0)),0) -> 0 | AE7: =IF(A7=0,0,IFERROR(SUMIFS([1]Population!R:R,[1]Population!J:J,'MASTER-2025'!A7),0)) -> 0 | AF7: =IFERROR(VLOOKUP($A7,'[1]Donor-Served OBs'!A:N,8,0),0) -> 0 | AG7: =ROUNDUP(IF(A7=0,0,IFERROR(VLOOKUP($A7,'[1]Donor''s Assigned Kilos'!A:N,6,0),0)),0) -> 0 | AH7: =IF(A7=0,0,IFERROR(SUMIFS([1]Population!P:P,[1]Population!J:J,'MASTER-2025'!A7),0)) -> 0 | AI7: =IFERROR(VLOOKUP($A7,'[1]Donor-Served OBs'!A:N,9,0),0) -> 0 | AJ7: =ROUNDUP(IF(A7=0,0,IFERROR(VLOOKUP($A7,'[1]Donor''s Assigned Kilos'!A:N,12,0),0)),0) -> 0 | AK7: =IF(A7=0,0,IFERROR(SUMIFS([1]Population!V:V,[1]Population!J:J,'MASTER-2025'!A7),0)) -> 0 | AL7: =IFERROR(VLOOKUP($A7,'[1]Donor-Served OBs'!A:N,16,0),0) -> 0 | AM7: =ROUNDUP(IF(A7=0,0,IFERROR(VLOOKUP($A7,'[1]Donor''s Assigned Kilos'!A:O,16,0),0)),0) -> 0 | AN7: =IF(A7=0,0,IFERROR(SUMIFS([1]Population!Z:Z,[1]Population!J:J,'MASTER-2025'!A7),0)) -> 0 | AO7: =IFERROR(VLOOKUP($A7,'[1]Donor-Served OBs'!A:N,11,0),0) -> 0 | AP7: =ROUNDUP(IF(A7=0,0,IFERROR(VLOOKUP($A7,'[1]Donor''s Assigned Kilos'!A:N,13,0),0)),0) -> 0 | AQ7: =IF(A7=0,0,IFERROR(SUMIFS([1]Population!W:W,[1]Population!J:J,'MASTER-2025'!A7),0)) -> 0 | AR7: =IFERROR(VLOOKUP($A7,'[1]Donor-Served OBs'!A:N,5,0),0) -> 0 | AS7: =ROUNDUP(IF(A7=0,0,IFERROR(VLOOKUP($A7,'[1]Donor''s Assigned Kilos'!A:N,10,0),0)),0) -> 0 | AT7: =IF(A7=0,0,IFERROR(SUMIFS([1]Population!T:T,[1]Population!J:J,'MASTER-2025'!A7),0)) -> 0 | AU7: =IFERROR(VLOOKUP($A7,'[1]Donor-Served OBs'!A:N,13,0),0) -> 0 | AV7: =ROUNDUP(IF(A7=0,0,IFERROR(VLOOKUP($A7,'[1]Donor''s Assigned Kilos'!A:N,14,0),0)),0) -> 0 | AW7: =IF(A7=0,0,IFERROR(SUMIFS([1]Population!X:X,[1]Population!J:J,'MASTER-2025'!A7),0)) -> 0 | AX7: =IFERROR(VLOOKUP($A7,'[1]Donor-Served OBs'!A:N,16,0),0) -> 0 | AY7: =ROUNDUP(IF(A7=0,0,IFERROR(VLOOKUP($A7,'[1]Donor''s Assigned Kilos'!A:O,16,0),0)),0) -> 0 | AZ7: =IF(A7=0,0,IFERROR(SUMIFS([1]Population!Y:Y,[1]Population!J:J,'MASTER-2025'!A7),0)) -> 0 | BA7: =+H7+K7+N7+Q7+T7+W7+Z7+AC7+AF7+AI7+AL7+AO7+AR7+AU7+AX7 -> 0 | BB7: =INT(I7+L7+O7+R7+U7+X7+AA7+AD7+AG7+AJ7+AM7+AP7+AS7+AV7+AY7) -> 0 | BC7: =ROUND(I7+L7+O7+R7+U7,0) -> 0 | BD7: =IF(A7=0,0,(+J7+M7+P7+S7+V7+Y7+AB7+AE7+AH7+AK7+AN7+AQ7+AT7+AW7+AZ7)) -> 0 | BE7: =IF(A7=0,0,SUMIFS([1]Population!C:C,[1]Population!A:A,'MASTER-2025'!A7)) -> #VALUE! | BF7: =IF(A7=0,0,SUMIFS([1]Population!D:D,[1]Population!A:A,'MASTER-2025'!A7)) -> #VALUE! | BG7: =IF(A7=0,0,SUMIFS([1]Population!E:E,[1]Population!A:A,'MASTER-2025'!A7)) -> #VALUE! | BH7: =IF(A7=0,0,SUMIFS([1]Population!F:F,[1]Population!A:A,'MASTER-2025'!A7)) -> #VALUE! | BI7: =+BF7+BG7+BH7 -> #VALUE! | BJ7: =+BK7-BI7-BH7-BG7-BF7-BE7 -> #VALUE! | BK7: =IF(A7=0,0,SUMIFS([1]Population!G:G,[1]Population!A:A,'MASTER-2025'!A7)) -> #VALUE! | BL7: {=IFERROR(VLOOKUP(A7,'[1]Now-OB-kg-POB-25'!A:AQ,{3,4,5,6,7,8,9,10,11,12,13,14},0),0)} -> 33 | BM7: 33 | BN7: 23 | BO7: 0 | BP7: 0 | BQ7: 0 | BR7: 0 | BS7: 0 | BT7: 0 | BU7: 0 | BV7: 0 | BW7: 0 | BX7: =SUM(BL7:BW7) -> 89 | BY7: {=IFERROR(VLOOKUP(A7,'[1]Now-OB-kg-POB-25'!A:AQ,{17,18,19,20,21,22,23,24,25,26,27,28},0),0)} -> 678 | BZ7: 663 | CA7: 663 | CB7: 0 | CC7: 0 | CD7: 0 | CE7: 0 | CF7: 0 | CG7: 0 | CH7: 0 | CI7: 0 | CJ7: 0 | CK7: =SUM(BY7:CJ7) -> 2004 | CL7: {=IFERROR(VLOOKUP(A7,'[1]Now-OB-kg-POB-25'!A:AQ,{31,32,33,34,35,36,37,38,39,40,41,42},0),0)} -> 14845 | CM7: 8298 | CN7: 6241 | CO7: 0 | CP7: 0 | CQ7: 0 | CR7: 0 | CS7: 0 | CT7: 0 | CU7: 0 | CV7: 0 | CW7: 0 | CX7: =SUM(CL7:CW7) -> 29384 | CY7: =IF(A7=0,0,IFERROR(VLOOKUP(A7,'[1]Info Donantes'!C:F,2,0),"Sin Contacto")) -> Sin Contacto | CZ7: =IF(A7=0,0,IFERROR(VLOOKUP(A7,'[1]Info Donantes'!C:F,3,0),"Sin Correo")) -> Sin Correo | DA7: =IF(A7=0,0,IFERROR(VLOOKUP(A7,'[1]Info Donantes'!C:F,4,0),"Sin Telefono")) -> Sin Telefono | DB7: Traceability Report - - KOL SHEARITH ISRAEL BROTHERHOOD CONGREGATION
A8: CORPORACIÓN INTERNACIONAL DE ALIMENTOS, S.A. | B8: =INT(IFERROR(VLOOKUP(A8,'[1]Donor Summary'!C:F,3,0),0)) -> 0 | C8: =INT(ROUND(IFERROR(VLOOKUP(A8,'[1]Donor Summary'!C:F,4,0),0),1)) -> 0 | D8: =INT(ROUND(C8-B8,1)) -> 0 | E8: =IF(A8=0,"",TEXT((IFERROR(D8/C8,0)),"0.00%")) -> 0.00% | F8: =IF(A8=0,"",TEXT((IFERROR(B8/C8,0)),"0.0%")) -> 0.0% | G8: =INT(D8*3) -> 0 | I8: =IFERROR(VLOOKUP(A8,'[1]Lot All by Part'!T:Y,6,0),0) -> 0 | K8: =IFERROR(VLOOKUP($A8,'[1]Donor-Served OBs'!A:N,3,0),0) -> 0 | L8: =ROUNDUP(IF(A8=0,0,IFERROR(VLOOKUP($A8,'[1]Donor''s Assigned Kilos'!A:O,3,0),0)),0) -> 0 | M8: =IF(A8=0,0,IFERROR(SUMIFS([1]Population!M:M,[1]Population!J:J,'MASTER-2025'!A8),0)) -> 0 | N8: =IFERROR(VLOOKUP($A8,'[1]Donor-Served OBs'!A:N,4,0),0) -> 0 | O8: =ROUNDUP(IF(A8=0,0,IFERROR(VLOOKUP($A8,'[1]Donor''s Assigned Kilos'!A:O,4,0),0)),0) -> 0 | P8: =IF(A8=0,0,IFERROR(SUMIFS([1]Population!N:N,[1]Population!J:J,'MASTER-2025'!A8),0)) -> 0 | Q8: =IFERROR(VLOOKUP($A8,'[1]Donor-Served OBs'!A:N,2,0),0) -> 0 | R8: =ROUNDUP(ROUND(IF(A8=0,0,IFERROR(VLOOKUP($A8,'[1]Donor''s Assigned Kilos'!A:O,9,0),0)),1),0) -> 0 | S8: =IF(A8=0,0,IFERROR(SUMIFS([1]Population!S:S,[1]Population!J:J,'MASTER-2025'!A8),0)) -> 0 | T8: =IFERROR(VLOOKUP($A8,'[1]Donor-Served OBs'!A:N,12,0),0) -> 0 | U8: =ROUNDUP(IF(A8=0,0,IF(A8=0,0,IFERROR(VLOOKUP($A8,'[1]Donor''s Assigned Kilos'!A:O,7,0),0))),0) -> 0 | V8: =IF(A8=0,0,IFERROR(SUMIFS([1]Population!Q:Q,[1]Population!J:J,'MASTER-2025'!A8),0)) -> 0 | W8: =IFERROR(VLOOKUP($A8,'[1]Donor-Served OBs'!A:N,10,0),0) -> 0 | X8: =ROUNDUP(IF(A8=0,0,IFERROR(VLOOKUP($A8,'[1]Donor''s Assigned Kilos'!A:N,5,0),0)),0) -> 0 | Y8: =IF(A8=0,0,IFERROR(SUMIFS([1]Population!O:O,[1]Population!J:J,'MASTER-2025'!A8),0)) -> 0 | Z8: =IFERROR(VLOOKUP($A8,'[1]Donor-Served OBs'!A:N,6,0),0) -> 0 | AA8: =ROUNDUP(IF(A8=0,0,IFERROR(VLOOKUP($A8,'[1]Donor''s Assigned Kilos'!A:N,11,0),0)),0) -> 0 | AB8: =IF(A8=0,0,IFERROR(SUMIFS([1]Population!U:U,[1]Population!J:J,'MASTER-2025'!A8),0)) -> 0 | AC8: =IFERROR(VLOOKUP($A8,'[1]Donor-Served OBs'!A:N,7,0),0) -> 0 | AD8: =ROUNDUP(IF(A8=0,0,IFERROR(VLOOKUP($A8,'[1]Donor''s Assigned Kilos'!A:N,8,0),0)),0) -> 0 | AE8: =IF(A8=0,0,IFERROR(SUMIFS([1]Population!R:R,[1]Population!J:J,'MASTER-2025'!A8),0)) -> 0 | AF8: =IFERROR(VLOOKUP($A8,'[1]Donor-Served OBs'!A:N,8,0),0) -> 0 | AG8: =ROUNDUP(IF(A8=0,0,IFERROR(VLOOKUP($A8,'[1]Donor''s Assigned Kilos'!A:N,6,0),0)),0) -> 0 | AH8: =IF(A8=0,0,IFERROR(SUMIFS([1]Population!P:P,[1]Population!J:J,'MASTER-2025'!A8),0)) -> 0 | AI8: =IFERROR(VLOOKUP($A8,'[1]Donor-Served OBs'!A:N,9,0),0) -> 0 | AJ8: =ROUNDUP(IF(A8=0,0,IFERROR(VLOOKUP($A8,'[1]Donor''s Assigned Kilos'!A:N,12,0),0)),0) -> 0 | AK8: =IF(A8=0,0,IFERROR(SUMIFS([1]Population!V:V,[1]Population!J:J,'MASTER-2025'!A8),0)) -> 0 | AL8: =IFERROR(VLOOKUP($A8,'[1]Donor-Served OBs'!A:N,16,0),0) -> 0 | AM8: =ROUNDUP(IF(A8=0,0,IFERROR(VLOOKUP($A8,'[1]Donor''s Assigned Kilos'!A:O,16,0),0)),0) -> 0 | AN8: =IF(A8=0,0,IFERROR(SUMIFS([1]Population!Z:Z,[1]Population!J:J,'MASTER-2025'!A8),0)) -> 0 | AO8: =IFERROR(VLOOKUP($A8,'[1]Donor-Served OBs'!A:N,11,0),0) -> 0 | AP8: =ROUNDUP(IF(A8=0,0,IFERROR(VLOOKUP($A8,'[1]Donor''s Assigned Kilos'!A:N,13,0),0)),0) -> 0 | AQ8: =IF(A8=0,0,IFERROR(SUMIFS([1]Population!W:W,[1]Population!J:J,'MASTER-2025'!A8),0)) -> 0 | AR8: =IFERROR(VLOOKUP($A8,'[1]Donor-Served OBs'!A:N,5,0),0) -> 0 | AS8: =ROUNDUP(IF(A8=0,0,IFERROR(VLOOKUP($A8,'[1]Donor''s Assigned Kilos'!A:N,10,0),0)),0) -> 0 | AT8: =IF(A8=0,0,IFERROR(SUMIFS([1]Population!T:T,[1]Population!J:J,'MASTER-2025'!A8),0)) -> 0 | AU8: =IFERROR(VLOOKUP($A8,'[1]Donor-Served OBs'!A:N,13,0),0) -> 0 | AV8: =ROUNDUP(IF(A8=0,0,IFERROR(VLOOKUP($A8,'[1]Donor''s Assigned Kilos'!A:N,14,0),0)),0) -> 0 | AW8: =IF(A8=0,0,IFERROR(SUMIFS([1]Population!X:X,[1]Population!J:J,'MASTER-2025'!A8),0)) -> 0 | AX8: =IFERROR(VLOOKUP($A8,'[1]Donor-Served OBs'!A:N,16,0),0) -> 0 | AY8: =ROUNDUP(IF(A8=0,0,IFERROR(VLOOKUP($A8,'[1]Donor''s Assigned Kilos'!A:O,16,0),0)),0) -> 0 | AZ8: =IF(A8=0,0,IFERROR(SUMIFS([1]Population!Y:Y,[1]Population!J:J,'MASTER-2025'!A8),0)) -> 0 | BA8: =+H8+K8+N8+Q8+T8+W8+Z8+AC8+AF8+AI8+AL8+AO8+AR8+AU8+AX8 -> 0 | BB8: =INT(I8+L8+O8+R8+U8+X8+AA8+AD8+AG8+AJ8+AM8+AP8+AS8+AV8+AY8) -> 0 | BC8: =ROUND(I8+L8+O8+R8+U8,0) -> 0 | BD8: =IF(A8=0,0,(+J8+M8+P8+S8+V8+Y8+AB8+AE8+AH8+AK8+AN8+AQ8+AT8+AW8+AZ8)) -> 0 | BE8: =IF(A8=0,0,SUMIFS([1]Population!C:C,[1]Population!A:A,'MASTER-2025'!A8)) -> #VALUE! | BF8: =IF(A8=0,0,SUMIFS([1]Population!D:D,[1]Population!A:A,'MASTER-2025'!A8)) -> #VALUE! | BG8: =IF(A8=0,0,SUMIFS([1]Population!E:E,[1]Population!A:A,'MASTER-2025'!A8)) -> #VALUE! | BH8: =IF(A8=0,0,SUMIFS([1]Population!F:F,[1]Population!A:A,'MASTER-2025'!A8)) -> #VALUE! | BI8: =+BF8+BG8+BH8 -> #VALUE! | BJ8: =+BK8-BI8-BH8-BG8-BF8-BE8 -> #VALUE! | BK8: =IF(A8=0,0,SUMIFS([1]Population!G:G,[1]Population!A:A,'MASTER-2025'!A8)) -> #VALUE! | BL8: {=IFERROR(VLOOKUP(A8,'[1]Now-OB-kg-POB-25'!A:AQ,{3,4,5,6,7,8,9,10,11,12,13,14},0),0)} -> 100 | BM8: 117 | BN8: 148 | BO8: 0 | BP8: 0 | BQ8: 0 | BR8: 0 | BS8: 0 | BT8: 0 | BU8: 0 | BV8: 0 | BW8: 0 | BX8: =SUM(BL8:BW8) -> 365 | BY8: {=IFERROR(VLOOKUP(A8,'[1]Now-OB-kg-POB-25'!A:AQ,{17,18,19,20,21,22,23,24,25,26,27,28},0),0)} -> 26159 | BZ8: 21470 | CA8: 60995 | CB8: 0 | CC8: 0 | CD8: 0 | CE8: 0 | CF8: 0 | CG8: 0 | CH8: 0 | CI8: 0 | CJ8: 0 | CK8: =SUM(BY8:CJ8) -> 108624 | CL8: {=IFERROR(VLOOKUP(A8,'[1]Now-OB-kg-POB-25'!A:AQ,{31,32,33,34,35,36,37,38,39,40,41,42},0),0)} -> 33000 | CM8: 35637 | CN8: 44724 | CO8: 0 | CP8: 0 | CQ8: 0 | CR8: 0 | CS8: 0 | CT8: 0 | CU8: 0 | CV8: 0 | CW8: 0 | CX8: =SUM(CL8:CW8) -> 113361 | CY8: =IF(A8=0,0,IFERROR(VLOOKUP(A8,'[1]Info Donantes'!C:F,2,0),"Sin Contacto")) -> Sin Contacto | CZ8: =IF(A8=0,0,IFERROR(VLOOKUP(A8,'[1]Info Donantes'!C:F,3,0),"Sin Correo")) -> Sin Correo | DA8: =IF(A8=0,0,IFERROR(VLOOKUP(A8,'[1]Info Donantes'!C:F,4,0),"Sin Telefono")) -> Sin Telefono | DB8: Traceability Report - - CORPORACIÓN INTERNACIONAL DE ALIMENTOS, S.A.
A9: Delivery Hero Dmart Panama S.A. (Orders Now) | B9: =INT(IFERROR(VLOOKUP(A9,'[1]Donor Summary'!C:F,3,0),0)) -> 0 | C9: =INT(ROUND(IFERROR(VLOOKUP(A9,'[1]Donor Summary'!C:F,4,0),0),1)) -> 0 | D9: =INT(ROUND(C9-B9,1)) -> 0 | E9: =IF(A9=0,"",TEXT((IFERROR(D9/C9,0)),"0.00%")) -> 0.00% | F9: =IF(A9=0,"",TEXT((IFERROR(B9/C9,0)),"0.0%")) -> 0.0% | G9: =INT(D9*3) -> 0 | I9: =IFERROR(VLOOKUP(A9,'[1]Lot All by Part'!T:Y,6,0),0) -> 0 | K9: =IFERROR(VLOOKUP($A9,'[1]Donor-Served OBs'!A:N,3,0),0) -> 0 | L9: =ROUNDUP(IF(A9=0,0,IFERROR(VLOOKUP($A9,'[1]Donor''s Assigned Kilos'!A:O,3,0),0)),0) -> 0 | M9: =IF(A9=0,0,IFERROR(SUMIFS([1]Population!M:M,[1]Population!J:J,'MASTER-2025'!A9),0)) -> 0 | N9: =IFERROR(VLOOKUP($A9,'[1]Donor-Served OBs'!A:N,4,0),0) -> 0 | O9: =ROUNDUP(IF(A9=0,0,IFERROR(VLOOKUP($A9,'[1]Donor''s Assigned Kilos'!A:O,4,0),0)),0) -> 0 | P9: =IF(A9=0,0,IFERROR(SUMIFS([1]Population!N:N,[1]Population!J:J,'MASTER-2025'!A9),0)) -> 0 | Q9: =IFERROR(VLOOKUP($A9,'[1]Donor-Served OBs'!A:N,2,0),0) -> 0 | R9: =ROUNDUP(ROUND(IF(A9=0,0,IFERROR(VLOOKUP($A9,'[1]Donor''s Assigned Kilos'!A:O,9,0),0)),1),0) -> 0 | S9: =IF(A9=0,0,IFERROR(SUMIFS([1]Population!S:S,[1]Population!J:J,'MASTER-2025'!A9),0)) -> 0 | T9: =IFERROR(VLOOKUP($A9,'[1]Donor-Served OBs'!A:N,12,0),0) -> 0 | U9: =ROUNDUP(IF(A9=0,0,IF(A9=0,0,IFERROR(VLOOKUP($A9,'[1]Donor''s Assigned Kilos'!A:O,7,0),0))),0) -> 0 | V9: =IF(A9=0,0,IFERROR(SUMIFS([1]Population!Q:Q,[1]Population!J:J,'MASTER-2025'!A9),0)) -> 0 | W9: =IFERROR(VLOOKUP($A9,'[1]Donor-Served OBs'!A:N,10,0),0) -> 0 | X9: =ROUNDUP(IF(A9=0,0,IFERROR(VLOOKUP($A9,'[1]Donor''s Assigned Kilos'!A:N,5,0),0)),0) -> 0 | Y9: =IF(A9=0,0,IFERROR(SUMIFS([1]Population!O:O,[1]Population!J:J,'MASTER-2025'!A9),0)) -> 0 | Z9: =IFERROR(VLOOKUP($A9,'[1]Donor-Served OBs'!A:N,6,0),0) -> 0 | AA9: =ROUNDUP(IF(A9=0,0,IFERROR(VLOOKUP($A9,'[1]Donor''s Assigned Kilos'!A:N,11,0),0)),0) -> 0 | AB9: =IF(A9=0,0,IFERROR(SUMIFS([1]Population!U:U,[1]Population!J:J,'MASTER-2025'!A9),0)) -> 0 | AC9: =IFERROR(VLOOKUP($A9,'[1]Donor-Served OBs'!A:N,7,0),0) -> 0 | AD9: =ROUNDUP(IF(A9=0,0,IFERROR(VLOOKUP($A9,'[1]Donor''s Assigned Kilos'!A:N,8,0),0)),0) -> 0 | AE9: =IF(A9=0,0,IFERROR(SUMIFS([1]Population!R:R,[1]Population!J:J,'MASTER-2025'!A9),0)) -> 0 | AF9: =IFERROR(VLOOKUP($A9,'[1]Donor-Served OBs'!A:N,8,0),0) -> 0 | AG9: =ROUNDUP(IF(A9=0,0,IFERROR(VLOOKUP($A9,'[1]Donor''s Assigned Kilos'!A:N,6,0),0)),0) -> 0 | AH9: =IF(A9=0,0,IFERROR(SUMIFS([1]Population!P:P,[1]Population!J:J,'MASTER-2025'!A9),0)) -> 0 | AI9: =IFERROR(VLOOKUP($A9,'[1]Donor-Served OBs'!A:N,9,0),0) -> 0 | AJ9: =ROUNDUP(IF(A9=0,0,IFERROR(VLOOKUP($A9,'[1]Donor''s Assigned Kilos'!A:N,12,0),0)),0) -> 0 | AK9: =IF(A9=0,0,IFERROR(SUMIFS([1]Population!V:V,[1]Population!J:J,'MASTER-2025'!A9),0)) -> 0 | AL9: =IFERROR(VLOOKUP($A9,'[1]Donor-Served OBs'!A:N,16,0),0) -> 0 | AM9: =ROUNDUP(IF(A9=0,0,IFERROR(VLOOKUP($A9,'[1]Donor''s Assigned Kilos'!A:O,16,0),0)),0) -> 0 | AN9: =IF(A9=0,0,IFERROR(SUMIFS([1]Population!Z:Z,[1]Population!J:J,'MASTER-2025'!A9),0)) -> 0 | AO9: =IFERROR(VLOOKUP($A9,'[1]Donor-Served OBs'!A:N,11,0),0) -> 0 | AP9: =ROUNDUP(IF(A9=0,0,IFERROR(VLOOKUP($A9,'[1]Donor''s Assigned Kilos'!A:N,13,0),0)),0) -> 0 | AQ9: =IF(A9=0,0,IFERROR(SUMIFS([1]Population!W:W,[1]Population!J:J,'MASTER-2025'!A9),0)) -> 0 | AR9: =IFERROR(VLOOKUP($A9,'[1]Donor-Served OBs'!A:N,5,0),0) -> 0 | AS9: =ROUNDUP(IF(A9=0,0,IFERROR(VLOOKUP($A9,'[1]Donor''s Assigned Kilos'!A:N,10,0),0)),0) -> 0 | AT9: =IF(A9=0,0,IFERROR(SUMIFS([1]Population!T:T,[1]Population!J:J,'MASTER-2025'!A9),0)) -> 0 | AU9: =IFERROR(VLOOKUP($A9,'[1]Donor-Served OBs'!A:N,13,0),0) -> 0 | AV9: =ROUNDUP(IF(A9=0,0,IFERROR(VLOOKUP($A9,'[1]Donor''s Assigned Kilos'!A:N,14,0),0)),0) -> 0 | AW9: =IF(A9=0,0,IFERROR(SUMIFS([1]Population!X:X,[1]Population!J:J,'MASTER-2025'!A9),0)) -> 0 | AX9: =IFERROR(VLOOKUP($A9,'[1]Donor-Served OBs'!A:N,16,0),0) -> 0 | AY9: =ROUNDUP(IF(A9=0,0,IFERROR(VLOOKUP($A9,'[1]Donor''s Assigned Kilos'!A:O,16,0),0)),0) -> 0 | AZ9: =IF(A9=0,0,IFERROR(SUMIFS([1]Population!Y:Y,[1]Population!J:J,'MASTER-2025'!A9),0)) -> 0 | BA9: =+H9+K9+N9+Q9+T9+W9+Z9+AC9+AF9+AI9+AL9+AO9+AR9+AU9+AX9 -> 0 | BB9: =INT(I9+L9+O9+R9+U9+X9+AA9+AD9+AG9+AJ9+AM9+AP9+AS9+AV9+AY9) -> 0 | BC9: =ROUND(I9+L9+O9+R9+U9,0) -> 0 | BD9: =IF(A9=0,0,(+J9+M9+P9+S9+V9+Y9+AB9+AE9+AH9+AK9+AN9+AQ9+AT9+AW9+AZ9)) -> 0 | BE9: =IF(A9=0,0,SUMIFS([1]Population!C:C,[1]Population!A:A,'MASTER-2025'!A9)) -> #VALUE! | BF9: =IF(A9=0,0,SUMIFS([1]Population!D:D,[1]Population!A:A,'MASTER-2025'!A9)) -> #VALUE! | BG9: =IF(A9=0,0,SUMIFS([1]Population!E:E,[1]Population!A:A,'MASTER-2025'!A9)) -> #VALUE! | BH9: =IF(A9=0,0,SUMIFS([1]Population!F:F,[1]Population!A:A,'MASTER-2025'!A9)) -> #VALUE! | BI9: =+BF9+BG9+BH9 -> #VALUE! | BJ9: =+BK9-BI9-BH9-BG9-BF9-BE9 -> #VALUE! | BK9: =IF(A9=0,0,SUMIFS([1]Population!G:G,[1]Population!A:A,'MASTER-2025'!A9)) -> #VALUE! | BL9: {=IFERROR(VLOOKUP(A9,'[1]Now-OB-kg-POB-25'!A:AQ,{3,4,5,6,7,8,9,10,11,12,13,14},0),0)} -> 24 | BM9: 30 | BN9: 26 | BO9: 0 | BP9: 0 | BQ9: 0 | BR9: 0 | BS9: 0 | BT9: 0 | BU9: 0 | BV9: 0 | BW9: 0 | BX9: =SUM(BL9:BW9) -> 80 | BY9: {=IFERROR(VLOOKUP(A9,'[1]Now-OB-kg-POB-25'!A:AQ,{17,18,19,20,21,22,23,24,25,26,27,28},0),0)} -> 242 | BZ9: 384 | CA9: 334 | CB9: 0 | CC9: 0 | CD9: 0 | CE9: 0 | CF9: 0 | CG9: 0 | CH9: 0 | CI9: 0 | CJ9: 0 | CK9: =SUM(BY9:CJ9) -> 960 | CL9: {=IFERROR(VLOOKUP(A9,'[1]Now-OB-kg-POB-25'!A:AQ,{31,32,33,34,35,36,37,38,39,40,41,42},0),0)} -> 7458 | CM9: 7006 | CN9: 7257 | CO9: 0 | CP9: 0 | CQ9: 0 | CR9: 0 | CS9: 0 | CT9: 0 | CU9: 0 | CV9: 0 | CW9: 0 | CX9: =SUM(CL9:CW9) -> 21721 | CY9: =IF(A9=0,0,IFERROR(VLOOKUP(A9,'[1]Info Donantes'!C:F,2,0),"Sin Contacto")) -> Sin Contacto | CZ9: =IF(A9=0,0,IFERROR(VLOOKUP(A9,'[1]Info Donantes'!C:F,3,0),"Sin Correo")) -> Sin Correo | DA9: =IF(A9=0,0,IFERROR(VLOOKUP(A9,'[1]Info Donantes'!C:F,4,0),"Sin Telefono")) -> Sin Telefono | DB9: Traceability Report - - Delivery Hero Dmart Panama S.A. (Orders Now)
A10: Empresa Panamaniña de Alimentos, S. A. | B10: =INT(IFERROR(VLOOKUP(A10,'[1]Donor Summary'!C:F,3,0),0)) -> 0 | C10: =INT(ROUND(IFERROR(VLOOKUP(A10,'[1]Donor Summary'!C:F,4,0),0),1)) -> 0 | D10: =INT(ROUND(C10-B10,1)) -> 0 | E10: =IF(A10=0,"",TEXT((IFERROR(D10/C10,0)),"0.00%")) -> 0.00% | F10: =IF(A10=0,"",TEXT((IFERROR(B10/C10,0)),"0.0%")) -> 0.0% | G10: =INT(D10*3) -> 0 | I10: =IFERROR(VLOOKUP(A10,'[1]Lot All by Part'!T:Y,6,0),0) -> 0 | K10: =IFERROR(VLOOKUP($A10,'[1]Donor-Served OBs'!A:N,3,0),0) -> 0 | L10: =ROUNDUP(IF(A10=0,0,IFERROR(VLOOKUP($A10,'[1]Donor''s Assigned Kilos'!A:O,3,0),0)),0) -> 0 | M10: =IF(A10=0,0,IFERROR(SUMIFS([1]Population!M:M,[1]Population!J:J,'MASTER-2025'!A10),0)) -> 0 | N10: =IFERROR(VLOOKUP($A10,'[1]Donor-Served OBs'!A:N,4,0),0) -> 0 | O10: =ROUNDUP(IF(A10=0,0,IFERROR(VLOOKUP($A10,'[1]Donor''s Assigned Kilos'!A:O,4,0),0)),0) -> 0 | P10: =IF(A10=0,0,IFERROR(SUMIFS([1]Population!N:N,[1]Population!J:J,'MASTER-2025'!A10),0)) -> 0 | Q10: =IFERROR(VLOOKUP($A10,'[1]Donor-Served OBs'!A:N,2,0),0) -> 0 | R10: =ROUNDUP(ROUND(IF(A10=0,0,IFERROR(VLOOKUP($A10,'[1]Donor''s Assigned Kilos'!A:O,9,0),0)),1),0) -> 0 | S10: =IF(A10=0,0,IFERROR(SUMIFS([1]Population!S:S,[1]Population!J:J,'MASTER-2025'!A10),0)) -> 0 | T10: =IFERROR(VLOOKUP($A10,'[1]Donor-Served OBs'!A:N,12,0),0) -> 0 | U10: =ROUNDUP(IF(A10=0,0,IF(A10=0,0,IFERROR(VLOOKUP($A10,'[1]Donor''s Assigned Kilos'!A:O,7,0),0))),0) -> 0 | V10: =IF(A10=0,0,IFERROR(SUMIFS([1]Population!Q:Q,[1]Population!J:J,'MASTER-2025'!A10),0)) -> 0 | W10: =IFERROR(VLOOKUP($A10,'[1]Donor-Served OBs'!A:N,10,0),0) -> 0 | X10: =ROUNDUP(IF(A10=0,0,IFERROR(VLOOKUP($A10,'[1]Donor''s Assigned Kilos'!A:N,5,0),0)),0) -> 0 | Y10: =IF(A10=0,0,IFERROR(SUMIFS([1]Population!O:O,[1]Population!J:J,'MASTER-2025'!A10),0)) -> 0 | Z10: =IFERROR(VLOOKUP($A10,'[1]Donor-Served OBs'!A:N,6,0),0) -> 0 | AA10: =ROUNDUP(IF(A10=0,0,IFERROR(VLOOKUP($A10,'[1]Donor''s Assigned Kilos'!A:N,11,0),0)),0) -> 0 | AB10: =IF(A10=0,0,IFERROR(SUMIFS([1]Population!U:U,[1]Population!J:J,'MASTER-2025'!A10),0)) -> 0 | AC10: =IFERROR(VLOOKUP($A10,'[1]Donor-Served OBs'!A:N,7,0),0) -> 0 | AD10: =ROUNDUP(IF(A10=0,0,IFERROR(VLOOKUP($A10,'[1]Donor''s Assigned Kilos'!A:N,8,0),0)),0) -> 0 | AE10: =IF(A10=0,0,IFERROR(SUMIFS([1]Population!R:R,[1]Population!J:J,'MASTER-2025'!A10),0)) -> 0 | AF10: =IFERROR(VLOOKUP($A10,'[1]Donor-Served OBs'!A:N,8,0),0) -> 0 | AG10: =ROUNDUP(IF(A10=0,0,IFERROR(VLOOKUP($A10,'[1]Donor''s Assigned Kilos'!A:N,6,0),0)),0) -> 0 | AH10: =IF(A10=0,0,IFERROR(SUMIFS([1]Population!P:P,[1]Population!J:J,'MASTER-2025'!A10),0)) -> 0 | AI10: =IFERROR(VLOOKUP($A10,'[1]Donor-Served OBs'!A:N,9,0),0) -> 0 | AJ10: =ROUNDUP(IF(A10=0,0,IFERROR(VLOOKUP($A10,'[1]Donor''s Assigned Kilos'!A:N,12,0),0)),0) -> 0 | AK10: =IF(A10=0,0,IFERROR(SUMIFS([1]Population!V:V,[1]Population!J:J,'MASTER-2025'!A10),0)) -> 0 | AL10: =IFERROR(VLOOKUP($A10,'[1]Donor-Served OBs'!A:N,16,0),0) -> 0 | AM10: =ROUNDUP(IF(A10=0,0,IFERROR(VLOOKUP($A10,'[1]Donor''s Assigned Kilos'!A:O,16,0),0)),0) -> 0 | AN10: =IF(A10=0,0,IFERROR(SUMIFS([1]Population!Z:Z,[1]Population!J:J,'MASTER-2025'!A10),0)) -> 0 | AO10: =IFERROR(VLOOKUP($A10,'[1]Donor-Served OBs'!A:N,11,0),0) -> 0 | AP10: =ROUNDUP(IF(A10=0,0,IFERROR(VLOOKUP($A10,'[1]Donor''s Assigned Kilos'!A:N,13,0),0)),0) -> 0 | AQ10: =IF(A10=0,0,IFERROR(SUMIFS([1]Population!W:W,[1]Population!J:J,'MASTER-2025'!A10),0)) -> 0 | AR10: =IFERROR(VLOOKUP($A10,'[1]Donor-Served OBs'!A:N,5,0),0) -> 0 | AS10: =ROUNDUP(IF(A10=0,0,IFERROR(VLOOKUP($A10,'[1]Donor''s Assigned Kilos'!A:N,10,0),0)),0) -> 0 | AT10: =IF(A10=0,0,IFERROR(SUMIFS([1]Population!T:T,[1]Population!J:J,'MASTER-2025'!A10),0)) -> 0 | AU10: =IFERROR(VLOOKUP($A10,'[1]Donor-Served OBs'!A:N,13,0),0) -> 0 | AV10: =ROUNDUP(IF(A10=0,0,IFERROR(VLOOKUP($A10,'[1]Donor''s Assigned Kilos'!A:N,14,0),0)),0) -> 0 | AW10: =IF(A10=0,0,IFERROR(SUMIFS([1]Population!X:X,[1]Population!J:J,'MASTER-2025'!A10),0)) -> 0 | AX10: =IFERROR(VLOOKUP($A10,'[1]Donor-Served OBs'!A:N,16,0),0) -> 0 | AY10: =ROUNDUP(IF(A10=0,0,IFERROR(VLOOKUP($A10,'[1]Donor''s Assigned Kilos'!A:O,16,0),0)),0) -> 0 | AZ10: =IF(A10=0,0,IFERROR(SUMIFS([1]Population!Y:Y,[1]Population!J:J,'MASTER-2025'!A10),0)) -> 0 | BA10: =+H10+K10+N10+Q10+T10+W10+Z10+AC10+AF10+AI10+AL10+AO10+AR10+AU10+AX10 -> 0 | BB10: =INT(I10+L10+O10+R10+U10+X10+AA10+AD10+AG10+AJ10+AM10+AP10+AS10+AV10+AY10) -> 0 | BC10: =ROUND(I10+L10+O10+R10+U10,0) -> 0 | BD10: =IF(A10=0,0,(+J10+M10+P10+S10+V10+Y10+AB10+AE10+AH10+AK10+AN10+AQ10+AT10+AW10+AZ10)) -> 0 | BE10: =IF(A10=0,0,SUMIFS([1]Population!C:C,[1]Population!A:A,'MASTER-2025'!A10)) -> #VALUE! | BF10: =IF(A10=0,0,SUMIFS([1]Population!D:D,[1]Population!A:A,'MASTER-2025'!A10)) -> #VALUE! | BG10: =IF(A10=0,0,SUMIFS([1]Population!E:E,[1]Population!A:A,'MASTER-2025'!A10)) -> #VALUE! | BH10: =IF(A10=0,0,SUMIFS([1]Population!F:F,[1]Population!A:A,'MASTER-2025'!A10)) -> #VALUE! | BI10: =+BF10+BG10+BH10 -> #VALUE! | BJ10: =+BK10-BI10-BH10-BG10-BF10-BE10 -> #VALUE! | BK10: =IF(A10=0,0,SUMIFS([1]Population!G:G,[1]Population!A:A,'MASTER-2025'!A10)) -> #VALUE! | BL10: {=IFERROR(VLOOKUP(A10,'[1]Now-OB-kg-POB-25'!A:AQ,{3,4,5,6,7,8,9,10,11,12,13,14},0),0)} -> 42 | BM10: 87 | BN10: 111 | BO10: 0 | BP10: 0 | BQ10: 0 | BR10: 0 | BS10: 0 | BT10: 0 | BU10: 0 | BV10: 0 | BW10: 0 | BX10: =SUM(BL10:BW10) -> 240 | BY10: {=IFERROR(VLOOKUP(A10,'[1]Now-OB-kg-POB-25'!A:AQ,{17,18,19,20,21,22,23,24,25,26,27,28},0),0)} -> 6842 | BZ10: 5690 | CA10: 6413 | CB10: 0 | CC10: 0 | CD10: 0 | CE10: 0 | CF10: 0 | CG10: 0 | CH10: 0 | CI10: 0 | CJ10: 0 | CK10: =SUM(BY10:CJ10) -> 18945 | CL10: {=IFERROR(VLOOKUP(A10,'[1]Now-OB-kg-POB-25'!A:AQ,{31,32,33,34,35,36,37,38,39,40,41,42},0),0)} -> 14846 | CM10: 24125 | CN10: 31867 | CO10: 0 | CP10: 0 | CQ10: 0 | CR10: 0 | CS10: 0 | CT10: 0 | CU10: 0 | CV10: 0 | CW10: 0 | CX10: =SUM(CL10:CW10) -> 70838 | CY10: =IF(A10=0,0,IFERROR(VLOOKUP(A10,'[1]Info Donantes'!C:F,2,0),"Sin Contacto")) -> Sin Contacto | CZ10: =IF(A10=0,0,IFERROR(VLOOKUP(A10,'[1]Info Donantes'!C:F,3,0),"Sin Correo")) -> Sin Correo | DA10: =IF(A10=0,0,IFERROR(VLOOKUP(A10,'[1]Info Donantes'!C:F,4,0),"Sin Telefono")) -> Sin Telefono | DB10: Traceability Report - - Empresa Panamaniña de Alimentos, S. A.
A11: FELIPE MOTTA, S.A | B11: =INT(IFERROR(VLOOKUP(A11,'[1]Donor Summary'!C:F,3,0),0)) -> 0 | C11: =INT(ROUND(IFERROR(VLOOKUP(A11,'[1]Donor Summary'!C:F,4,0),0),1)) -> 388 | D11: =INT(ROUND(C11-B11,1)) -> 388 | E11: =IF(A11=0,"",TEXT((IFERROR(D11/C11,0)),"0.00%")) -> 100.00% | F11: =IF(A11=0,"",TEXT((IFERROR(B11/C11,0)),"0.0%")) -> 0.0% | G11: =INT(D11*3) -> 1164 | I11: =IFERROR(VLOOKUP(A11,'[1]Lot All by Part'!T:Y,6,0),0) -> 0 | K11: =IFERROR(VLOOKUP($A11,'[1]Donor-Served OBs'!A:N,3,0),0) -> 8 | L11: =ROUNDUP(IF(A11=0,0,IFERROR(VLOOKUP($A11,'[1]Donor''s Assigned Kilos'!A:O,3,0),0)),0) -> 81 | M11: =IF(A11=0,0,IFERROR(SUMIFS([1]Population!M:M,[1]Population!J:J,'MASTER-2025'!A11),0)) -> 0 | N11: =IFERROR(VLOOKUP($A11,'[1]Donor-Served OBs'!A:N,4,0),0) -> 11 | O11: =ROUNDUP(IF(A11=0,0,IFERROR(VLOOKUP($A11,'[1]Donor''s Assigned Kilos'!A:O,4,0),0)),0) -> 113 | P11: =IF(A11=0,0,IFERROR(SUMIFS([1]Population!N:N,[1]Population!J:J,'MASTER-2025'!A11),0)) -> 0 | Q11: =IFERROR(VLOOKUP($A11,'[1]Donor-Served OBs'!A:N,2,0),0) -> 2 | R11: =ROUNDUP(ROUND(IF(A11=0,0,IFERROR(VLOOKUP($A11,'[1]Donor''s Assigned Kilos'!A:O,9,0),0)),1),0) -> 19 | S11: =IF(A11=0,0,IFERROR(SUMIFS([1]Population!S:S,[1]Population!J:J,'MASTER-2025'!A11),0)) -> 0 | T11: =IFERROR(VLOOKUP($A11,'[1]Donor-Served OBs'!A:N,12,0),0) -> 2 | U11: =ROUNDUP(IF(A11=0,0,IF(A11=0,0,IFERROR(VLOOKUP($A11,'[1]Donor''s Assigned Kilos'!A:O,7,0),0))),0) -> 16 | V11: =IF(A11=0,0,IFERROR(SUMIFS([1]Population!Q:Q,[1]Population!J:J,'MASTER-2025'!A11),0)) -> 0 | W11: =IFERROR(VLOOKUP($A11,'[1]Donor-Served OBs'!A:N,10,0),0) -> 6 | X11: =ROUNDUP(IF(A11=0,0,IFERROR(VLOOKUP($A11,'[1]Donor''s Assigned Kilos'!A:N,5,0),0)),0) -> 35 | Y11: =IF(A11=0,0,IFERROR(SUMIFS([1]Population!O:O,[1]Population!J:J,'MASTER-2025'!A11),0)) -> 0 | Z11: =IFERROR(VLOOKUP($A11,'[1]Donor-Served OBs'!A:N,6,0),0) -> 0 | AA11: =ROUNDUP(IF(A11=0,0,IFERROR(VLOOKUP($A11,'[1]Donor''s Assigned Kilos'!A:N,11,0),0)),0) -> 0 | AB11: =IF(A11=0,0,IFERROR(SUMIFS([1]Population!U:U,[1]Population!J:J,'MASTER-2025'!A11),0)) -> 0 | AC11: =IFERROR(VLOOKUP($A11,'[1]Donor-Served OBs'!A:N,7,0),0) -> 2 | AD11: =ROUNDUP(IF(A11=0,0,IFERROR(VLOOKUP($A11,'[1]Donor''s Assigned Kilos'!A:N,8,0),0)),0) -> 28 | AE11: =IF(A11=0,0,IFERROR(SUMIFS([1]Population!R:R,[1]Population!J:J,'MASTER-2025'!A11),0)) -> 0 | AF11: =IFERROR(VLOOKUP($A11,'[1]Donor-Served OBs'!A:N,8,0),0) -> 1 | AG11: =ROUNDUP(IF(A11=0,0,IFERROR(VLOOKUP($A11,'[1]Donor''s Assigned Kilos'!A:N,6,0),0)),0) -> 1 | AH11: =IF(A11=0,0,IFERROR(SUMIFS([1]Population!P:P,[1]Population!J:J,'MASTER-2025'!A11),0)) -> 0 | AI11: =IFERROR(VLOOKUP($A11,'[1]Donor-Served OBs'!A:N,9,0),0) -> 0 | AJ11: =ROUNDUP(IF(A11=0,0,IFERROR(VLOOKUP($A11,'[1]Donor''s Assigned Kilos'!A:N,12,0),0)),0) -> 0 | AK11: =IF(A11=0,0,IFERROR(SUMIFS([1]Population!V:V,[1]Population!J:J,'MASTER-2025'!A11),0)) -> 0 | AL11: =IFERROR(VLOOKUP($A11,'[1]Donor-Served OBs'!A:N,16,0),0) -> 0 | AM11: =ROUNDUP(IF(A11=0,0,IFERROR(VLOOKUP($A11,'[1]Donor''s Assigned Kilos'!A:O,16,0),0)),0) -> 0 | AN11: =IF(A11=0,0,IFERROR(SUMIFS([1]Population!Z:Z,[1]Population!J:J,'MASTER-2025'!A11),0)) -> 0 | AO11: =IFERROR(VLOOKUP($A11,'[1]Donor-Served OBs'!A:N,11,0),0) -> 0 | AP11: =ROUNDUP(IF(A11=0,0,IFERROR(VLOOKUP($A11,'[1]Donor''s Assigned Kilos'!A:N,13,0),0)),0) -> 0 | AQ11: =IF(A11=0,0,IFERROR(SUMIFS([1]Population!W:W,[1]Population!J:J,'MASTER-2025'!A11),0)) -> 0 | AR11: =IFERROR(VLOOKUP($A11,'[1]Donor-Served OBs'!A:N,5,0),0) -> 1 | AS11: =ROUNDUP(IF(A11=0,0,IFERROR(VLOOKUP($A11,'[1]Donor''s Assigned Kilos'!A:N,10,0),0)),0) -> 3 | AT11: =IF(A11=0,0,IFERROR(SUMIFS([1]Population!T:T,[1]Population!J:J,'MASTER-2025'!A11),0)) -> 0 | AU11: =IFERROR(VLOOKUP($A11,'[1]Donor-Served OBs'!A:N,13,0),0) -> 0 | AV11: =ROUNDUP(IF(A11=0,0,IFERROR(VLOOKUP($A11,'[1]Donor''s Assigned Kilos'!A:N,14,0),0)),0) -> 0 | AW11: =IF(A11=0,0,IFERROR(SUMIFS([1]Population!X:X,[1]Population!J:J,'MASTER-2025'!A11),0)) -> 0 | AX11: =IFERROR(VLOOKUP($A11,'[1]Donor-Served OBs'!A:N,16,0),0) -> 0 | AY11: =ROUNDUP(IF(A11=0,0,IFERROR(VLOOKUP($A11,'[1]Donor''s Assigned Kilos'!A:O,16,0),0)),0) -> 0 | AZ11: =IF(A11=0,0,IFERROR(SUMIFS([1]Population!Y:Y,[1]Population!J:J,'MASTER-2025'!A11),0)) -> 0 | BA11: =+H11+K11+N11+Q11+T11+W11+Z11+AC11+AF11+AI11+AL11+AO11+AR11+AU11+AX11 -> 33 | BB11: =INT(I11+L11+O11+R11+U11+X11+AA11+AD11+AG11+AJ11+AM11+AP11+AS11+AV11+AY11) -> 296 | BC11: =ROUND(I11+L11+O11+R11+U11,0) -> 229 | BD11: =IF(A11=0,0,(+J11+M11+P11+S11+V11+Y11+AB11+AE11+AH11+AK11+AN11+AQ11+AT11+AW11+AZ11)) -> 0 | BE11: =IF(A11=0,0,SUMIFS([1]Population!C:C,[1]Population!A:A,'MASTER-2025'!A11)) -> #VALUE! | BF11: =IF(A11=0,0,SUMIFS([1]Population!D:D,[1]Population!A:A,'MASTER-2025'!A11)) -> #VALUE! | BG11: =IF(A11=0,0,SUMIFS([1]Population!E:E,[1]Population!A:A,'MASTER-2025'!A11)) -> #VALUE! | BH11: =IF(A11=0,0,SUMIFS([1]Population!F:F,[1]Population!A:A,'MASTER-2025'!A11)) -> #VALUE! | BI11: =+BF11+BG11+BH11 -> #VALUE! | BJ11: =+BK11-BI11-BH11-BG11-BF11-BE11 -> #VALUE! | BK11: =IF(A11=0,0,SUMIFS([1]Population!G:G,[1]Population!A:A,'MASTER-2025'!A11)) -> #VALUE! | BL11: {=IFERROR(VLOOKUP(A11,'[1]Now-OB-kg-POB-25'!A:AQ,{3,4,5,6,7,8,9,10,11,12,13,14},0),0)} -> 41 | BM11: 33 | BN11: 33 | BO11: 0 | BP11: 0 | BQ11: 0 | BR11: 0 | BS11: 0 | BT11: 0 | BU11: 0 | BV11: 0 | BW11: 0 | BX11: =SUM(BL11:BW11) -> 107 | BY11: {=IFERROR(VLOOKUP(A11,'[1]Now-OB-kg-POB-25'!A:AQ,{17,18,19,20,21,22,23,24,25,26,27,28},0),0)} -> 650 | BZ11: 1596 | CA11: 388 | CB11: 0 | CC11: 0 | CD11: 0 | CE11: 0 | CF11: 0 | CG11: 0 | CH11: 0 | CI11: 0 | CJ11: 0 | CK11: =SUM(BY11:CJ11) -> 2634 | CL11: {=IFERROR(VLOOKUP(A11,'[1]Now-OB-kg-POB-25'!A:AQ,{31,32,33,34,35,36,37,38,39,40,41,42},0),0)} -> 10195 | CM11: 11526 | CN11: 13490 | CO11: 0 | CP11: 0 | CQ11: 0 | CR11: 0 | CS11: 0 | CT11: 0 | CU11: 0 | CV11: 0 | CW11: 0 | CX11: =SUM(CL11:CW11) -> 35211 | CY11: =IF(A11=0,0,IFERROR(VLOOKUP(A11,'[1]Info Donantes'!C:F,2,0),"Sin Contacto")) -> Marcela Vallarino | CZ11: =IF(A11=0,0,IFERROR(VLOOKUP(A11,'[1]Info Donantes'!C:F,3,0),"Sin Correo")) -> marcellavallarino@felipemotta.com | DA11: =IF(A11=0,0,IFERROR(VLOOKUP(A11,'[1]Info Donantes'!C:F,4,0),"Sin Telefono")) -> 302-5555 | DB11: Traceability Report - - FELIPE MOTTA, S.A
A12: PANAMEAN FRANCHISES | B12: =INT(IFERROR(VLOOKUP(A12,'[1]Donor Summary'!C:F,3,0),0)) -> 0 | C12: =INT(ROUND(IFERROR(VLOOKUP(A12,'[1]Donor Summary'!C:F,4,0),0),1)) -> 0 | D12: =INT(ROUND(C12-B12,1)) -> 0 | E12: =IF(A12=0,"",TEXT((IFERROR(D12/C12,0)),"0.00%")) -> 0.00% | F12: =IF(A12=0,"",TEXT((IFERROR(B12/C12,0)),"0.0%")) -> 0.0% | G12: =INT(D12*3) -> 0 | I12: =IFERROR(VLOOKUP(A12,'[1]Lot All by Part'!T:Y,6,0),0) -> 0 | K12: =IFERROR(VLOOKUP($A12,'[1]Donor-Served OBs'!A:N,3,0),0) -> 0 | L12: =ROUNDUP(IF(A12=0,0,IFERROR(VLOOKUP($A12,'[1]Donor''s Assigned Kilos'!A:O,3,0),0)),0) -> 0 | M12: =IF(A12=0,0,IFERROR(SUMIFS([1]Population!M:M,[1]Population!J:J,'MASTER-2025'!A12),0)) -> 0 | N12: =IFERROR(VLOOKUP($A12,'[1]Donor-Served OBs'!A:N,4,0),0) -> 0 | O12: =ROUNDUP(IF(A12=0,0,IFERROR(VLOOKUP($A12,'[1]Donor''s Assigned Kilos'!A:O,4,0),0)),0) -> 0 | P12: =IF(A12=0,0,IFERROR(SUMIFS([1]Population!N:N,[1]Population!J:J,'MASTER-2025'!A12),0)) -> 0 | Q12: =IFERROR(VLOOKUP($A12,'[1]Donor-Served OBs'!A:N,2,0),0) -> 0 | R12: =ROUNDUP(ROUND(IF(A12=0,0,IFERROR(VLOOKUP($A12,'[1]Donor''s Assigned Kilos'!A:O,9,0),0)),1),0) -> 0 | S12: =IF(A12=0,0,IFERROR(SUMIFS([1]Population!S:S,[1]Population!J:J,'MASTER-2025'!A12),0)) -> 0 | T12: =IFERROR(VLOOKUP($A12,'[1]Donor-Served OBs'!A:N,12,0),0) -> 0 | U12: =ROUNDUP(IF(A12=0,0,IF(A12=0,0,IFERROR(VLOOKUP($A12,'[1]Donor''s Assigned Kilos'!A:O,7,0),0))),0) -> 0 | V12: =IF(A12=0,0,IFERROR(SUMIFS([1]Population!Q:Q,[1]Population!J:J,'MASTER-2025'!A12),0)) -> 0 | W12: =IFERROR(VLOOKUP($A12,'[1]Donor-Served OBs'!A:N,10,0),0) -> 0 | X12: =ROUNDUP(IF(A12=0,0,IFERROR(VLOOKUP($A12,'[1]Donor''s Assigned Kilos'!A:N,5,0),0)),0) -> 0 | Y12: =IF(A12=0,0,IFERROR(SUMIFS([1]Population!O:O,[1]Population!J:J,'MASTER-2025'!A12),0)) -> 0 | Z12: =IFERROR(VLOOKUP($A12,'[1]Donor-Served OBs'!A:N,6,0),0) -> 0 | AA12: =ROUNDUP(IF(A12=0,0,IFERROR(VLOOKUP($A12,'[1]Donor''s Assigned Kilos'!A:N,11,0),0)),0) -> 0 | AB12: =IF(A12=0,0,IFERROR(SUMIFS([1]Population!U:U,[1]Population!J:J,'MASTER-2025'!A12),0)) -> 0 | AC12: =IFERROR(VLOOKUP($A12,'[1]Donor-Served OBs'!A:N,7,0),0) -> 0 | AD12: =ROUNDUP(IF(A12=0,0,IFERROR(VLOOKUP($A12,'[1]Donor''s Assigned Kilos'!A:N,8,0),0)),0) -> 0 | AE12: =IF(A12=0,0,IFERROR(SUMIFS([1]Population!R:R,[1]Population!J:J,'MASTER-2025'!A12),0)) -> 0 | AF12: =IFERROR(VLOOKUP($A12,'[1]Donor-Served OBs'!A:N,8,0),0) -> 0 | AG12: =ROUNDUP(IF(A12=0,0,IFERROR(VLOOKUP($A12,'[1]Donor''s Assigned Kilos'!A:N,6,0),0)),0) -> 0 | AH12: =IF(A12=0,0,IFERROR(SUMIFS([1]Population!P:P,[1]Population!J:J,'MASTER-2025'!A12),0)) -> 0 | AI12: =IFERROR(VLOOKUP($A12,'[1]Donor-Served OBs'!A:N,9,0),0) -> 0 | AJ12: =ROUNDUP(IF(A12=0,0,IFERROR(VLOOKUP($A12,'[1]Donor''s Assigned Kilos'!A:N,12,0),0)),0) -> 0 | AK12: =IF(A12=0,0,IFERROR(SUMIFS([1]Population!V:V,[1]Population!J:J,'MASTER-2025'!A12),0)) -> 0 | AL12: =IFERROR(VLOOKUP($A12,'[1]Donor-Served OBs'!A:N,16,0),0) -> 0 | AM12: =ROUNDUP(IF(A12=0,0,IFERROR(VLOOKUP($A12,'[1]Donor''s Assigned Kilos'!A:O,16,0),0)),0) -> 0 | AN12: =IF(A12=0,0,IFERROR(SUMIFS([1]Population!Z:Z,[1]Population!J:J,'MASTER-2025'!A12),0)) -> 0 | AO12: =IFERROR(VLOOKUP($A12,'[1]Donor-Served OBs'!A:N,11,0),0) -> 0 | AP12: =ROUNDUP(IF(A12=0,0,IFERROR(VLOOKUP($A12,'[1]Donor''s Assigned Kilos'!A:N,13,0),0)),0) -> 0 | AQ12: =IF(A12=0,0,IFERROR(SUMIFS([1]Population!W:W,[1]Population!J:J,'MASTER-2025'!A12),0)) -> 0 | AR12: =IFERROR(VLOOKUP($A12,'[1]Donor-Served OBs'!A:N,5,0),0) -> 0 | AS12: =ROUNDUP(IF(A12=0,0,IFERROR(VLOOKUP($A12,'[1]Donor''s Assigned Kilos'!A:N,10,0),0)),0) -> 0 | AT12: =IF(A12=0,0,IFERROR(SUMIFS([1]Population!T:T,[1]Population!J:J,'MASTER-2025'!A12),0)) -> 0 | AU12: =IFERROR(VLOOKUP($A12,'[1]Donor-Served OBs'!A:N,13,0),0) -> 0 | AV12: =ROUNDUP(IF(A12=0,0,IFERROR(VLOOKUP($A12,'[1]Donor''s Assigned Kilos'!A:N,14,0),0)),0) -> 0 | AW12: =IF(A12=0,0,IFERROR(SUMIFS([1]Population!X:X,[1]Population!J:J,'MASTER-2025'!A12),0)) -> 0 | AX12: =IFERROR(VLOOKUP($A12,'[1]Donor-Served OBs'!A:N,16,0),0) -> 0 | AY12: =ROUNDUP(IF(A12=0,0,IFERROR(VLOOKUP($A12,'[1]Donor''s Assigned Kilos'!A:O,16,0),0)),0) -> 0 | AZ12: =IF(A12=0,0,IFERROR(SUMIFS([1]Population!Y:Y,[1]Population!J:J,'MASTER-2025'!A12),0)) -> 0 | BA12: =+H12+K12+N12+Q12+T12+W12+Z12+AC12+AF12+AI12+AL12+AO12+AR12+AU12+AX12 -> 0 | BB12: =INT(I12+L12+O12+R12+U12+X12+AA12+AD12+AG12+AJ12+AM12+AP12+AS12+AV12+AY12) -> 0 | BC12: =ROUND(I12+L12+O12+R12+U12,0) -> 0 | BD12: =IF(A12=0,0,(+J12+M12+P12+S12+V12+Y12+AB12+AE12+AH12+AK12+AN12+AQ12+AT12+AW12+AZ12)) -> 0 | BE12: =IF(A12=0,0,SUMIFS([1]Population!C:C,[1]Population!A:A,'MASTER-2025'!A12)) -> #VALUE! | BF12: =IF(A12=0,0,SUMIFS([1]Population!D:D,[1]Population!A:A,'MASTER-2025'!A12)) -> #VALUE! | BG12: =IF(A12=0,0,SUMIFS([1]Population!E:E,[1]Population!A:A,'MASTER-2025'!A12)) -> #VALUE! | BH12: =IF(A12=0,0,SUMIFS([1]Population!F:F,[1]Population!A:A,'MASTER-2025'!A12)) -> #VALUE! | BI12: =+BF12+BG12+BH12 -> #VALUE! | BJ12: =+BK12-BI12-BH12-BG12-BF12-BE12 -> #VALUE! | BK12: =IF(A12=0,0,SUMIFS([1]Population!G:G,[1]Population!A:A,'MASTER-2025'!A12)) -> #VALUE! | BL12: {=IFERROR(VLOOKUP(A12,'[1]Now-OB-kg-POB-25'!A:AQ,{3,4,5,6,7,8,9,10,11,12,13,14},0),0)} -> 77 | BM12: 62 | BN12: 64 | BO12: 0 | BP12: 0 | BQ12: 0 | BR12: 0 | BS12: 0 | BT12: 0 | BU12: 0 | BV12: 0 | BW12: 0 | BX12: =SUM(BL12:BW12) -> 203 | BY12: {=IFERROR(VLOOKUP(A12,'[1]Now-OB-kg-POB-25'!A:AQ,{17,18,19,20,21,22,23,24,25,26,27,28},0),0)} -> 492 | BZ12: 340 | CA12: 446 | CB12: 0 | CC12: 0 | CD12: 0 | CE12: 0 | CF12: 0 | CG12: 0 | CH12: 0 | CI12: 0 | CJ12: 0 | CK12: =SUM(BY12:CJ12) -> 1278 | CL12: {=IFERROR(VLOOKUP(A12,'[1]Now-OB-kg-POB-25'!A:AQ,{31,32,33,34,35,36,37,38,39,40,41,42},0),0)} -> 22206 | CM12: 14083 | CN12: 21155 | CO12: 0 | CP12: 0 | CQ12: 0 | CR12: 0 | CS12: 0 | CT12: 0 | CU12: 0 | CV12: 0 | CW12: 0 | CX12: =SUM(CL12:CW12) -> 57444 | CY12: =IF(A12=0,0,IFERROR(VLOOKUP(A12,'[1]Info Donantes'!C:F,2,0),"Sin Contacto")) -> Sin Contacto | CZ12: =IF(A12=0,0,IFERROR(VLOOKUP(A12,'[1]Info Donantes'!C:F,3,0),"Sin Correo")) -> Sin Correo | DA12: =IF(A12=0,0,IFERROR(VLOOKUP(A12,'[1]Info Donantes'!C:F,4,0),"Sin Telefono")) -> Sin Telefono | DB12: Traceability Report - - PANAMEAN FRANCHISES
A13: GENTILE - G & H. S.A. | B13: =INT(IFERROR(VLOOKUP(A13,'[1]Donor Summary'!C:F,3,0),0)) -> 0 | C13: =INT(ROUND(IFERROR(VLOOKUP(A13,'[1]Donor Summary'!C:F,4,0),0),1)) -> 15 | D13: =INT(ROUND(C13-B13,1)) -> 15 | E13: =IF(A13=0,"",TEXT((IFERROR(D13/C13,0)),"0.00%")) -> 100.00% | F13: =IF(A13=0,"",TEXT((IFERROR(B13/C13,0)),"0.0%")) -> 0.0% | G13: =INT(D13*3) -> 45 | I13: =IFERROR(VLOOKUP(A13,'[1]Lot All by Part'!T:Y,6,0),0) -> 0 | K13: =IFERROR(VLOOKUP($A13,'[1]Donor-Served OBs'!A:N,3,0),0) -> 0 | L13: =ROUNDUP(IF(A13=0,0,IFERROR(VLOOKUP($A13,'[1]Donor''s Assigned Kilos'!A:O,3,0),0)),0) -> 0 | M13: =IF(A13=0,0,IFERROR(SUMIFS([1]Population!M:M,[1]Population!J:J,'MASTER-2025'!A13),0)) -> 0 | N13: =IFERROR(VLOOKUP($A13,'[1]Donor-Served OBs'!A:N,4,0),0) -> 3 | O13: =ROUNDUP(IF(A13=0,0,IFERROR(VLOOKUP($A13,'[1]Donor''s Assigned Kilos'!A:O,4,0),0)),0) -> 15 | P13: =IF(A13=0,0,IFERROR(SUMIFS([1]Population!N:N,[1]Population!J:J,'MASTER-2025'!A13),0)) -> 0 | Q13: =IFERROR(VLOOKUP($A13,'[1]Donor-Served OBs'!A:N,2,0),0) -> 0 | R13: =ROUNDUP(ROUND(IF(A13=0,0,IFERROR(VLOOKUP($A13,'[1]Donor''s Assigned Kilos'!A:O,9,0),0)),1),0) -> 0 | S13: =IF(A13=0,0,IFERROR(SUMIFS([1]Population!S:S,[1]Population!J:J,'MASTER-2025'!A13),0)) -> 0 | T13: =IFERROR(VLOOKUP($A13,'[1]Donor-Served OBs'!A:N,12,0),0) -> 0 | U13: =ROUNDUP(IF(A13=0,0,IF(A13=0,0,IFERROR(VLOOKUP($A13,'[1]Donor''s Assigned Kilos'!A:O,7,0),0))),0) -> 0 | V13: =IF(A13=0,0,IFERROR(SUMIFS([1]Population!Q:Q,[1]Population!J:J,'MASTER-2025'!A13),0)) -> 0 | W13: =IFERROR(VLOOKUP($A13,'[1]Donor-Served OBs'!A:N,10,0),0) -> 0 | X13: =ROUNDUP(IF(A13=0,0,IFERROR(VLOOKUP($A13,'[1]Donor''s Assigned Kilos'!A:N,5,0),0)),0) -> 0 | Y13: =IF(A13=0,0,IFERROR(SUMIFS([1]Population!O:O,[1]Population!J:J,'MASTER-2025'!A13),0)) -> 0 | Z13: =IFERROR(VLOOKUP($A13,'[1]Donor-Served OBs'!A:N,6,0),0) -> 0 | AA13: =ROUNDUP(IF(A13=0,0,IFERROR(VLOOKUP($A13,'[1]Donor''s Assigned Kilos'!A:N,11,0),0)),0) -> 0 | AB13: =IF(A13=0,0,IFERROR(SUMIFS([1]Population!U:U,[1]Population!J:J,'MASTER-2025'!A13),0)) -> 0 | AC13: =IFERROR(VLOOKUP($A13,'[1]Donor-Served OBs'!A:N,7,0),0) -> 0 | AD13: =ROUNDUP(IF(A13=0,0,IFERROR(VLOOKUP($A13,'[1]Donor''s Assigned Kilos'!A:N,8,0),0)),0) -> 0 | AE13: =IF(A13=0,0,IFERROR(SUMIFS([1]Population!R:R,[1]Population!J:J,'MASTER-2025'!A13),0)) -> 0 | AF13: =IFERROR(VLOOKUP($A13,'[1]Donor-Served OBs'!A:N,8,0),0) -> 0 | AG13: =ROUNDUP(IF(A13=0,0,IFERROR(VLOOKUP($A13,'[1]Donor''s Assigned Kilos'!A:N,6,0),0)),0) -> 0 | AH13: =IF(A13=0,0,IFERROR(SUMIFS([1]Population!P:P,[1]Population!J:J,'MASTER-2025'!A13),0)) -> 0 | AI13: =IFERROR(VLOOKUP($A13,'[1]Donor-Served OBs'!A:N,9,0),0) -> 0 | AJ13: =ROUNDUP(IF(A13=0,0,IFERROR(VLOOKUP($A13,'[1]Donor''s Assigned Kilos'!A:N,12,0),0)),0) -> 0 | AK13: =IF(A13=0,0,IFERROR(SUMIFS([1]Population!V:V,[1]Population!J:J,'MASTER-2025'!A13),0)) -> 0 | AL13: =IFERROR(VLOOKUP($A13,'[1]Donor-Served OBs'!A:N,16,0),0) -> 0 | AM13: =ROUNDUP(IF(A13=0,0,IFERROR(VLOOKUP($A13,'[1]Donor''s Assigned Kilos'!A:O,16,0),0)),0) -> 0 | AN13: =IF(A13=0,0,IFERROR(SUMIFS([1]Population!Z:Z,[1]Population!J:J,'MASTER-2025'!A13),0)) -> 0 | AO13: =IFERROR(VLOOKUP($A13,'[1]Donor-Served OBs'!A:N,11,0),0) -> 0 | AP13: =ROUNDUP(IF(A13=0,0,IFERROR(VLOOKUP($A13,'[1]Donor''s Assigned Kilos'!A:N,13,0),0)),0) -> 0 | AQ13: =IF(A13=0,0,IFERROR(SUMIFS([1]Population!W:W,[1]Population!J:J,'MASTER-2025'!A13),0)) -> 0 | AR13: =IFERROR(VLOOKUP($A13,'[1]Donor-Served OBs'!A:N,5,0),0) -> 0 | AS13: =ROUNDUP(IF(A13=0,0,IFERROR(VLOOKUP($A13,'[1]Donor''s Assigned Kilos'!A:N,10,0),0)),0) -> 0 | AT13: =IF(A13=0,0,IFERROR(SUMIFS([1]Population!T:T,[1]Population!J:J,'MASTER-2025'!A13),0)) -> 0 | AU13: =IFERROR(VLOOKUP($A13,'[1]Donor-Served OBs'!A:N,13,0),0) -> 0 | AV13: =ROUNDUP(IF(A13=0,0,IFERROR(VLOOKUP($A13,'[1]Donor''s Assigned Kilos'!A:N,14,0),0)),0) -> 0 | AW13: =IF(A13=0,0,IFERROR(SUMIFS([1]Population!X:X,[1]Population!J:J,'MASTER-2025'!A13),0)) -> 0 | AX13: =IFERROR(VLOOKUP($A13,'[1]Donor-Served OBs'!A:N,16,0),0) -> 0 | AY13: =ROUNDUP(IF(A13=0,0,IFERROR(VLOOKUP($A13,'[1]Donor''s Assigned Kilos'!A:O,16,0),0)),0) -> 0 | AZ13: =IF(A13=0,0,IFERROR(SUMIFS([1]Population!Y:Y,[1]Population!J:J,'MASTER-2025'!A13),0)) -> 0 | BA13: =+H13+K13+N13+Q13+T13+W13+Z13+AC13+AF13+AI13+AL13+AO13+AR13+AU13+AX13 -> 3 | BB13: =INT(I13+L13+O13+R13+U13+X13+AA13+AD13+AG13+AJ13+AM13+AP13+AS13+AV13+AY13) -> 15 | BC13: =ROUND(I13+L13+O13+R13+U13,0) -> 15 | BD13: =IF(A13=0,0,(+J13+M13+P13+S13+V13+Y13+AB13+AE13+AH13+AK13+AN13+AQ13+AT13+AW13+AZ13)) -> 0 | BE13: =IF(A13=0,0,SUMIFS([1]Population!C:C,[1]Population!A:A,'MASTER-2025'!A13)) -> #VALUE! | BF13: =IF(A13=0,0,SUMIFS([1]Population!D:D,[1]Population!A:A,'MASTER-2025'!A13)) -> #VALUE! | BG13: =IF(A13=0,0,SUMIFS([1]Population!E:E,[1]Population!A:A,'MASTER-2025'!A13)) -> #VALUE! | BH13: =IF(A13=0,0,SUMIFS([1]Population!F:F,[1]Population!A:A,'MASTER-2025'!A13)) -> #VALUE! | BI13: =+BF13+BG13+BH13 -> #VALUE! | BJ13: =+BK13-BI13-BH13-BG13-BF13-BE13 -> #VALUE! | BK13: =IF(A13=0,0,SUMIFS([1]Population!G:G,[1]Population!A:A,'MASTER-2025'!A13)) -> #VALUE! | BL13: {=IFERROR(VLOOKUP(A13,'[1]Now-OB-kg-POB-25'!A:AQ,{3,4,5,6,7,8,9,10,11,12,13,14},0),0)} -> 6 | BM13: 4 | BN13: 3 | BO13: 0 | BP13: 0 | BQ13: 0 | BR13: 0 | BS13: 0 | BT13: 0 | BU13: 0 | BV13: 0 | BW13: 0 | BX13: =SUM(BL13:BW13) -> 13 | BY13: {=IFERROR(VLOOKUP(A13,'[1]Now-OB-kg-POB-25'!A:AQ,{17,18,19,20,21,22,23,24,25,26,27,28},0),0)} -> 11 | BZ13: 9 | CA13: 15 | CB13: 0 | CC13: 0 | CD13: 0 | CE13: 0 | CF13: 0 | CG13: 0 | CH13: 0 | CI13: 0 | CJ13: 0 | CK13: =SUM(BY13:CJ13) -> 35 | CL13: {=IFERROR(VLOOKUP(A13,'[1]Now-OB-kg-POB-25'!A:AQ,{31,32,33,34,35,36,37,38,39,40,41,42},0),0)} -> 756 | CM13: 782 | CN13: 1205 | CO13: 0 | CP13: 0 | CQ13: 0 | CR13: 0 | CS13: 0 | CT13: 0 | CU13: 0 | CV13: 0 | CW13: 0 | CX13: =SUM(CL13:CW13) -> 2743 | CY13: =IF(A13=0,0,IFERROR(VLOOKUP(A13,'[1]Info Donantes'!C:F,2,0),"Sin Contacto")) -> 0 | CZ13: =IF(A13=0,0,IFERROR(VLOOKUP(A13,'[1]Info Donantes'!C:F,3,0),"Sin Correo")) -> 0 | DA13: =IF(A13=0,0,IFERROR(VLOOKUP(A13,'[1]Info Donantes'!C:F,4,0),"Sin Telefono")) -> 0 | DB13: Traceability Report - - GENTILE - G & H. S.A.
... A33: REPRESENTACIONES TEJEIRA, S.A | B33: =INT(IFERROR(VLOOKUP(A33,'[1]Donor Summary'!C:F,3,0),0)) -> 0 | C33: =INT(ROUND(IFERROR(VLOOKUP(A33,'[1]Donor Summary'!C:F,4,0),0),1)) -> 0 | D33: =INT(ROUND(C33-B33,1)) -> 0 | E33: =IF(A33=0,"",TEXT((IFERROR(D33/C33,0)),"0.00%")) -> 0.00% | F33: =IF(A33=0,"",TEXT((IFERROR(B33/C33,0)),"0.0%")) -> 0.0% | G33: =INT(D33*3) -> 0 | I33: =IFERROR(VLOOKUP(A33,'[1]Lot All by Part'!T:Y,6,0),0) -> 0 | K33: =IFERROR(VLOOKUP($A33,'[1]Donor-Served OBs'!A:N,3,0),0) -> 0 | L33: =ROUNDUP(IF(A33=0,0,IFERROR(VLOOKUP($A33,'[1]Donor''s Assigned Kilos'!A:O,3,0),0)),0) -> 0 | M33: =IF(A33=0,0,IFERROR(SUMIFS([1]Population!M:M,[1]Population!J:J,'MASTER-2025'!A33),0)) -> 0 | N33: =IFERROR(VLOOKUP($A33,'[1]Donor-Served OBs'!A:N,4,0),0) -> 0 | O33: =ROUNDUP(IF(A33=0,0,IFERROR(VLOOKUP($A33,'[1]Donor''s Assigned Kilos'!A:O,4,0),0)),0) -> 0 | P33: =IF(A33=0,0,IFERROR(SUMIFS([1]Population!N:N,[1]Population!J:J,'MASTER-2025'!A33),0)) -> 0 | Q33: =IFERROR(VLOOKUP($A33,'[1]Donor-Served OBs'!A:N,2,0),0) -> 0 | R33: =ROUNDUP(ROUND(IF(A33=0,0,IFERROR(VLOOKUP($A33,'[1]Donor''s Assigned Kilos'!A:O,9,0),0)),1),0) -> 0 | S33: =IF(A33=0,0,IFERROR(SUMIFS([1]Population!S:S,[1]Population!J:J,'MASTER-2025'!A33),0)) -> 0 | T33: =IFERROR(VLOOKUP($A33,'[1]Donor-Served OBs'!A:N,12,0),0) -> 0 | U33: =ROUNDUP(IF(A33=0,0,IF(A33=0,0,IFERROR(VLOOKUP($A33,'[1]Donor''s Assigned Kilos'!A:O,7,0),0))),0) -> 0 | V33: =IF(A33=0,0,IFERROR(SUMIFS([1]Population!Q:Q,[1]Population!J:J,'MASTER-2025'!A33),0)) -> 0 | W33: =IFERROR(VLOOKUP($A33,'[1]Donor-Served OBs'!A:N,10,0),0) -> 0 | X33: =ROUNDUP(IF(A33=0,0,IFERROR(VLOOKUP($A33,'[1]Donor''s Assigned Kilos'!A:N,5,0),0)),0) -> 0 | Y33: =IF(A33=0,0,IFERROR(SUMIFS([1]Population!O:O,[1]Population!J:J,'MASTER-2025'!A33),0)) -> 0 | Z33: =IFERROR(VLOOKUP($A33,'[1]Donor-Served OBs'!A:N,6,0),0) -> 0 | AA33: =ROUNDUP(IF(A33=0,0,IFERROR(VLOOKUP($A33,'[1]Donor''s Assigned Kilos'!A:N,11,0),0)),0) -> 0 | AB33: =IF(A33=0,0,IFERROR(SUMIFS([1]Population!U:U,[1]Population!J:J,'MASTER-2025'!A33),0)) -> 0 | AC33: =IFERROR(VLOOKUP($A33,'[1]Donor-Served OBs'!A:N,7,0),0) -> 0 | AD33: =ROUNDUP(IF(A33=0,0,IFERROR(VLOOKUP($A33,'[1]Donor''s Assigned Kilos'!A:N,8,0),0)),0) -> 0 | AE33: =IF(A33=0,0,IFERROR(SUMIFS([1]Population!R:R,[1]Population!J:J,'MASTER-2025'!A33),0)) -> 0 | AF33: =IFERROR(VLOOKUP($A33,'[1]Donor-Served OBs'!A:N,8,0),0) -> 0 | AG33: =ROUNDUP(IF(A33=0,0,IFERROR(VLOOKUP($A33,'[1]Donor''s Assigned Kilos'!A:N,6,0),0)),0) -> 0 | AH33: =IF(A33=0,0,IFERROR(SUMIFS([1]Population!P:P,[1]Population!J:J,'MASTER-2025'!A33),0)) -> 0 | AI33: =IFERROR(VLOOKUP($A33,'[1]Donor-Served OBs'!A:N,9,0),0) -> 0 | AJ33: =ROUNDUP(IF(A33=0,0,IFERROR(VLOOKUP($A33,'[1]Donor''s Assigned Kilos'!A:N,12,0),0)),0) -> 0 | AK33: =IF(A33=0,0,IFERROR(SUMIFS([1]Population!V:V,[1]Population!J:J,'MASTER-2025'!A33),0)) -> 0 | AL33: =IFERROR(VLOOKUP($A33,'[1]Donor-Served OBs'!A:N,16,0),0) -> 0 | AM33: =ROUNDUP(IF(A33=0,0,IFERROR(VLOOKUP($A33,'[1]Donor''s Assigned Kilos'!A:O,16,0),0)),0) -> 0 | AN33: =IF(A33=0,0,IFERROR(SUMIFS([1]Population!Z:Z,[1]Population!J:J,'MASTER-2025'!A33),0)) -> 0 | AO33: =IFERROR(VLOOKUP($A33,'[1]Donor-Served OBs'!A:N,11,0),0) -> 0 | AP33: =ROUNDUP(IF(A33=0,0,IFERROR(VLOOKUP($A33,'[1]Donor''s Assigned Kilos'!A:N,13,0),0)),0) -> 0 | AQ33: =IF(A33=0,0,IFERROR(SUMIFS([1]Population!W:W,[1]Population!J:J,'MASTER-2025'!A33),0)) -> 0 | AR33: =IFERROR(VLOOKUP($A33,'[1]Donor-Served OBs'!A:N,5,0),0) -> 0 | AS33: =ROUNDUP(IF(A33=0,0,IFERROR(VLOOKUP($A33,'[1]Donor''s Assigned Kilos'!A:N,10,0),0)),0) -> 0 | AT33: =IF(A33=0,0,IFERROR(SUMIFS([1]Population!T:T,[1]Population!J:J,'MASTER-2025'!A33),0)) -> 0 | AU33: =IFERROR(VLOOKUP($A33,'[1]Donor-Served OBs'!A:N,13,0),0) -> 0 | AV33: =ROUNDUP(IF(A33=0,0,IFERROR(VLOOKUP($A33,'[1]Donor''s Assigned Kilos'!A:N,14,0),0)),0) -> 0 | AW33: =IF(A33=0,0,IFERROR(SUMIFS([1]Population!X:X,[1]Population!J:J,'MASTER-2025'!A33),0)) -> 0 | AX33: =IFERROR(VLOOKUP($A33,'[1]Donor-Served OBs'!A:N,16,0),0) -> 0 | AY33: =ROUNDUP(IF(A33=0,0,IFERROR(VLOOKUP($A33,'[1]Donor''s Assigned Kilos'!A:O,16,0),0)),0) -> 0 | AZ33: =IF(A33=0,0,IFERROR(SUMIFS([1]Population!Y:Y,[1]Population!J:J,'MASTER-2025'!A33),0)) -> 0 | BA33: =+H33+K33+N33+Q33+T33+W33+Z33+AC33+AF33+AI33+AL33+AO33+AR33+AU33+AX33 -> 0 | BB33: =INT(I33+L33+O33+R33+U33+X33+AA33+AD33+AG33+AJ33+AM33+AP33+AS33+AV33+AY33) -> 0 | BC33: =ROUND(I33+L33+O33+R33+U33,0) -> 0 | BD33: =IF(A33=0,0,(+J33+M33+P33+S33+V33+Y33+AB33+AE33+AH33+AK33+AN33+AQ33+AT33+AW33+AZ33)) -> 0 | BE33: =IF(A33=0,0,SUMIFS([1]Population!C:C,[1]Population!A:A,'MASTER-2025'!A33)) -> #VALUE! | BF33: =IF(A33=0,0,SUMIFS([1]Population!D:D,[1]Population!A:A,'MASTER-2025'!A33)) -> #VALUE! | BG33: =IF(A33=0,0,SUMIFS([1]Population!E:E,[1]Population!A:A,'MASTER-2025'!A33)) -> #VALUE! | BH33: =IF(A33=0,0,SUMIFS([1]Population!F:F,[1]Population!A:A,'MASTER-2025'!A33)) -> #VALUE! | BI33: =+BF33+BG33+BH33 -> #VALUE! | BJ33: =+BK33-BI33-BH33-BG33-BF33-BE33 -> #VALUE! | BK33: =IF(A33=0,0,SUMIFS([1]Population!G:G,[1]Population!A:A,'MASTER-2025'!A33)) -> #VALUE! | BL33: {=IFERROR(VLOOKUP(A33,'[1]Now-OB-kg-POB-25'!A:AQ,{3,4,5,6,7,8,9,10,11,12,13,14},0),0)} -> 0 | BM33: 0 | BN33: 0 | BO33: 0 | BP33: 0 | BQ33: 0 | BR33: 0 | BS33: 0 | BT33: 0 | BU33: 0 | BV33: 0 | BW33: 0 | BX33: =SUM(BL33:BW33) -> 0 | BY33: {=IFERROR(VLOOKUP(A33,'[1]Now-OB-kg-POB-25'!A:AQ,{17,18,19,20,21,22,23,24,25,26,27,28},0),0)} -> 0 | BZ33: 0 | CA33: 0 | CB33: 0 | CC33: 0 | CD33: 0 | CE33: 0 | CF33: 0 | CG33: 0 | CH33: 0 | CI33: 0 | CJ33: 0 | CK33: =SUM(BY33:CJ33) -> 0 | CL33: {=IFERROR(VLOOKUP(A33,'[1]Now-OB-kg-POB-25'!A:AQ,{31,32,33,34,35,36,37,38,39,40,41,42},0),0)} -> 0 | CM33: 0 | CN33: 0 | CO33: 0 | CP33: 0 | CQ33: 0 | CR33: 0 | CS33: 0 | CT33: 0 | CU33: 0 | CV33: 0 | CW33: 0 | CX33: =SUM(CL33:CW33) -> 0 | CY33: =IF(A33=0,0,IFERROR(VLOOKUP(A33,'[1]Info Donantes'!C:F,2,0),"Sin Contacto")) -> Itzel Tejeira | CZ33: =IF(A33=0,0,IFERROR(VLOOKUP(A33,'[1]Info Donantes'!C:F,3,0),"Sin Correo")) -> itzeltejeira@gmail.com | DA33: =IF(A33=0,0,IFERROR(VLOOKUP(A33,'[1]Info Donantes'!C:F,4,0),"Sin Telefono")) -> 232 6790 | DB33: Traceability Report - - REPRESENTACIONES TEJEIRA, S.A
A34: SALVA - SEA, | B34: =INT(IFERROR(VLOOKUP(A34,'[1]Donor Summary'!C:F,3,0),0)) -> 0 | C34: =INT(ROUND(IFERROR(VLOOKUP(A34,'[1]Donor Summary'!C:F,4,0),0),1)) -> 0 | D34: =INT(ROUND(C34-B34,1)) -> 0 | E34: =IF(A34=0,"",TEXT((IFERROR(D34/C34,0)),"0.00%")) -> 0.00% | F34: =IF(A34=0,"",TEXT((IFERROR(B34/C34,0)),"0.0%")) -> 0.0% | G34: =INT(D34*3) -> 0 | I34: =IFERROR(VLOOKUP(A34,'[1]Lot All by Part'!T:Y,6,0),0) -> 0 | J34: =+H34*55 -> 0 | K34: =IFERROR(VLOOKUP($A34,'[1]Donor-Served OBs'!A:N,3,0),0) -> 0 | L34: =ROUNDUP(IF(A34=0,0,IFERROR(VLOOKUP($A34,'[1]Donor''s Assigned Kilos'!A:O,3,0),0)),0) -> 0 | M34: =IF(A34=0,0,IFERROR(SUMIFS([1]Population!M:M,[1]Population!J:J,'MASTER-2025'!A34),0)) -> 0 | N34: =IFERROR(VLOOKUP($A34,'[1]Donor-Served OBs'!A:N,4,0),0) -> 0 | O34: =ROUNDUP(IF(A34=0,0,IFERROR(VLOOKUP($A34,'[1]Donor''s Assigned Kilos'!A:O,4,0),0)),0) -> 0 | P34: =IF(A34=0,0,IFERROR(SUMIFS([1]Population!N:N,[1]Population!J:J,'MASTER-2025'!A34),0)) -> 0 | Q34: =IFERROR(VLOOKUP($A34,'[1]Donor-Served OBs'!A:N,2,0),0) -> 0 | R34: =ROUNDUP(ROUND(IF(A34=0,0,IFERROR(VLOOKUP($A34,'[1]Donor''s Assigned Kilos'!A:O,9,0),0)),1),0) -> 0 | S34: =IF(A34=0,0,IFERROR(SUMIFS([1]Population!S:S,[1]Population!J:J,'MASTER-2025'!A34),0)) -> 0 | T34: =IFERROR(VLOOKUP($A34,'[1]Donor-Served OBs'!A:N,12,0),0) -> 0 | U34: =ROUNDUP(IF(A34=0,0,IF(A34=0,0,IFERROR(VLOOKUP($A34,'[1]Donor''s Assigned Kilos'!A:O,7,0),0))),0) -> 0 | V34: =IF(A34=0,0,IFERROR(SUMIFS([1]Population!Q:Q,[1]Population!J:J,'MASTER-2025'!A34),0)) -> 0 | W34: =IFERROR(VLOOKUP($A34,'[1]Donor-Served OBs'!A:N,10,0),0) -> 0 | X34: =ROUNDUP(IF(A34=0,0,IFERROR(VLOOKUP($A34,'[1]Donor''s Assigned Kilos'!A:N,5,0),0)),0) -> 0 | Y34: =IF(A34=0,0,IFERROR(SUMIFS([1]Population!O:O,[1]Population!J:J,'MASTER-2025'!A34),0)) -> 0 | Z34: =IFERROR(VLOOKUP($A34,'[1]Donor-Served OBs'!A:N,6,0),0) -> 0 | AA34: =ROUNDUP(IF(A34=0,0,IFERROR(VLOOKUP($A34,'[1]Donor''s Assigned Kilos'!A:N,11,0),0)),0) -> 0 | AB34: =IF(A34=0,0,IFERROR(SUMIFS([1]Population!U:U,[1]Population!J:J,'MASTER-2025'!A34),0)) -> 0 | AC34: =IFERROR(VLOOKUP($A34,'[1]Donor-Served OBs'!A:N,7,0),0) -> 0 | AD34: =ROUNDUP(IF(A34=0,0,IFERROR(VLOOKUP($A34,'[1]Donor''s Assigned Kilos'!A:N,8,0),0)),0) -> 0 | AE34: =IF(A34=0,0,IFERROR(SUMIFS([1]Population!R:R,[1]Population!J:J,'MASTER-2025'!A34),0)) -> 0 | AF34: =IFERROR(VLOOKUP($A34,'[1]Donor-Served OBs'!A:N,8,0),0) -> 0 | AG34: =ROUNDUP(IF(A34=0,0,IFERROR(VLOOKUP($A34,'[1]Donor''s Assigned Kilos'!A:N,6,0),0)),0) -> 0 | AH34: =IF(A34=0,0,IFERROR(SUMIFS([1]Population!P:P,[1]Population!J:J,'MASTER-2025'!A34),0)) -> 0 | AI34: =IFERROR(VLOOKUP($A34,'[1]Donor-Served OBs'!A:N,9,0),0) -> 0 | AJ34: =ROUNDUP(IF(A34=0,0,IFERROR(VLOOKUP($A34,'[1]Donor''s Assigned Kilos'!A:N,12,0),0)),0) -> 0 | AK34: =IF(A34=0,0,IFERROR(SUMIFS([1]Population!V:V,[1]Population!J:J,'MASTER-2025'!A34),0)) -> 0 | AL34: =IFERROR(VLOOKUP($A34,'[1]Donor-Served OBs'!A:N,16,0),0) -> 0 | AM34: =ROUNDUP(IF(A34=0,0,IFERROR(VLOOKUP($A34,'[1]Donor''s Assigned Kilos'!A:O,16,0),0)),0) -> 0 | AN34: =IF(A34=0,0,IFERROR(SUMIFS([1]Population!Z:Z,[1]Population!J:J,'MASTER-2025'!A34),0)) -> 0 | AO34: =IFERROR(VLOOKUP($A34,'[1]Donor-Served OBs'!A:N,11,0),0) -> 0 | AP34: =ROUNDUP(IF(A34=0,0,IFERROR(VLOOKUP($A34,'[1]Donor''s Assigned Kilos'!A:N,13,0),0)),0) -> 0 | AQ34: =IF(A34=0,0,IFERROR(SUMIFS([1]Population!W:W,[1]Population!J:J,'MASTER-2025'!A34),0)) -> 0 | AR34: =IFERROR(VLOOKUP($A34,'[1]Donor-Served OBs'!A:N,5,0),0) -> 0 | AS34: =ROUNDUP(IF(A34=0,0,IFERROR(VLOOKUP($A34,'[1]Donor''s Assigned Kilos'!A:N,10,0),0)),0) -> 0 | AT34: =IF(A34=0,0,IFERROR(SUMIFS([1]Population!T:T,[1]Population!J:J,'MASTER-2025'!A34),0)) -> 0 | AU34: =IFERROR(VLOOKUP($A34,'[1]Donor-Served OBs'!A:N,13,0),0) -> 0 | AV34: =ROUNDUP(IF(A34=0,0,IFERROR(VLOOKUP($A34,'[1]Donor''s Assigned Kilos'!A:N,14,0),0)),0) -> 0 | AW34: =IF(A34=0,0,IFERROR(SUMIFS([1]Population!X:X,[1]Population!J:J,'MASTER-2025'!A34),0)) -> 0 | AX34: =IFERROR(VLOOKUP($A34,'[1]Donor-Served OBs'!A:N,16,0),0) -> 0 | AY34: =ROUNDUP(IF(A34=0,0,IFERROR(VLOOKUP($A34,'[1]Donor''s Assigned Kilos'!A:O,16,0),0)),0) -> 0 | AZ34: =IF(A34=0,0,IFERROR(SUMIFS([1]Population!Y:Y,[1]Population!J:J,'MASTER-2025'!A34),0)) -> 0 | BA34: =+H34+K34+N34+Q34+T34+W34+Z34+AC34+AF34+AI34+AL34+AO34+AR34+AU34+AX34 -> 0 | BB34: =INT(I34+L34+O34+R34+U34+X34+AA34+AD34+AG34+AJ34+AM34+AP34+AS34+AV34+AY34) -> 0 | BC34: =ROUND(I34+L34+O34+R34+U34,0) -> 0 | BD34: =IF(A34=0,0,(+J34+M34+P34+S34+V34+Y34+AB34+AE34+AH34+AK34+AN34+AQ34+AT34+AW34+AZ34)) -> 0 | BE34: =IF(A34=0,0,SUMIFS([1]Population!C:C,[1]Population!A:A,'MASTER-2025'!A34)) -> #VALUE! | BF34: =IF(A34=0,0,SUMIFS([1]Population!D:D,[1]Population!A:A,'MASTER-2025'!A34)) -> #VALUE! | BG34: =IF(A34=0,0,SUMIFS([1]Population!E:E,[1]Population!A:A,'MASTER-2025'!A34)) -> #VALUE! | BH34: =IF(A34=0,0,SUMIFS([1]Population!F:F,[1]Population!A:A,'MASTER-2025'!A34)) -> #VALUE! | BI34: =+BF34+BG34+BH34 -> #VALUE! | BJ34: =+BK34-BI34-BH34-BG34-BF34-BE34 -> #VALUE! | BK34: =IF(A34=0,0,SUMIFS([1]Population!G:G,[1]Population!A:A,'MASTER-2025'!A34)) -> #VALUE! | BL34: {=IFERROR(VLOOKUP(A34,'[1]Now-OB-kg-POB-25'!A:AQ,{3,4,5,6,7,8,9,10,11,12,13,14},0),0)} -> 64 | BM34: 26 | BN34: 43 | BO34: 0 | BP34: 0 | BQ34: 0 | BR34: 0 | BS34: 0 | BT34: 0 | BU34: 0 | BV34: 0 | BW34: 0 | BX34: =SUM(BL34:BW34) -> 133 | BY34: {=IFERROR(VLOOKUP(A34,'[1]Now-OB-kg-POB-25'!A:AQ,{17,18,19,20,21,22,23,24,25,26,27,28},0),0)} -> 1040 | BZ34: 1007 | CA34: 1021 | CB34: 0 | CC34: 0 | CD34: 0 | CE34: 0 | CF34: 0 | CG34: 0 | CH34: 0 | CI34: 0 | CJ34: 0 | CK34: =SUM(BY34:CJ34) -> 3068 | CL34: {=IFERROR(VLOOKUP(A34,'[1]Now-OB-kg-POB-25'!A:AQ,{31,32,33,34,35,36,37,38,39,40,41,42},0),0)} -> 9401 | CM34: 5731 | CN34: 12682 | CO34: 0 | CP34: 0 | CQ34: 0 | CR34: 0 | CS34: 0 | CT34: 0 | CU34: 0 | CV34: 0 | CW34: 0 | CX34: =SUM(CL34:CW34) -> 27814 | CY34: =IF(A34=0,0,IFERROR(VLOOKUP(A34,'[1]Info Donantes'!C:F,2,0),"Sin Contacto")) -> Sin Contacto | CZ34: =IF(A34=0,0,IFERROR(VLOOKUP(A34,'[1]Info Donantes'!C:F,3,0),"Sin Correo")) -> Sin Correo | DA34: =IF(A34=0,0,IFERROR(VLOOKUP(A34,'[1]Info Donantes'!C:F,4,0),"Sin Telefono")) -> Sin Telefono | DB34: Traceability Report - - SAVE - SEA,
A35: SUPER MEATS | B35: =INT(IFERROR(VLOOKUP(A35,'[1]Donor Summary'!C:F,3,0),0)) -> 0 | C35: =INT(ROUND(IFERROR(VLOOKUP(A35,'[1]Donor Summary'!C:F,4,0),0),1)) -> 0 | D35: =INT(ROUND(C35-B35,1)) -> 0 | E35: =IF(A35=0,"",TEXT((IFERROR(D35/C35,0)),"0.00%")) -> 0.00% | F35: =IF(A35=0,"",TEXT((IFERROR(B35/C35,0)),"0.0%")) -> 0.0% | G35: =INT(D35*3) -> 0 | I35: =IFERROR(VLOOKUP(A35,'[1]Lot All by Part'!T:Y,6,0),0) -> 0 | K35: =IFERROR(VLOOKUP($A35,'[1]Donor-Served OBs'!A:N,3,0),0) -> 0 | L35: =ROUNDUP(IF(A35=0,0,IFERROR(VLOOKUP($A35,'[1]Donor''s Assigned Kilos'!A:O,3,0),0)),0) -> 0 | M35: =IF(A35=0,0,IFERROR(SUMIFS([1]Population!M:M,[1]Population!J:J,'MASTER-2025'!A35),0)) -> 0 | N35: =IFERROR(VLOOKUP($A35,'[1]Donor-Served OBs'!A:N,4,0),0) -> 0 | O35: =ROUNDUP(IF(A35=0,0,IFERROR(VLOOKUP($A35,'[1]Donor''s Assigned Kilos'!A:O,4,0),0)),0) -> 0 | P35: =IF(A35=0,0,IFERROR(SUMIFS([1]Population!N:N,[1]Population!J:J,'MASTER-2025'!A35),0)) -> 0 | Q35: =IFERROR(VLOOKUP($A35,'[1]Donor-Served OBs'!A:N,2,0),0) -> 0 | R35: =ROUNDUP(ROUND(IF(A35=0,0,IFERROR(VLOOKUP($A35,'[1]Donor''s Assigned Kilos'!A:O,9,0),0)),1),0) -> 0 | S35: =IF(A35=0,0,IFERROR(SUMIFS([1]Population!S:S,[1]Population!J:J,'MASTER-2025'!A35),0)) -> 0 | T35: =IFERROR(VLOOKUP($A35,'[1]Donor-Served OBs'!A:N,12,0),0) -> 0 | U35: =ROUNDUP(IF(A35=0,0,IF(A35=0,0,IFERROR(VLOOKUP($A35,'[1]Donor''s Assigned Kilos'!A:O,7,0),0))),0) -> 0 | V35: =IF(A35=0,0,IFERROR(SUMIFS([1]Population!Q:Q,[1]Population!J:J,'MASTER-2025'!A35),0)) -> 0 | W35: =IFERROR(VLOOKUP($A35,'[1]Donor-Served OBs'!A:N,10,0),0) -> 0 | X35: =ROUNDUP(IF(A35=0,0,IFERROR(VLOOKUP($A35,'[1]Donor''s Assigned Kilos'!A:N,5,0),0)),0) -> 0 | Y35: =IF(A35=0,0,IFERROR(SUMIFS([1]Population!O:O,[1]Population!J:J,'MASTER-2025'!A35),0)) -> 0 | Z35: =IFERROR(VLOOKUP($A35,'[1]Donor-Served OBs'!A:N,6,0),0) -> 0 | AA35: =ROUNDUP(IF(A35=0,0,IFERROR(VLOOKUP($A35,'[1]Donor''s Assigned Kilos'!A:N,11,0),0)),0) -> 0 | AB35: =IF(A35=0,0,IFERROR(SUMIFS([1]Population!U:U,[1]Population!J:J,'MASTER-2025'!A35),0)) -> 0 | AC35: =IFERROR(VLOOKUP($A35,'[1]Donor-Served OBs'!A:N,7,0),0) -> 0 | AD35: =ROUNDUP(IF(A35=0,0,IFERROR(VLOOKUP($A35,'[1]Donor''s Assigned Kilos'!A:N,8,0),0)),0) -> 0 | AE35: =IF(A35=0,0,IFERROR(SUMIFS([1]Population!R:R,[1]Population!J:J,'MASTER-2025'!A35),0)) -> 0 | AF35: =IFERROR(VLOOKUP($A35,'[1]Donor-Served OBs'!A:N,8,0),0) -> 0 | AG35: =ROUNDUP(IF(A35=0,0,IFERROR(VLOOKUP($A35,'[1]Donor''s Assigned Kilos'!A:N,6,0),0)),0) -> 0 | AH35: =IF(A35=0,0,IFERROR(SUMIFS([1]Population!P:P,[1]Population!J:J,'MASTER-2025'!A35),0)) -> 0 | AI35: =IFERROR(VLOOKUP($A35,'[1]Donor-Served OBs'!A:N,9,0),0) -> 0 | AJ35: =ROUNDUP(IF(A35=0,0,IFERROR(VLOOKUP($A35,'[1]Donor''s Assigned Kilos'!A:N,12,0),0)),0) -> 0 | AK35: =IF(A35=0,0,IFERROR(SUMIFS([1]Population!V:V,[1]Population!J:J,'MASTER-2025'!A35),0)) -> 0 | AL35: =IFERROR(VLOOKUP($A35,'[1]Donor-Served OBs'!A:N,16,0),0) -> 0 | AM35: =ROUNDUP(IF(A35=0,0,IFERROR(VLOOKUP($A35,'[1]Donor''s Assigned Kilos'!A:O,16,0),0)),0) -> 0 | AN35: =IF(A35=0,0,IFERROR(SUMIFS([1]Population!Z:Z,[1]Population!J:J,'MASTER-2025'!A35),0)) -> 0 | AO35: =IFERROR(VLOOKUP($A35,'[1]Donor-Served OBs'!A:N,11,0),0) -> 0 | AP35: =ROUNDUP(IF(A35=0,0,IFERROR(VLOOKUP($A35,'[1]Donor''s Assigned Kilos'!A:N,13,0),0)),0) -> 0 | AQ35: =IF(A35=0,0,IFERROR(SUMIFS([1]Population!W:W,[1]Population!J:J,'MASTER-2025'!A35),0)) -> 0 | AR35: =IFERROR(VLOOKUP($A35,'[1]Donor-Served OBs'!A:N,5,0),0) -> 0 | AS35: =ROUNDUP(IF(A35=0,0,IFERROR(VLOOKUP($A35,'[1]Donor''s Assigned Kilos'!A:N,10,0),0)),0) -> 0 | AT35: =IF(A35=0,0,IFERROR(SUMIFS([1]Population!T:T,[1]Population!J:J,'MASTER-2025'!A35),0)) -> 0 | AU35: =IFERROR(VLOOKUP($A35,'[1]Donor-Served OBs'!A:N,13,0),0) -> 0 | AV35: =ROUNDUP(IF(A35=0,0,IFERROR(VLOOKUP($A35,'[1]Donor''s Assigned Kilos'!A:N,14,0),0)),0) -> 0 | AW35: =IF(A35=0,0,IFERROR(SUMIFS([1]Population!X:X,[1]Population!J:J,'MASTER-2025'!A35),0)) -> 0 | AX35: =IFERROR(VLOOKUP($A35,'[1]Donor-Served OBs'!A:N,16,0),0) -> 0 | AY35: =ROUNDUP(IF(A35=0,0,IFERROR(VLOOKUP($A35,'[1]Donor''s Assigned Kilos'!A:O,16,0),0)),0) -> 0 | AZ35: =IF(A35=0,0,IFERROR(SUMIFS([1]Population!Y:Y,[1]Population!J:J,'MASTER-2025'!A35),0)) -> 0 | BA35: =+H35+K35+N35+Q35+T35+W35+Z35+AC35+AF35+AI35+AL35+AO35+AR35+AU35+AX35 -> 0 | BB35: =INT(I35+L35+O35+R35+U35+X35+AA35+AD35+AG35+AJ35+AM35+AP35+AS35+AV35+AY35) -> 0 | BC35: =ROUND(I35+L35+O35+R35+U35,0) -> 0 | BD35: =IF(A35=0,0,(+J35+M35+P35+S35+V35+Y35+AB35+AE35+AH35+AK35+AN35+AQ35+AT35+AW35+AZ35)) -> 0 | BE35: =IF(A35=0,0,SUMIFS([1]Population!C:C,[1]Population!A:A,'MASTER-2025'!A35)) -> #VALUE! | BF35: =IF(A35=0,0,SUMIFS([1]Population!D:D,[1]Population!A:A,'MASTER-2025'!A35)) -> #VALUE! | BG35: =IF(A35=0,0,SUMIFS([1]Population!E:E,[1]Population!A:A,'MASTER-2025'!A35)) -> #VALUE! | BH35: =IF(A35=0,0,SUMIFS([1]Population!F:F,[1]Population!A:A,'MASTER-2025'!A35)) -> #VALUE! | BI35: =+BF35+BG35+BH35 -> #VALUE! | BJ35: =+BK35-BI35-BH35-BG35-BF35-BE35 -> #VALUE! | BK35: =IF(A35=0,0,SUMIFS([1]Population!G:G,[1]Population!A:A,'MASTER-2025'!A35)) -> #VALUE! | BL35: {=IFERROR(VLOOKUP(A35,'[1]Now-OB-kg-POB-25'!A:AQ,{3,4,5,6,7,8,9,10,11,12,13,14},0),0)} -> 14 | BM35: 16 | BN35: 18 | BO35: 0 | BP35: 0 | BQ35: 0 | BR35: 0 | BS35: 0 | BT35: 0 | BU35: 0 | BV35: 0 | BW35: 0 | BX35: =SUM(BL35:BW35) -> 48 | BY35: {=IFERROR(VLOOKUP(A35,'[1]Now-OB-kg-POB-25'!A:AQ,{17,18,19,20,21,22,23,24,25,26,27,28},0),0)} -> 3130 | BZ35: 2993 | CA35: 3799 | CB35: 0 | CC35: 0 | CD35: 0 | CE35: 0 | CF35: 0 | CG35: 0 | CH35: 0 | CI35: 0 | CJ35: 0 | CK35: =SUM(BY35:CJ35) -> 9922 | CL35: {=IFERROR(VLOOKUP(A35,'[1]Now-OB-kg-POB-25'!A:AQ,{31,32,33,34,35,36,37,38,39,40,41,42},0),0)} -> 1750 | CM35: 2418 | CN35: 2155 | CO35: 0 | CP35: 0 | CQ35: 0 | CR35: 0 | CS35: 0 | CT35: 0 | CU35: 0 | CV35: 0 | CW35: 0 | CX35: =SUM(CL35:CW35) -> 6323 | CY35: =IF(A35=0,0,IFERROR(VLOOKUP(A35,'[1]Info Donantes'!C:F,2,0),"Sin Contacto")) -> Sin Contacto | CZ35: =IF(A35=0,0,IFERROR(VLOOKUP(A35,'[1]Info Donantes'!C:F,3,0),"Sin Correo")) -> Sin Correo | DA35: =IF(A35=0,0,IFERROR(VLOOKUP(A35,'[1]Info Donantes'!C:F,4,0),"Sin Telefono")) -> Sin Telefono | DB35: Traceability Report - - SUPER MEATS
A36: VENTAS Y MERCADEO, S.A | B36: =INT(IFERROR(VLOOKUP(A36,'[1]Donor Summary'!C:F,3,0),0)) -> 0 | C36: =INT(ROUND(IFERROR(VLOOKUP(A36,'[1]Donor Summary'!C:F,4,0),0),1)) -> 0 | D36: =INT(ROUND(C36-B36,1)) -> 0 | E36: =IF(A36=0,"",TEXT((IFERROR(D36/C36,0)),"0.00%")) -> 0.00% | F36: =IF(A36=0,"",TEXT((IFERROR(B36/C36,0)),"0.0%")) -> 0.0% | G36: =INT(D36*3) -> 0 | I36: =IFERROR(VLOOKUP(A36,'[1]Lot All by Part'!T:Y,6,0),0) -> 0 | K36: =IFERROR(VLOOKUP($A36,'[1]Donor-Served OBs'!A:N,3,0),0) -> 0 | L36: =ROUNDUP(IF(A36=0,0,IFERROR(VLOOKUP($A36,'[1]Donor''s Assigned Kilos'!A:O,3,0),0)),0) -> 0 | M36: =IF(A36=0,0,IFERROR(SUMIFS([1]Population!M:M,[1]Population!J:J,'MASTER-2025'!A36),0)) -> 0 | N36: =IFERROR(VLOOKUP($A36,'[1]Donor-Served OBs'!A:N,4,0),0) -> 0 | O36: =ROUNDUP(IF(A36=0,0,IFERROR(VLOOKUP($A36,'[1]Donor''s Assigned Kilos'!A:O,4,0),0)),0) -> 0 | P36: =IF(A36=0,0,IFERROR(SUMIFS([1]Population!N:N,[1]Population!J:J,'MASTER-2025'!A36),0)) -> 0 | Q36: =IFERROR(VLOOKUP($A36,'[1]Donor-Served OBs'!A:N,2,0),0) -> 0 | R36: =ROUNDUP(ROUND(IF(A36=0,0,IFERROR(VLOOKUP($A36,'[1]Donor''s Assigned Kilos'!A:O,9,0),0)),1),0) -> 0 | S36: =IF(A36=0,0,IFERROR(SUMIFS([1]Population!S:S,[1]Population!J:J,'MASTER-2025'!A36),0)) -> 0 | T36: =IFERROR(VLOOKUP($A36,'[1]Donor-Served OBs'!A:N,12,0),0) -> 0 | U36: =ROUNDUP(IF(A36=0,0,IF(A36=0,0,IFERROR(VLOOKUP($A36,'[1]Donor''s Assigned Kilos'!A:O,7,0),0))),0) -> 0 | V36: =IF(A36=0,0,IFERROR(SUMIFS([1]Population!Q:Q,[1]Population!J:J,'MASTER-2025'!A36),0)) -> 0 | W36: =IFERROR(VLOOKUP($A36,'[1]Donor-Served OBs'!A:N,10,0),0) -> 0 | X36: =ROUNDUP(IF(A36=0,0,IFERROR(VLOOKUP($A36,'[1]Donor''s Assigned Kilos'!A:N,5,0),0)),0) -> 0 | Y36: =IF(A36=0,0,IFERROR(SUMIFS([1]Population!O:O,[1]Population!J:J,'MASTER-2025'!A36),0)) -> 0 | Z36: =IFERROR(VLOOKUP($A36,'[1]Donor-Served OBs'!A:N,6,0),0) -> 0 | AA36: =ROUNDUP(IF(A36=0,0,IFERROR(VLOOKUP($A36,'[1]Donor''s Assigned Kilos'!A:N,11,0),0)),0) -> 0 | AB36: =IF(A36=0,0,IFERROR(SUMIFS([1]Population!U:U,[1]Population!J:J,'MASTER-2025'!A36),0)) -> 0 | AC36: =IFERROR(VLOOKUP($A36,'[1]Donor-Served OBs'!A:N,7,0),0) -> 0 | AD36: =ROUNDUP(IF(A36=0,0,IFERROR(VLOOKUP($A36,'[1]Donor''s Assigned Kilos'!A:N,8,0),0)),0) -> 0 | AE36: =IF(A36=0,0,IFERROR(SUMIFS([1]Population!R:R,[1]Population!J:J,'MASTER-2025'!A36),0)) -> 0 | AF36: =IFERROR(VLOOKUP($A36,'[1]Donor-Served OBs'!A:N,8,0),0) -> 0 | AG36: =ROUNDUP(IF(A36=0,0,IFERROR(VLOOKUP($A36,'[1]Donor''s Assigned Kilos'!A:N,6,0),0)),0) -> 0 | AH36: =IF(A36=0,0,IFERROR(SUMIFS([1]Population!P:P,[1]Population!J:J,'MASTER-2025'!A36),0)) -> 0 | AI36: =IFERROR(VLOOKUP($A36,'[1]Donor-Served OBs'!A:N,9,0),0) -> 0 | AJ36: =ROUNDUP(IF(A36=0,0,IFERROR(VLOOKUP($A36,'[1]Donor''s Assigned Kilos'!A:N,12,0),0)),0) -> 0 | AK36: =IF(A36=0,0,IFERROR(SUMIFS([1]Population!V:V,[1]Population!J:J,'MASTER-2025'!A36),0)) -> 0 | AL36: =IFERROR(VLOOKUP($A36,'[1]Donor-Served OBs'!A:N,16,0),0) -> 0 | AM36: =ROUNDUP(IF(A36=0,0,IFERROR(VLOOKUP($A36,'[1]Donor''s Assigned Kilos'!A:O,16,0),0)),0) -> 0 | AN36: =IF(A36=0,0,IFERROR(SUMIFS([1]Population!Z:Z,[1]Population!J:J,'MASTER-2025'!A36),0)) -> 0 | AO36: =IFERROR(VLOOKUP($A36,'[1]Donor-Served OBs'!A:N,11,0),0) -> 0 | AP36: =ROUNDUP(IF(A36=0,0,IFERROR(VLOOKUP($A36,'[1]Donor''s Assigned Kilos'!A:N,13,0),0)),0) -> 0 | AQ36: =IF(A36=0,0,IFERROR(SUMIFS([1]Population!W:W,[1]Population!J:J,'MASTER-2025'!A36),0)) -> 0 | AR36: =IFERROR(VLOOKUP($A36,'[1]Donor-Served OBs'!A:N,5,0),0) -> 0 | AS36: =ROUNDUP(IF(A36=0,0,IFERROR(VLOOKUP($A36,'[1]Donor''s Assigned Kilos'!A:N,10,0),0)),0) -> 0 | AT36: =IF(A36=0,0,IFERROR(SUMIFS([1]Population!T:T,[1]Population!J:J,'MASTER-2025'!A36),0)) -> 0 | AU36: =IFERROR(VLOOKUP($A36,'[1]Donor-Served OBs'!A:N,13,0),0) -> 0 | AV36: =ROUNDUP(IF(A36=0,0,IFERROR(VLOOKUP($A36,'[1]Donor''s Assigned Kilos'!A:N,14,0),0)),0) -> 0 | AW36: =IF(A36=0,0,IFERROR(SUMIFS([1]Population!X:X,[1]Population!J:J,'MASTER-2025'!A36),0)) -> 0 | AX36: =IFERROR(VLOOKUP($A36,'[1]Donor-Served OBs'!A:N,16,0),0) -> 0 | AY36: =ROUNDUP(IF(A36=0,0,IFERROR(VLOOKUP($A36,'[1]Donor''s Assigned Kilos'!A:O,16,0),0)),0) -> 0 | AZ36: =IF(A36=0,0,IFERROR(SUMIFS([1]Population!Y:Y,[1]Population!J:J,'MASTER-2025'!A36),0)) -> 0 | BA36: =+H36+K36+N36+Q36+T36+W36+Z36+AC36+AF36+AI36+AL36+AO36+AR36+AU36+AX36 -> 0 | BB36: =INT(I36+L36+O36+R36+U36+X36+AA36+AD36+AG36+AJ36+AM36+AP36+AS36+AV36+AY36) -> 0 | BC36: =ROUND(I36+L36+O36+R36+U36,0) -> 0 | BD36: =IF(A36=0,0,(+J36+M36+P36+S36+V36+Y36+AB36+AE36+AH36+AK36+AN36+AQ36+AT36+AW36+AZ36)) -> 0 | BE36: =IF(A36=0,0,SUMIFS([1]Population!C:C,[1]Population!A:A,'MASTER-2025'!A36)) -> #VALUE! | BF36: =IF(A36=0,0,SUMIFS([1]Population!D:D,[1]Population!A:A,'MASTER-2025'!A36)) -> #VALUE! | BG36: =IF(A36=0,0,SUMIFS([1]Population!E:E,[1]Population!A:A,'MASTER-2025'!A36)) -> #VALUE! | BH36: =IF(A36=0,0,SUMIFS([1]Population!F:F,[1]Population!A:A,'MASTER-2025'!A36)) -> #VALUE! | BI36: =+BF36+BG36+BH36 -> #VALUE! | BJ36: =+BK36-BI36-BH36-BG36-BF36-BE36 -> #VALUE! | BK36: =IF(A36=0,0,SUMIFS([1]Population!G:G,[1]Population!A:A,'MASTER-2025'!A36)) -> #VALUE! | BL36: {=IFERROR(VLOOKUP(A36,'[1]Now-OB-kg-POB-25'!A:AQ,{3,4,5,6,7,8,9,10,11,12,13,14},0),0)} -> 0 | BM36: 0 | BN36: 0 | BO36: 0 | BP36: 0 | BQ36: 0 | BR36: 0 | BS36: 0 | BT36: 0 | BU36: 0 | BV36: 0 | BW36: 0 | BX36: =SUM(BL36:BW36) -> 0 | BY36: {=IFERROR(VLOOKUP(A36,'[1]Now-OB-kg-POB-25'!A:AQ,{17,18,19,20,21,22,23,24,25,26,27,28},0),0)} -> 0 | BZ36: 0 | CA36: 0 | CB36: 0 | CC36: 0 | CD36: 0 | CE36: 0 | CF36: 0 | CG36: 0 | CH36: 0 | CI36: 0 | CJ36: 0 | CK36: =SUM(BY36:CJ36) -> 0 | CL36: {=IFERROR(VLOOKUP(A36,'[1]Now-OB-kg-POB-25'!A:AQ,{31,32,33,34,35,36,37,38,39,40,41,42},0),0)} -> 0 | CM36: 0 | CN36: 0 | CO36: 0 | CP36: 0 | CQ36: 0 | CR36: 0 | CS36: 0 | CT36: 0 | CU36: 0 | CV36: 0 | CW36: 0 | CX36: =SUM(CL36:CW36) -> 0 | CY36: =IF(A36=0,0,IFERROR(VLOOKUP(A36,'[1]Info Donantes'!C:F,2,0),"Sin Contacto")) -> Karina Hernandez | CZ36: =IF(A36=0,0,IFERROR(VLOOKUP(A36,'[1]Info Donantes'!C:F,3,0),"Sin Correo")) -> karina.hernandezl@kof.com.mx | DA36: =IF(A36=0,0,IFERROR(VLOOKUP(A36,'[1]Info Donantes'!C:F,4,0),"Sin Telefono")) -> 274-9000 EXT. 5270 | DB36: Traceability Report - - VENTAS Y MERCADEO, S.A
A37: Colgate Palmolive (CENTRAL AMERICA) INC | B37: =INT(IFERROR(VLOOKUP(A37,'[1]Donor Summary'!C:F,3,0),0)) -> 13 | C37: =INT(ROUND(IFERROR(VLOOKUP(A37,'[1]Donor Summary'!C:F,4,0),0),1)) -> 2464 | D37: =INT(ROUND(C37-B37,1)) -> 2451 | E37: =IF(A37=0,"",TEXT((IFERROR(D37/C37,0)),"0.00%")) -> 99.47% | F37: =IF(A37=0,"",TEXT((IFERROR(B37/C37,0)),"0.0%")) -> 0.5% | G37: =INT(D37*3) -> 7353 | I37: =IFERROR(VLOOKUP(A37,'[1]Lot All by Part'!T:Y,6,0),0) -> 0 | K37: =IFERROR(VLOOKUP($A37,'[1]Donor-Served OBs'!A:N,3,0),0) -> 12 | L37: =ROUNDUP(IF(A37=0,0,IFERROR(VLOOKUP($A37,'[1]Donor''s Assigned Kilos'!A:O,3,0),0)),0) -> 161 | M37: =IF(A37=0,0,IFERROR(SUMIFS([1]Population!M:M,[1]Population!J:J,'MASTER-2025'!A37),0)) -> 0 | N37: =IFERROR(VLOOKUP($A37,'[1]Donor-Served OBs'!A:N,4,0),0) -> 21 | O37: =ROUNDUP(IF(A37=0,0,IFERROR(VLOOKUP($A37,'[1]Donor''s Assigned Kilos'!A:O,4,0),0)),0) -> 173 | P37: =IF(A37=0,0,IFERROR(SUMIFS([1]Population!N:N,[1]Population!J:J,'MASTER-2025'!A37),0)) -> 0 | Q37: =IFERROR(VLOOKUP($A37,'[1]Donor-Served OBs'!A:N,2,0),0) -> 7 | R37: =ROUNDUP(ROUND(IF(A37=0,0,IFERROR(VLOOKUP($A37,'[1]Donor''s Assigned Kilos'!A:O,9,0),0)),1),0) -> 38 | S37: =IF(A37=0,0,IFERROR(SUMIFS([1]Population!S:S,[1]Population!J:J,'MASTER-2025'!A37),0)) -> 0 | T37: =IFERROR(VLOOKUP($A37,'[1]Donor-Served OBs'!A:N,12,0),0) -> 4 | U37: =ROUNDUP(IF(A37=0,0,IF(A37=0,0,IFERROR(VLOOKUP($A37,'[1]Donor''s Assigned Kilos'!A:O,7,0),0))),0) -> 14 | V37: =IF(A37=0,0,IFERROR(SUMIFS([1]Population!Q:Q,[1]Population!J:J,'MASTER-2025'!A37),0)) -> 0 | W37: =IFERROR(VLOOKUP($A37,'[1]Donor-Served OBs'!A:N,10,0),0) -> 10 | X37: =ROUNDUP(IF(A37=0,0,IFERROR(VLOOKUP($A37,'[1]Donor''s Assigned Kilos'!A:N,5,0),0)),0) -> 84 | Y37: =IF(A37=0,0,IFERROR(SUMIFS([1]Population!O:O,[1]Population!J:J,'MASTER-2025'!A37),0)) -> 0 | Z37: =IFERROR(VLOOKUP($A37,'[1]Donor-Served OBs'!A:N,6,0),0) -> 1 | AA37: =ROUNDUP(IF(A37=0,0,IFERROR(VLOOKUP($A37,'[1]Donor''s Assigned Kilos'!A:N,11,0),0)),0) -> 40 | AB37: =IF(A37=0,0,IFERROR(SUMIFS([1]Population!U:U,[1]Population!J:J,'MASTER-2025'!A37),0)) -> 0 | AC37: =IFERROR(VLOOKUP($A37,'[1]Donor-Served OBs'!A:N,7,0),0) -> 1 | AD37: =ROUNDUP(IF(A37=0,0,IFERROR(VLOOKUP($A37,'[1]Donor''s Assigned Kilos'!A:N,8,0),0)),0) -> 29 | AE37: =IF(A37=0,0,IFERROR(SUMIFS([1]Population!R:R,[1]Population!J:J,'MASTER-2025'!A37),0)) -> 0 | AF37: =IFERROR(VLOOKUP($A37,'[1]Donor-Served OBs'!A:N,8,0),0) -> 2 | AG37: =ROUNDUP(IF(A37=0,0,IFERROR(VLOOKUP($A37,'[1]Donor''s Assigned Kilos'!A:N,6,0),0)),0) -> 14 | AH37: =IF(A37=0,0,IFERROR(SUMIFS([1]Population!P:P,[1]Population!J:J,'MASTER-2025'!A37),0)) -> 0 | AI37: =IFERROR(VLOOKUP($A37,'[1]Donor-Served OBs'!A:N,9,0),0) -> 2 | AJ37: =ROUNDUP(IF(A37=0,0,IFERROR(VLOOKUP($A37,'[1]Donor''s Assigned Kilos'!A:N,12,0),0)),0) -> 14 | AK37: =IF(A37=0,0,IFERROR(SUMIFS([1]Population!V:V,[1]Population!J:J,'MASTER-2025'!A37),0)) -> 0 | AL37: =IFERROR(VLOOKUP($A37,'[1]Donor-Served OBs'!A:N,16,0),0) -> 0 | AM37: =ROUNDUP(IF(A37=0,0,IFERROR(VLOOKUP($A37,'[1]Donor''s Assigned Kilos'!A:O,16,0),0)),0) -> 0 | AN37: =IF(A37=0,0,IFERROR(SUMIFS([1]Population!Z:Z,[1]Population!J:J,'MASTER-2025'!A37),0)) -> 0 | AO37: =IFERROR(VLOOKUP($A37,'[1]Donor-Served OBs'!A:N,11,0),0) -> 1 | AP37: =ROUNDUP(IF(A37=0,0,IFERROR(VLOOKUP($A37,'[1]Donor''s Assigned Kilos'!A:N,13,0),0)),0) -> 6 | AQ37: =IF(A37=0,0,IFERROR(SUMIFS([1]Population!W:W,[1]Population!J:J,'MASTER-2025'!A37),0)) -> 0 | AR37: =IFERROR(VLOOKUP($A37,'[1]Donor-Served OBs'!A:N,5,0),0) -> 5 | AS37: =ROUNDUP(IF(A37=0,0,IFERROR(VLOOKUP($A37,'[1]Donor''s Assigned Kilos'!A:N,10,0),0)),0) -> 34 | AT37: =IF(A37=0,0,IFERROR(SUMIFS([1]Population!T:T,[1]Population!J:J,'MASTER-2025'!A37),0)) -> 0 | AU37: =IFERROR(VLOOKUP($A37,'[1]Donor-Served OBs'!A:N,13,0),0) -> 0 | AV37: =ROUNDUP(IF(A37=0,0,IFERROR(VLOOKUP($A37,'[1]Donor''s Assigned Kilos'!A:N,14,0),0)),0) -> 0 | AW37: =IF(A37=0,0,IFERROR(SUMIFS([1]Population!X:X,[1]Population!J:J,'MASTER-2025'!A37),0)) -> 0 | AX37: =IFERROR(VLOOKUP($A37,'[1]Donor-Served OBs'!A:N,16,0),0) -> 0 | AY37: =ROUNDUP(IF(A37=0,0,IFERROR(VLOOKUP($A37,'[1]Donor''s Assigned Kilos'!A:O,16,0),0)),0) -> 0 | AZ37: =IF(A37=0,0,IFERROR(SUMIFS([1]Population!Y:Y,[1]Population!J:J,'MASTER-2025'!A37),0)) -> 0 | BA37: =+H37+K37+N37+Q37+T37+W37+Z37+AC37+AF37+AI37+AL37+AO37+AR37+AU37+AX37 -> 66 | BB37: =INT(I37+L37+O37+R37+U37+X37+AA37+AD37+AG37+AJ37+AM37+AP37+AS37+AV37+AY37) -> 607 | BC37: =ROUND(I37+L37+O37+R37+U37,0) -> 386 | BD37: =IF(A37=0,0,(+J37+M37+P37+S37+V37+Y37+AB37+AE37+AH37+AK37+AN37+AQ37+AT37+AW37+AZ37)) -> 0 | BE37: =IF(A37=0,0,SUMIFS([1]Population!C:C,[1]Population!A:A,'MASTER-2025'!A37)) -> #VALUE! | BF37: =IF(A37=0,0,SUMIFS([1]Population!D:D,[1]Population!A:A,'MASTER-2025'!A37)) -> #VALUE! | BG37: =IF(A37=0,0,SUMIFS([1]Population!E:E,[1]Population!A:A,'MASTER-2025'!A37)) -> #VALUE! | BH37: =IF(A37=0,0,SUMIFS([1]Population!F:F,[1]Population!A:A,'MASTER-2025'!A37)) -> #VALUE! | BI37: =+BF37+BG37+BH37 -> #VALUE! | BJ37: =+BK37-BI37-BH37-BG37-BF37-BE37 -> #VALUE! | BK37: =IF(A37=0,0,SUMIFS([1]Population!G:G,[1]Population!A:A,'MASTER-2025'!A37)) -> #VALUE! | BL37: {=IFERROR(VLOOKUP(A37,'[1]Now-OB-kg-POB-25'!A:AQ,{3,4,5,6,7,8,9,10,11,12,13,14},0),0)} -> 92 | BM37: 88 | BN37: 66 | BO37: 0 | BP37: 0 | BQ37: 0 | BR37: 0 | BS37: 0 | BT37: 0 | BU37: 0 | BV37: 0 | BW37: 0 | BX37: =SUM(BL37:BW37) -> 246 | BY37: {=IFERROR(VLOOKUP(A37,'[1]Now-OB-kg-POB-25'!A:AQ,{17,18,19,20,21,22,23,24,25,26,27,28},0),0)} -> 4741 | BZ37: 1030 | CA37: 2464 | CB37: 0 | CC37: 0 | CD37: 0 | CE37: 0 | CF37: 0 | CG37: 0 | CH37: 0 | CI37: 0 | CJ37: 0 | CK37: =SUM(BY37:CJ37) -> 8235 | CL37: {=IFERROR(VLOOKUP(A37,'[1]Now-OB-kg-POB-25'!A:AQ,{31,32,33,34,35,36,37,38,39,40,41,42},0),0)} -> 24800 | CM37: 24370 | CN37: 16281 | CO37: 0 | CP37: 0 | CQ37: 0 | CR37: 0 | CS37: 0 | CT37: 0 | CU37: 0 | CV37: 0 | CW37: 0 | CX37: =SUM(CL37:CW37) -> 65451 | CY37: =IF(A37=0,0,IFERROR(VLOOKUP(A37,'[1]Info Donantes'!C:F,2,0),"Sin Contacto")) -> Ramon Aguilar | CZ37: =IF(A37=0,0,IFERROR(VLOOKUP(A37,'[1]Info Donantes'!C:F,3,0),"Sin Correo")) -> ramon_a_aguilar@colpal.com | DA37: =IF(A37=0,0,IFERROR(VLOOKUP(A37,'[1]Info Donantes'!C:F,4,0),"Sin Telefono")) -> 6678-5925 | DB37: Traceability Report - - Colgate Palmolive (CENTRAL AMERICA) INC
A38: IMPORTADORA FRUTA INTERNACIONAL PANAMÁ, S.A. | B38: =INT(IFERROR(VLOOKUP(A38,'[1]Donor Summary'!C:F,3,0),0)) -> 6 | C38: =INT(ROUND(IFERROR(VLOOKUP(A38,'[1]Donor Summary'!C:F,4,0),0),1)) -> 3940 | D38: =INT(ROUND(C38-B38,1)) -> 3934 | E38: =IF(A38=0,"",TEXT((IFERROR(D38/C38,0)),"0.00%")) -> 99.85% | F38: =IF(A38=0,"",TEXT((IFERROR(B38/C38,0)),"0.0%")) -> 0.2% | G38: =INT(D38*3) -> 11802 | I38: =IFERROR(VLOOKUP(A38,'[1]Lot All by Part'!T:Y,6,0),0) -> 0 | K38: =IFERROR(VLOOKUP($A38,'[1]Donor-Served OBs'!A:N,3,0),0) -> 9 | L38: =ROUNDUP(IF(A38=0,0,IFERROR(VLOOKUP($A38,'[1]Donor''s Assigned Kilos'!A:O,3,0),0)),0) -> 632 | M38: =IF(A38=0,0,IFERROR(SUMIFS([1]Population!M:M,[1]Population!J:J,'MASTER-2025'!A38),0)) -> 0 | N38: =IFERROR(VLOOKUP($A38,'[1]Donor-Served OBs'!A:N,4,0),0) -> 18 | O38: =ROUNDUP(IF(A38=0,0,IFERROR(VLOOKUP($A38,'[1]Donor''s Assigned Kilos'!A:O,4,0),0)),0) -> 1292 | P38: =IF(A38=0,0,IFERROR(SUMIFS([1]Population!N:N,[1]Population!J:J,'MASTER-2025'!A38),0)) -> 0 | Q38: =IFERROR(VLOOKUP($A38,'[1]Donor-Served OBs'!A:N,2,0),0) -> 4 | R38: =ROUNDUP(ROUND(IF(A38=0,0,IFERROR(VLOOKUP($A38,'[1]Donor''s Assigned Kilos'!A:O,9,0),0)),1),0) -> 240 | S38: =IF(A38=0,0,IFERROR(SUMIFS([1]Population!S:S,[1]Population!J:J,'MASTER-2025'!A38),0)) -> 0 | T38: =IFERROR(VLOOKUP($A38,'[1]Donor-Served OBs'!A:N,12,0),0) -> 0 | U38: =ROUNDUP(IF(A38=0,0,IF(A38=0,0,IFERROR(VLOOKUP($A38,'[1]Donor''s Assigned Kilos'!A:O,7,0),0))),0) -> 0 | V38: =IF(A38=0,0,IFERROR(SUMIFS([1]Population!Q:Q,[1]Population!J:J,'MASTER-2025'!A38),0)) -> 0 | W38: =IFERROR(VLOOKUP($A38,'[1]Donor-Served OBs'!A:N,10,0),0) -> 6 | X38: =ROUNDUP(IF(A38=0,0,IFERROR(VLOOKUP($A38,'[1]Donor''s Assigned Kilos'!A:N,5,0),0)),0) -> 380 | Y38: =IF(A38=0,0,IFERROR(SUMIFS([1]Population!O:O,[1]Population!J:J,'MASTER-2025'!A38),0)) -> 0 | Z38: =IFERROR(VLOOKUP($A38,'[1]Donor-Served OBs'!A:N,6,0),0) -> 0 | AA38: =ROUNDUP(IF(A38=0,0,IFERROR(VLOOKUP($A38,'[1]Donor''s Assigned Kilos'!A:N,11,0),0)),0) -> 0 | AB38: =IF(A38=0,0,IFERROR(SUMIFS([1]Population!U:U,[1]Population!J:J,'MASTER-2025'!A38),0)) -> 0 | AC38: =IFERROR(VLOOKUP($A38,'[1]Donor-Served OBs'!A:N,7,0),0) -> 3 | AD38: =ROUNDUP(IF(A38=0,0,IFERROR(VLOOKUP($A38,'[1]Donor''s Assigned Kilos'!A:N,8,0),0)),0) -> 520 | AE38: =IF(A38=0,0,IFERROR(SUMIFS([1]Population!R:R,[1]Population!J:J,'MASTER-2025'!A38),0)) -> 0 | AF38: =IFERROR(VLOOKUP($A38,'[1]Donor-Served OBs'!A:N,8,0),0) -> 0 | AG38: =ROUNDUP(IF(A38=0,0,IFERROR(VLOOKUP($A38,'[1]Donor''s Assigned Kilos'!A:N,6,0),0)),0) -> 0 | AH38: =IF(A38=0,0,IFERROR(SUMIFS([1]Population!P:P,[1]Population!J:J,'MASTER-2025'!A38),0)) -> 0 | AI38: =IFERROR(VLOOKUP($A38,'[1]Donor-Served OBs'!A:N,9,0),0) -> 0 | AJ38: =ROUNDUP(IF(A38=0,0,IFERROR(VLOOKUP($A38,'[1]Donor''s Assigned Kilos'!A:N,12,0),0)),0) -> 0 | AK38: =IF(A38=0,0,IFERROR(SUMIFS([1]Population!V:V,[1]Population!J:J,'MASTER-2025'!A38),0)) -> 0 | AL38: =IFERROR(VLOOKUP($A38,'[1]Donor-Served OBs'!A:N,16,0),0) -> 0 | AM38: =ROUNDUP(IF(A38=0,0,IFERROR(VLOOKUP($A38,'[1]Donor''s Assigned Kilos'!A:O,16,0),0)),0) -> 0 | AN38: =IF(A38=0,0,IFERROR(SUMIFS([1]Population!Z:Z,[1]Population!J:J,'MASTER-2025'!A38),0)) -> 0 | AO38: =IFERROR(VLOOKUP($A38,'[1]Donor-Served OBs'!A:N,11,0),0) -> 0 | AP38: =ROUNDUP(IF(A38=0,0,IFERROR(VLOOKUP($A38,'[1]Donor''s Assigned Kilos'!A:N,13,0),0)),0) -> 0 | AQ38: =IF(A38=0,0,IFERROR(SUMIFS([1]Population!W:W,[1]Population!J:J,'MASTER-2025'!A38),0)) -> 0 | AR38: =IFERROR(VLOOKUP($A38,'[1]Donor-Served OBs'!A:N,5,0),0) -> 1 | AS38: =ROUNDUP(IF(A38=0,0,IFERROR(VLOOKUP($A38,'[1]Donor''s Assigned Kilos'!A:N,10,0),0)),0) -> 40 | AT38: =IF(A38=0,0,IFERROR(SUMIFS([1]Population!T:T,[1]Population!J:J,'MASTER-2025'!A38),0)) -> 0 | AU38: =IFERROR(VLOOKUP($A38,'[1]Donor-Served OBs'!A:N,13,0),0) -> 0 | AV38: =ROUNDUP(IF(A38=0,0,IFERROR(VLOOKUP($A38,'[1]Donor''s Assigned Kilos'!A:N,14,0),0)),0) -> 0 | AW38: =IF(A38=0,0,IFERROR(SUMIFS([1]Population!X:X,[1]Population!J:J,'MASTER-2025'!A38),0)) -> 0 | AX38: =IFERROR(VLOOKUP($A38,'[1]Donor-Served OBs'!A:N,16,0),0) -> 0 | AY38: =ROUNDUP(IF(A38=0,0,IFERROR(VLOOKUP($A38,'[1]Donor''s Assigned Kilos'!A:O,16,0),0)),0) -> 0 | AZ38: =IF(A38=0,0,IFERROR(SUMIFS([1]Population!Y:Y,[1]Population!J:J,'MASTER-2025'!A38),0)) -> 0 | BA38: =+H38+K38+N38+Q38+T38+W38+Z38+AC38+AF38+AI38+AL38+AO38+AR38+AU38+AX38 -> 41 | BB38: =INT(I38+L38+O38+R38+U38+X38+AA38+AD38+AG38+AJ38+AM38+AP38+AS38+AV38+AY38) -> 3104 | BC38: =ROUND(I38+L38+O38+R38+U38,0) -> 2164 | BD38: =IF(A38=0,0,(+J38+M38+P38+S38+V38+Y38+AB38+AE38+AH38+AK38+AN38+AQ38+AT38+AW38+AZ38)) -> 0 | BE38: =IF(A38=0,0,SUMIFS([1]Population!C:C,[1]Population!A:A,'MASTER-2025'!A38)) -> #VALUE! | BF38: =IF(A38=0,0,SUMIFS([1]Population!D:D,[1]Population!A:A,'MASTER-2025'!A38)) -> #VALUE! | BG38: =IF(A38=0,0,SUMIFS([1]Population!E:E,[1]Population!A:A,'MASTER-2025'!A38)) -> #VALUE! | BH38: =IF(A38=0,0,SUMIFS([1]Population!F:F,[1]Population!A:A,'MASTER-2025'!A38)) -> #VALUE! | BI38: =+BF38+BG38+BH38 -> #VALUE! | BJ38: =+BK38-BI38-BH38-BG38-BF38-BE38 -> #VALUE! | BK38: =IF(A38=0,0,SUMIFS([1]Population!G:G,[1]Population!A:A,'MASTER-2025'!A38)) -> #VALUE! | BL38: {=IFERROR(VLOOKUP(A38,'[1]Now-OB-kg-POB-25'!A:AQ,{3,4,5,6,7,8,9,10,11,12,13,14},0),0)} -> 7 | BM38: 7 | BN38: 41 | BO38: 0 | BP38: 0 | BQ38: 0 | BR38: 0 | BS38: 0 | BT38: 0 | BU38: 0 | BV38: 0 | BW38: 0 | BX38: =SUM(BL38:BW38) -> 55 | BY38: {=IFERROR(VLOOKUP(A38,'[1]Now-OB-kg-POB-25'!A:AQ,{17,18,19,20,21,22,23,24,25,26,27,28},0),0)} -> 560 | BZ38: 168 | CA38: 3940 | CB38: 0 | CC38: 0 | CD38: 0 | CE38: 0 | CF38: 0 | CG38: 0 | CH38: 0 | CI38: 0 | CJ38: 0 | CK38: =SUM(BY38:CJ38) -> 4668 | CL38: {=IFERROR(VLOOKUP(A38,'[1]Now-OB-kg-POB-25'!A:AQ,{31,32,33,34,35,36,37,38,39,40,41,42},0),0)} -> 1207 | CM38: 2068 | CN38: 10535 | CO38: 0 | CP38: 0 | CQ38: 0 | CR38: 0 | CS38: 0 | CT38: 0 | CU38: 0 | CV38: 0 | CW38: 0 | CX38: =SUM(CL38:CW38) -> 13810 | CY38: =IF(A38=0,0,IFERROR(VLOOKUP(A38,'[1]Info Donantes'!C:F,2,0),"Sin Contacto")) -> Sin Contacto | CZ38: =IF(A38=0,0,IFERROR(VLOOKUP(A38,'[1]Info Donantes'!C:F,3,0),"Sin Correo")) -> Sin Correo | DA38: =IF(A38=0,0,IFERROR(VLOOKUP(A38,'[1]Info Donantes'!C:F,4,0),"Sin Telefono")) -> Sin Telefono | DB38: Traceability Report - - IMPORTADORA FRUTA INTERNACIONAL PANAMÁ, S.A.
A39: IMPORTADORA TRANSMUNDI, S.A | B39: =INT(IFERROR(VLOOKUP(A39,'[1]Donor Summary'!C:F,3,0),0)) -> 0 | C39: =INT(ROUND(IFERROR(VLOOKUP(A39,'[1]Donor Summary'!C:F,4,0),0),1)) -> 0 | D39: =INT(ROUND(C39-B39,1)) -> 0 | E39: =IF(A39=0,"",TEXT((IFERROR(D39/C39,0)),"0.00%")) -> 0.00% | F39: =IF(A39=0,"",TEXT((IFERROR(B39/C39,0)),"0.0%")) -> 0.0% | G39: =INT(D39*3) -> 0 | I39: =IFERROR(VLOOKUP(A39,'[1]Lot All by Part'!T:Y,6,0),0) -> 0 | K39: =IFERROR(VLOOKUP($A39,'[1]Donor-Served OBs'!A:N,3,0),0) -> 0 | L39: =ROUNDUP(IF(A39=0,0,IFERROR(VLOOKUP($A39,'[1]Donor''s Assigned Kilos'!A:O,3,0),0)),0) -> 0 | M39: =IF(A39=0,0,IFERROR(SUMIFS([1]Population!M:M,[1]Population!J:J,'MASTER-2025'!A39),0)) -> 0 | N39: =IFERROR(VLOOKUP($A39,'[1]Donor-Served OBs'!A:N,4,0),0) -> 0 | O39: =ROUNDUP(IF(A39=0,0,IFERROR(VLOOKUP($A39,'[1]Donor''s Assigned Kilos'!A:O,4,0),0)),0) -> 0 | P39: =IF(A39=0,0,IFERROR(SUMIFS([1]Population!N:N,[1]Population!J:J,'MASTER-2025'!A39),0)) -> 0 | Q39: =IFERROR(VLOOKUP($A39,'[1]Donor-Served OBs'!A:N,2,0),0) -> 0 | R39: =ROUNDUP(ROUND(IF(A39=0,0,IFERROR(VLOOKUP($A39,'[1]Donor''s Assigned Kilos'!A:O,9,0),0)),1),0) -> 0 | S39: =IF(A39=0,0,IFERROR(SUMIFS([1]Population!S:S,[1]Population!J:J,'MASTER-2025'!A39),0)) -> 0 | T39: =IFERROR(VLOOKUP($A39,'[1]Donor-Served OBs'!A:N,12,0),0) -> 0 | U39: =ROUNDUP(IF(A39=0,0,IF(A39=0,0,IFERROR(VLOOKUP($A39,'[1]Donor''s Assigned Kilos'!A:O,7,0),0))),0) -> 0 | V39: =IF(A39=0,0,IFERROR(SUMIFS([1]Population!Q:Q,[1]Population!J:J,'MASTER-2025'!A39),0)) -> 0 | W39: =IFERROR(VLOOKUP($A39,'[1]Donor-Served OBs'!A:N,10,0),0) -> 0 | X39: =ROUNDUP(IF(A39=0,0,IFERROR(VLOOKUP($A39,'[1]Donor''s Assigned Kilos'!A:N,5,0),0)),0) -> 0 | Y39: =IF(A39=0,0,IFERROR(SUMIFS([1]Population!O:O,[1]Population!J:J,'MASTER-2025'!A39),0)) -> 0 | Z39: =IFERROR(VLOOKUP($A39,'[1]Donor-Served OBs'!A:N,6,0),0) -> 0 | AA39: =ROUNDUP(IF(A39=0,0,IFERROR(VLOOKUP($A39,'[1]Donor''s Assigned Kilos'!A:N,11,0),0)),0) -> 0 | AB39: =IF(A39=0,0,IFERROR(SUMIFS([1]Population!U:U,[1]Population!J:J,'MASTER-2025'!A39),0)) -> 0 | AC39: =IFERROR(VLOOKUP($A39,'[1]Donor-Served OBs'!A:N,7,0),0) -> 0 | AD39: =ROUNDUP(IF(A39=0,0,IFERROR(VLOOKUP($A39,'[1]Donor''s Assigned Kilos'!A:N,8,0),0)),0) -> 0 | AE39: =IF(A39=0,0,IFERROR(SUMIFS([1]Population!R:R,[1]Population!J:J,'MASTER-2025'!A39),0)) -> 0 | AF39: =IFERROR(VLOOKUP($A39,'[1]Donor-Served OBs'!A:N,8,0),0) -> 0 | AG39: =ROUNDUP(IF(A39=0,0,IFERROR(VLOOKUP($A39,'[1]Donor''s Assigned Kilos'!A:N,6,0),0)),0) -> 0 | AH39: =IF(A39=0,0,IFERROR(SUMIFS([1]Population!P:P,[1]Population!J:J,'MASTER-2025'!A39),0)) -> 0 | AI39: =IFERROR(VLOOKUP($A39,'[1]Donor-Served OBs'!A:N,9,0),0) -> 0 | AJ39: =ROUNDUP(IF(A39=0,0,IFERROR(VLOOKUP($A39,'[1]Donor''s Assigned Kilos'!A:N,12,0),0)),0) -> 0 | AK39: =IF(A39=0,0,IFERROR(SUMIFS([1]Population!V:V,[1]Population!J:J,'MASTER-2025'!A39),0)) -> 0 | AL39: =IFERROR(VLOOKUP($A39,'[1]Donor-Served OBs'!A:N,16,0),0) -> 0 | AM39: =ROUNDUP(IF(A39=0,0,IFERROR(VLOOKUP($A39,'[1]Donor''s Assigned Kilos'!A:O,16,0),0)),0) -> 0 | AN39: =IF(A39=0,0,IFERROR(SUMIFS([1]Population!Z:Z,[1]Population!J:J,'MASTER-2025'!A39),0)) -> 0 | AO39: =IFERROR(VLOOKUP($A39,'[1]Donor-Served OBs'!A:N,11,0),0) -> 0 | AP39: =ROUNDUP(IF(A39=0,0,IFERROR(VLOOKUP($A39,'[1]Donor''s Assigned Kilos'!A:N,13,0),0)),0) -> 0 | AQ39: =IF(A39=0,0,IFERROR(SUMIFS([1]Population!W:W,[1]Population!J:J,'MASTER-2025'!A39),0)) -> 0 | AR39: =IFERROR(VLOOKUP($A39,'[1]Donor-Served OBs'!A:N,5,0),0) -> 0 | AS39: =ROUNDUP(IF(A39=0,0,IFERROR(VLOOKUP($A39,'[1]Donor''s Assigned Kilos'!A:N,10,0),0)),0) -> 0 | AT39: =IF(A39=0,0,IFERROR(SUMIFS([1]Population!T:T,[1]Population!J:J,'MASTER-2025'!A39),0)) -> 0 | AU39: =IFERROR(VLOOKUP($A39,'[1]Donor-Served OBs'!A:N,13,0),0) -> 0 | AV39: =ROUNDUP(IF(A39=0,0,IFERROR(VLOOKUP($A39,'[1]Donor''s Assigned Kilos'!A:N,14,0),0)),0) -> 0 | AW39: =IF(A39=0,0,IFERROR(SUMIFS([1]Population!X:X,[1]Population!J:J,'MASTER-2025'!A39),0)) -> 0 | AX39: =IFERROR(VLOOKUP($A39,'[1]Donor-Served OBs'!A:N,16,0),0) -> 0 | AY39: =ROUNDUP(IF(A39=0,0,IFERROR(VLOOKUP($A39,'[1]Donor''s Assigned Kilos'!A:O,16,0),0)),0) -> 0 | AZ39: =IF(A39=0,0,IFERROR(SUMIFS([1]Population!Y:Y,[1]Population!J:J,'MASTER-2025'!A39),0)) -> 0 | BA39: =+H39+K39+N39+Q39+T39+W39+Z39+AC39+AF39+AI39+AL39+AO39+AR39+AU39+AX39 -> 0 | BB39: =INT(I39+L39+O39+R39+U39+X39+AA39+AD39+AG39+AJ39+AM39+AP39+AS39+AV39+AY39) -> 0 | BC39: =ROUND(I39+L39+O39+R39+U39,0) -> 0 | BD39: =IF(A39=0,0,(+J39+M39+P39+S39+V39+Y39+AB39+AE39+AH39+AK39+AN39+AQ39+AT39+AW39+AZ39)) -> 0 | BE39: =IF(A39=0,0,SUMIFS([1]Population!C:C,[1]Population!A:A,'MASTER-2025'!A39)) -> #VALUE! | BF39: =IF(A39=0,0,SUMIFS([1]Population!D:D,[1]Population!A:A,'MASTER-2025'!A39)) -> #VALUE! | BG39: =IF(A39=0,0,SUMIFS([1]Population!E:E,[1]Population!A:A,'MASTER-2025'!A39)) -> #VALUE! | BH39: =IF(A39=0,0,SUMIFS([1]Population!F:F,[1]Population!A:A,'MASTER-2025'!A39)) -> #VALUE! | BI39: =+BF39+BG39+BH39 -> #VALUE! | BJ39: =+BK39-BI39-BH39-BG39-BF39-BE39 -> #VALUE! | BK39: =IF(A39=0,0,SUMIFS([1]Population!G:G,[1]Population!A:A,'MASTER-2025'!A39)) -> #VALUE! | BL39: {=IFERROR(VLOOKUP(A39,'[1]Now-OB-kg-POB-25'!A:AQ,{3,4,5,6,7,8,9,10,11,12,13,14},0),0)} -> 0 | BM39: 0 | BN39: 0 | BO39: 0 | BP39: 0 | BQ39: 0 | BR39: 0 | BS39: 0 | BT39: 0 | BU39: 0 | BV39: 0 | BW39: 0 | BX39: =SUM(BL39:BW39) -> 0 | BY39: {=IFERROR(VLOOKUP(A39,'[1]Now-OB-kg-POB-25'!A:AQ,{17,18,19,20,21,22,23,24,25,26,27,28},0),0)} -> 0 | BZ39: 0 | CA39: 0 | CB39: 0 | CC39: 0 | CD39: 0 | CE39: 0 | CF39: 0 | CG39: 0 | CH39: 0 | CI39: 0 | CJ39: 0 | CK39: =SUM(BY39:CJ39) -> 0 | CL39: {=IFERROR(VLOOKUP(A39,'[1]Now-OB-kg-POB-25'!A:AQ,{31,32,33,34,35,36,37,38,39,40,41,42},0),0)} -> 0 | CM39: 0 | CN39: 0 | CO39: 0 | CP39: 0 | CQ39: 0 | CR39: 0 | CS39: 0 | CT39: 0 | CU39: 0 | CV39: 0 | CW39: 0 | CX39: =SUM(CL39:CW39) -> 0 | CY39: =IF(A39=0,0,IFERROR(VLOOKUP(A39,'[1]Info Donantes'!C:F,2,0),"Sin Contacto")) -> Jose Duarte | CZ39: =IF(A39=0,0,IFERROR(VLOOKUP(A39,'[1]Info Donantes'!C:F,3,0),"Sin Correo")) -> 0 | DA39: =IF(A39=0,0,IFERROR(VLOOKUP(A39,'[1]Info Donantes'!C:F,4,0),"Sin Telefono")) -> 233-9200 | DB39: Traceability Report - - IMPORTADORA TRANSMUNDI, S.A
A40: FOREVER OCEANS PANAMA, S.A. | B40: =INT(IFERROR(VLOOKUP(A40,'[1]Donor Summary'!C:F,3,0),0)) -> 0 | C40: =INT(ROUND(IFERROR(VLOOKUP(A40,'[1]Donor Summary'!C:F,4,0),0),1)) -> 0 | D40: =INT(ROUND(C40-B40,1)) -> 0 | E40: =IF(A40=0,"",TEXT((IFERROR(D40/C40,0)),"0.00%")) -> 0.00% | F40: =IF(A40=0,"",TEXT((IFERROR(B40/C40,0)),"0.0%")) -> 0.0% | G40: =INT(D40*3) -> 0 | I40: =IFERROR(VLOOKUP(A40,'[1]Lot All by Part'!T:Y,6,0),0) -> 0 | K40: =IFERROR(VLOOKUP($A40,'[1]Donor-Served OBs'!A:N,3,0),0) -> 0 | L40: =ROUNDUP(IF(A40=0,0,IFERROR(VLOOKUP($A40,'[1]Donor''s Assigned Kilos'!A:O,3,0),0)),0) -> 0 | M40: =IF(A40=0,0,IFERROR(SUMIFS([1]Population!M:M,[1]Population!J:J,'MASTER-2025'!A40),0)) -> 0 | N40: =IFERROR(VLOOKUP($A40,'[1]Donor-Served OBs'!A:N,4,0),0) -> 0 | O40: =ROUNDUP(IF(A40=0,0,IFERROR(VLOOKUP($A40,'[1]Donor''s Assigned Kilos'!A:O,4,0),0)),0) -> 0 | P40: =IF(A40=0,0,IFERROR(SUMIFS([1]Population!N:N,[1]Population!J:J,'MASTER-2025'!A40),0)) -> 0 | Q40: =IFERROR(VLOOKUP($A40,'[1]Donor-Served OBs'!A:N,2,0),0) -> 0 | R40: =ROUNDUP(ROUND(IF(A40=0,0,IFERROR(VLOOKUP($A40,'[1]Donor''s Assigned Kilos'!A:O,9,0),0)),1),0) -> 0 | S40: =IF(A40=0,0,IFERROR(SUMIFS([1]Population!S:S,[1]Population!J:J,'MASTER-2025'!A40),0)) -> 0 | T40: =IFERROR(VLOOKUP($A40,'[1]Donor-Served OBs'!A:N,12,0),0) -> 0 | U40: =ROUNDUP(IF(A40=0,0,IF(A40=0,0,IFERROR(VLOOKUP($A40,'[1]Donor''s Assigned Kilos'!A:O,7,0),0))),0) -> 0 | V40: =IF(A40=0,0,IFERROR(SUMIFS([1]Population!Q:Q,[1]Population!J:J,'MASTER-2025'!A40),0)) -> 0 | W40: =IFERROR(VLOOKUP($A40,'[1]Donor-Served OBs'!A:N,10,0),0) -> 0 | X40: =ROUNDUP(IF(A40=0,0,IFERROR(VLOOKUP($A40,'[1]Donor''s Assigned Kilos'!A:N,5,0),0)),0) -> 0 | Y40: =IF(A40=0,0,IFERROR(SUMIFS([1]Population!O:O,[1]Population!J:J,'MASTER-2025'!A40),0)) -> 0 | Z40: =IFERROR(VLOOKUP($A40,'[1]Donor-Served OBs'!A:N,6,0),0) -> 0 | AA40: =ROUNDUP(IF(A40=0,0,IFERROR(VLOOKUP($A40,'[1]Donor''s Assigned Kilos'!A:N,11,0),0)),0) -> 0 | AB40: =IF(A40=0,0,IFERROR(SUMIFS([1]Population!U:U,[1]Population!J:J,'MASTER-2025'!A40),0)) -> 0 | AC40: =IFERROR(VLOOKUP($A40,'[1]Donor-Served OBs'!A:N,7,0),0) -> 0 | AD40: =ROUNDUP(IF(A40=0,0,IFERROR(VLOOKUP($A40,'[1]Donor''s Assigned Kilos'!A:N,8,0),0)),0) -> 0 | AE40: =IF(A40=0,0,IFERROR(SUMIFS([1]Population!R:R,[1]Population!J:J,'MASTER-2025'!A40),0)) -> 0 | AF40: =IFERROR(VLOOKUP($A40,'[1]Donor-Served OBs'!A:N,8,0),0) -> 0 | AG40: =ROUNDUP(IF(A40=0,0,IFERROR(VLOOKUP($A40,'[1]Donor''s Assigned Kilos'!A:N,6,0),0)),0) -> 0 | AH40: =IF(A40=0,0,IFERROR(SUMIFS([1]Population!P:P,[1]Population!J:J,'MASTER-2025'!A40),0)) -> 0 | AI40: =IFERROR(VLOOKUP($A40,'[1]Donor-Served OBs'!A:N,9,0),0) -> 0 | AJ40: =ROUNDUP(IF(A40=0,0,IFERROR(VLOOKUP($A40,'[1]Donor''s Assigned Kilos'!A:N,12,0),0)),0) -> 0 | AK40: =IF(A40=0,0,IFERROR(SUMIFS([1]Population!V:V,[1]Population!J:J,'MASTER-2025'!A40),0)) -> 0 | AL40: =IFERROR(VLOOKUP($A40,'[1]Donor-Served OBs'!A:N,16,0),0) -> 0 | AM40: =ROUNDUP(IF(A40=0,0,IFERROR(VLOOKUP($A40,'[1]Donor''s Assigned Kilos'!A:O,16,0),0)),0) -> 0 | AN40: =IF(A40=0,0,IFERROR(SUMIFS([1]Population!Z:Z,[1]Population!J:J,'MASTER-2025'!A40),0)) -> 0 | AO40: =IFERROR(VLOOKUP($A40,'[1]Donor-Served OBs'!A:N,11,0),0) -> 0 | AP40: =ROUNDUP(IF(A40=0,0,IFERROR(VLOOKUP($A40,'[1]Donor''s Assigned Kilos'!A:N,13,0),0)),0) -> 0 | AQ40: =IF(A40=0,0,IFERROR(SUMIFS([1]Population!W:W,[1]Population!J:J,'MASTER-2025'!A40),0)) -> 0 | AR40: =IFERROR(VLOOKUP($A40,'[1]Donor-Served OBs'!A:N,5,0),0) -> 0 | AS40: =ROUNDUP(IF(A40=0,0,IFERROR(VLOOKUP($A40,'[1]Donor''s Assigned Kilos'!A:N,10,0),0)),0) -> 0 | AT40: =IF(A40=0,0,IFERROR(SUMIFS([1]Population!T:T,[1]Population!J:J,'MASTER-2025'!A40),0)) -> 0 | AU40: =IFERROR(VLOOKUP($A40,'[1]Donor-Served OBs'!A:N,13,0),0) -> 0 | AV40: =ROUNDUP(IF(A40=0,0,IFERROR(VLOOKUP($A40,'[1]Donor''s Assigned Kilos'!A:N,14,0),0)),0) -> 0 | AW40: =IF(A40=0,0,IFERROR(SUMIFS([1]Population!X:X,[1]Population!J:J,'MASTER-2025'!A40),0)) -> 0 | AX40: =IFERROR(VLOOKUP($A40,'[1]Donor-Served OBs'!A:N,16,0),0) -> 0 | AY40: =ROUNDUP(IF(A40=0,0,IFERROR(VLOOKUP($A40,'[1]Donor''s Assigned Kilos'!A:O,16,0),0)),0) -> 0 | AZ40: =IF(A40=0,0,IFERROR(SUMIFS([1]Population!Y:Y,[1]Population!J:J,'MASTER-2025'!A40),0)) -> 0 | BA40: =+H40+K40+N40+Q40+T40+W40+Z40+AC40+AF40+AI40+AL40+AO40+AR40+AU40+AX40 -> 0 | BB40: =INT(I40+L40+O40+R40+U40+X40+AA40+AD40+AG40+AJ40+AM40+AP40+AS40+AV40+AY40) -> 0 | BC40: =ROUND(I40+L40+O40+R40+U40,0) -> 0 | BD40: =IF(A40=0,0,(+J40+M40+P40+S40+V40+Y40+AB40+AE40+AH40+AK40+AN40+AQ40+AT40+AW40+AZ40)) -> 0 | BE40: =IF(A40=0,0,SUMIFS([1]Population!C:C,[1]Population!A:A,'MASTER-2025'!A40)) -> #VALUE! | BF40: =IF(A40=0,0,SUMIFS([1]Population!D:D,[1]Population!A:A,'MASTER-2025'!A40)) -> #VALUE! | BG40: =IF(A40=0,0,SUMIFS([1]Population!E:E,[1]Population!A:A,'MASTER-2025'!A40)) -> #VALUE! | BH40: =IF(A40=0,0,SUMIFS([1]Population!F:F,[1]Population!A:A,'MASTER-2025'!A40)) -> #VALUE! | BI40: =+BF40+BG40+BH40 -> #VALUE! | BJ40: =+BK40-BI40-BH40-BG40-BF40-BE40 -> #VALUE! | BK40: =IF(A40=0,0,SUMIFS([1]Population!G:G,[1]Population!A:A,'MASTER-2025'!A40)) -> #VALUE! | BL40: {=IFERROR(VLOOKUP(A40,'[1]Now-OB-kg-POB-25'!A:AQ,{3,4,5,6,7,8,9,10,11,12,13,14},0),0)} -> 0 | BM40: 0 | BN40: 0 | BO40: 0 | BP40: 0 | BQ40: 0 | BR40: 0 | BS40: 0 | BT40: 0 | BU40: 0 | BV40: 0 | BW40: 0 | BX40: =SUM(BL40:BW40) -> 0 | BY40: {=IFERROR(VLOOKUP(A40,'[1]Now-OB-kg-POB-25'!A:AQ,{17,18,19,20,21,22,23,24,25,26,27,28},0),0)} -> 0 | BZ40: 0 | CA40: 0 | CB40: 0 | CC40: 0 | CD40: 0 | CE40: 0 | CF40: 0 | CG40: 0 | CH40: 0 | CI40: 0 | CJ40: 0 | CK40: =SUM(BY40:CJ40) -> 0 | CL40: {=IFERROR(VLOOKUP(A40,'[1]Now-OB-kg-POB-25'!A:AQ,{31,32,33,34,35,36,37,38,39,40,41,42},0),0)} -> 0 | CM40: 0 | CN40: 0 | CO40: 0 | CP40: 0 | CQ40: 0 | CR40: 0 | CS40: 0 | CT40: 0 | CU40: 0 | CV40: 0 | CW40: 0 | CX40: =SUM(CL40:CW40) -> 0 | CY40: =IF(A40=0,0,IFERROR(VLOOKUP(A40,'[1]Info Donantes'!C:F,2,0),"Sin Contacto")) -> Sin Contacto | CZ40: =IF(A40=0,0,IFERROR(VLOOKUP(A40,'[1]Info Donantes'!C:F,3,0),"Sin Correo")) -> Sin Correo | DA40: =IF(A40=0,0,IFERROR(VLOOKUP(A40,'[1]Info Donantes'!C:F,4,0),"Sin Telefono")) -> Sin Telefono | DB40: Traceability Report - - FOREVER OCEANS PANAMA, S.A.
A41: SUPER BRANDS CORPORATION | B41: =INT(IFERROR(VLOOKUP(A41,'[1]Donor Summary'!C:F,3,0),0)) -> 0 | C41: =INT(ROUND(IFERROR(VLOOKUP(A41,'[1]Donor Summary'!C:F,4,0),0),1)) -> 0 | D41: =INT(ROUND(C41-B41,1)) -> 0 | E41: =IF(A41=0,"",TEXT((IFERROR(D41/C41,0)),"0.00%")) -> 0.00% | F41: =IF(A41=0,"",TEXT((IFERROR(B41/C41,0)),"0.0%")) -> 0.0% | G41: =INT(D41*3) -> 0 | I41: =IFERROR(VLOOKUP(A41,'[1]Lot All by Part'!T:Y,6,0),0) -> 0 | K41: =IFERROR(VLOOKUP($A41,'[1]Donor-Served OBs'!A:N,3,0),0) -> 0 | L41: =ROUNDUP(IF(A41=0,0,IFERROR(VLOOKUP($A41,'[1]Donor''s Assigned Kilos'!A:O,3,0),0)),0) -> 0 | M41: =IF(A41=0,0,IFERROR(SUMIFS([1]Population!M:M,[1]Population!J:J,'MASTER-2025'!A41),0)) -> 0 | N41: =IFERROR(VLOOKUP($A41,'[1]Donor-Served OBs'!A:N,4,0),0) -> 0 | O41: =ROUNDUP(IF(A41=0,0,IFERROR(VLOOKUP($A41,'[1]Donor''s Assigned Kilos'!A:O,4,0),0)),0) -> 0 | P41: =IF(A41=0,0,IFERROR(SUMIFS([1]Population!N:N,[1]Population!J:J,'MASTER-2025'!A41),0)) -> 0 | Q41: =IFERROR(VLOOKUP($A41,'[1]Donor-Served OBs'!A:N,2,0),0) -> 0 | R41: =ROUNDUP(ROUND(IF(A41=0,0,IFERROR(VLOOKUP($A41,'[1]Donor''s Assigned Kilos'!A:O,9,0),0)),1),0) -> 0 | S41: =IF(A41=0,0,IFERROR(SUMIFS([1]Population!S:S,[1]Population!J:J,'MASTER-2025'!A41),0)) -> 0 | T41: =IFERROR(VLOOKUP($A41,'[1]Donor-Served OBs'!A:N,12,0),0) -> 0 | U41: =ROUNDUP(IF(A41=0,0,IF(A41=0,0,IFERROR(VLOOKUP($A41,'[1]Donor''s Assigned Kilos'!A:O,7,0),0))),0) -> 0 | V41: =IF(A41=0,0,IFERROR(SUMIFS([1]Population!Q:Q,[1]Population!J:J,'MASTER-2025'!A41),0)) -> 0 | W41: =IFERROR(VLOOKUP($A41,'[1]Donor-Served OBs'!A:N,10,0),0) -> 0 | X41: =ROUNDUP(IF(A41=0,0,IFERROR(VLOOKUP($A41,'[1]Donor''s Assigned Kilos'!A:N,5,0),0)),0) -> 0 | Y41: =IF(A41=0,0,IFERROR(SUMIFS([1]Population!O:O,[1]Population!J:J,'MASTER-2025'!A41),0)) -> 0 | Z41: =IFERROR(VLOOKUP($A41,'[1]Donor-Served OBs'!A:N,6,0),0) -> 0 | AA41: =ROUNDUP(IF(A41=0,0,IFERROR(VLOOKUP($A41,'[1]Donor''s Assigned Kilos'!A:N,11,0),0)),0) -> 0 | AB41: =IF(A41=0,0,IFERROR(SUMIFS([1]Population!U:U,[1]Population!J:J,'MASTER-2025'!A41),0)) -> 0 | AC41: =IFERROR(VLOOKUP($A41,'[1]Donor-Served OBs'!A:N,7,0),0) -> 0 | AD41: =ROUNDUP(IF(A41=0,0,IFERROR(VLOOKUP($A41,'[1]Donor''s Assigned Kilos'!A:N,8,0),0)),0) -> 0 | AE41: =IF(A41=0,0,IFERROR(SUMIFS([1]Population!R:R,[1]Population!J:J,'MASTER-2025'!A41),0)) -> 0 | AF41: =IFERROR(VLOOKUP($A41,'[1]Donor-Served OBs'!A:N,8,0),0) -> 0 | AG41: =ROUNDUP(IF(A41=0,0,IFERROR(VLOOKUP($A41,'[1]Donor''s Assigned Kilos'!A:N,6,0),0)),0) -> 0 | AH41: =IF(A41=0,0,IFERROR(SUMIFS([1]Population!P:P,[1]Population!J:J,'MASTER-2025'!A41),0)) -> 0 | AI41: =IFERROR(VLOOKUP($A41,'[1]Donor-Served OBs'!A:N,9,0),0) -> 0 | AJ41: =ROUNDUP(IF(A41=0,0,IFERROR(VLOOKUP($A41,'[1]Donor''s Assigned Kilos'!A:N,12,0),0)),0) -> 0 | AK41: =IF(A41=0,0,IFERROR(SUMIFS([1]Population!V:V,[1]Population!J:J,'MASTER-2025'!A41),0)) -> 0 | AL41: =IFERROR(VLOOKUP($A41,'[1]Donor-Served OBs'!A:N,16,0),0) -> 0 | AM41: =ROUNDUP(IF(A41=0,0,IFERROR(VLOOKUP($A41,'[1]Donor''s Assigned Kilos'!A:O,16,0),0)),0) -> 0 | AN41: =IF(A41=0,0,IFERROR(SUMIFS([1]Population!Z:Z,[1]Population!J:J,'MASTER-2025'!A41),0)) -> 0 | AO41: =IFERROR(VLOOKUP($A41,'[1]Donor-Served OBs'!A:N,11,0),0) -> 0 | AP41: =ROUNDUP(IF(A41=0,0,IFERROR(VLOOKUP($A41,'[1]Donor''s Assigned Kilos'!A:N,13,0),0)),0) -> 0 | AQ41: =IF(A41=0,0,IFERROR(SUMIFS([1]Population!W:W,[1]Population!J:J,'MASTER-2025'!A41),0)) -> 0 | AR41: =IFERROR(VLOOKUP($A41,'[1]Donor-Served OBs'!A:N,5,0),0) -> 0 | AS41: =ROUNDUP(IF(A41=0,0,IFERROR(VLOOKUP($A41,'[1]Donor''s Assigned Kilos'!A:N,10,0),0)),0) -> 0 | AT41: =IF(A41=0,0,IFERROR(SUMIFS([1]Population!T:T,[1]Population!J:J,'MASTER-2025'!A41),0)) -> 0 | AU41: =IFERROR(VLOOKUP($A41,'[1]Donor-Served OBs'!A:N,13,0),0) -> 0 | AV41: =ROUNDUP(IF(A41=0,0,IFERROR(VLOOKUP($A41,'[1]Donor''s Assigned Kilos'!A:N,14,0),0)),0) -> 0 | AW41: =IF(A41=0,0,IFERROR(SUMIFS([1]Population!X:X,[1]Population!J:J,'MASTER-2025'!A41),0)) -> 0 | AX41: =IFERROR(VLOOKUP($A41,'[1]Donor-Served OBs'!A:N,16,0),0) -> 0 | AY41: =ROUNDUP(IF(A41=0,0,IFERROR(VLOOKUP($A41,'[1]Donor''s Assigned Kilos'!A:O,16,0),0)),0) -> 0 | AZ41: =IF(A41=0,0,IFERROR(SUMIFS([1]Population!Y:Y,[1]Population!J:J,'MASTER-2025'!A41),0)) -> 0 | BA41: =+H41+K41+N41+Q41+T41+W41+Z41+AC41+AF41+AI41+AL41+AO41+AR41+AU41+AX41 -> 0 | BB41: =INT(I41+L41+O41+R41+U41+X41+AA41+AD41+AG41+AJ41+AM41+AP41+AS41+AV41+AY41) -> 0 | BC41: =ROUND(I41+L41+O41+R41+U41,0) -> 0 | BD41: =IF(A41=0,0,(+J41+M41+P41+S41+V41+Y41+AB41+AE41+AH41+AK41+AN41+AQ41+AT41+AW41+AZ41)) -> 0 | BE41: =IF(A41=0,0,SUMIFS([1]Population!C:C,[1]Population!A:A,'MASTER-2025'!A41)) -> #VALUE! | BF41: =IF(A41=0,0,SUMIFS([1]Population!D:D,[1]Population!A:A,'MASTER-2025'!A41)) -> #VALUE! | BG41: =IF(A41=0,0,SUMIFS([1]Population!E:E,[1]Population!A:A,'MASTER-2025'!A41)) -> #VALUE! | BH41: =IF(A41=0,0,SUMIFS([1]Population!F:F,[1]Population!A:A,'MASTER-2025'!A41)) -> #VALUE! | BI41: =+BF41+BG41+BH41 -> #VALUE! | BJ41: =+BK41-BI41-BH41-BG41-BF41-BE41 -> #VALUE! | BK41: =IF(A41=0,0,SUMIFS([1]Population!G:G,[1]Population!A:A,'MASTER-2025'!A41)) -> #VALUE! | BL41: {=IFERROR(VLOOKUP(A41,'[1]Now-OB-kg-POB-25'!A:AQ,{3,4,5,6,7,8,9,10,11,12,13,14},0),0)} -> 0 | BM41: 0 | BN41: 0 | BO41: 0 | BP41: 0 | BQ41: 0 | BR41: 0 | BS41: 0 | BT41: 0 | BU41: 0 | BV41: 0 | BW41: 0 | BX41: =SUM(BL41:BW41) -> 0 | BY41: {=IFERROR(VLOOKUP(A41,'[1]Now-OB-kg-POB-25'!A:AQ,{17,18,19,20,21,22,23,24,25,26,27,28},0),0)} -> 0 | BZ41: 0 | CA41: 0 | CB41: 0 | CC41: 0 | CD41: 0 | CE41: 0 | CF41: 0 | CG41: 0 | CH41: 0 | CI41: 0 | CJ41: 0 | CK41: =SUM(BY41:CJ41) -> 0 | CL41: {=IFERROR(VLOOKUP(A41,'[1]Now-OB-kg-POB-25'!A:AQ,{31,32,33,34,35,36,37,38,39,40,41,42},0),0)} -> 0 | CM41: 0 | CN41: 0 | CO41: 0 | CP41: 0 | CQ41: 0 | CR41: 0 | CS41: 0 | CT41: 0 | CU41: 0 | CV41: 0 | CW41: 0 | CX41: =SUM(CL41:CW41) -> 0 | CY41: =IF(A41=0,0,IFERROR(VLOOKUP(A41,'[1]Info Donantes'!C:F,2,0),"Sin Contacto")) -> Sin Contacto | CZ41: =IF(A41=0,0,IFERROR(VLOOKUP(A41,'[1]Info Donantes'!C:F,3,0),"Sin Correo")) -> Sin Correo | DA41: =IF(A41=0,0,IFERROR(VLOOKUP(A41,'[1]Info Donantes'!C:F,4,0),"Sin Telefono")) -> Sin Telefono | DB41: Traceability Report - - SUPER BRANDS CORPORATION
A42: Jacach S.A. | B42: =INT(IFERROR(VLOOKUP(A42,'[1]Donor Summary'!C:F,3,0),0)) -> 0 | C42: =INT(ROUND(IFERROR(VLOOKUP(A42,'[1]Donor Summary'!C:F,4,0),0),1)) -> 0 | D42: =INT(ROUND(C42-B42,1)) -> 0 | E42: =IF(A42=0,"",TEXT((IFERROR(D42/C42,0)),"0.00%")) -> 0.00% | F42: =IF(A42=0,"",TEXT((IFERROR(B42/C42,0)),"0.0%")) -> 0.0% | G42: =INT(D42*3) -> 0 | I42: =IFERROR(VLOOKUP(A42,'[1]Lot All by Part'!T:Y,6,0),0) -> 0 | K42: =IFERROR(VLOOKUP($A42,'[1]Donor-Served OBs'!A:N,3,0),0) -> 0 | L42: =ROUNDUP(IF(A42=0,0,IFERROR(VLOOKUP($A42,'[1]Donor''s Assigned Kilos'!A:O,3,0),0)),0) -> 0 | M42: =IF(A42=0,0,IFERROR(SUMIFS([1]Population!M:M,[1]Population!J:J,'MASTER-2025'!A42),0)) -> 0 | N42: =IFERROR(VLOOKUP($A42,'[1]Donor-Served OBs'!A:N,4,0),0) -> 0 | O42: =ROUNDUP(IF(A42=0,0,IFERROR(VLOOKUP($A42,'[1]Donor''s Assigned Kilos'!A:O,4,0),0)),0) -> 0 | P42: =IF(A42=0,0,IFERROR(SUMIFS([1]Population!N:N,[1]Population!J:J,'MASTER-2025'!A42),0)) -> 0 | Q42: =IFERROR(VLOOKUP($A42,'[1]Donor-Served OBs'!A:N,2,0),0) -> 0 | R42: =ROUNDUP(ROUND(IF(A42=0,0,IFERROR(VLOOKUP($A42,'[1]Donor''s Assigned Kilos'!A:O,9,0),0)),1),0) -> 0 | S42: =IF(A42=0,0,IFERROR(SUMIFS([1]Population!S:S,[1]Population!J:J,'MASTER-2025'!A42),0)) -> 0 | T42: =IFERROR(VLOOKUP($A42,'[1]Donor-Served OBs'!A:N,12,0),0) -> 0 | U42: =ROUNDUP(IF(A42=0,0,IF(A42=0,0,IFERROR(VLOOKUP($A42,'[1]Donor''s Assigned Kilos'!A:O,7,0),0))),0) -> 0 | V42: =IF(A42=0,0,IFERROR(SUMIFS([1]Population!Q:Q,[1]Population!J:J,'MASTER-2025'!A42),0)) -> 0 | W42: =IFERROR(VLOOKUP($A42,'[1]Donor-Served OBs'!A:N,10,0),0) -> 0 | X42: =ROUNDUP(IF(A42=0,0,IFERROR(VLOOKUP($A42,'[1]Donor''s Assigned Kilos'!A:N,5,0),0)),0) -> 0 | Y42: =IF(A42=0,0,IFERROR(SUMIFS([1]Population!O:O,[1]Population!J:J,'MASTER-2025'!A42),0)) -> 0 | Z42: =IFERROR(VLOOKUP($A42,'[1]Donor-Served OBs'!A:N,6,0),0) -> 0 | AA42: =ROUNDUP(IF(A42=0,0,IFERROR(VLOOKUP($A42,'[1]Donor''s Assigned Kilos'!A:N,11,0),0)),0) -> 0 | AB42: =IF(A42=0,0,IFERROR(SUMIFS([1]Population!U:U,[1]Population!J:J,'MASTER-2025'!A42),0)) -> 0 | AC42: =IFERROR(VLOOKUP($A42,'[1]Donor-Served OBs'!A:N,7,0),0) -> 0 | AD42: =ROUNDUP(IF(A42=0,0,IFERROR(VLOOKUP($A42,'[1]Donor''s Assigned Kilos'!A:N,8,0),0)),0) -> 0 | AE42: =IF(A42=0,0,IFERROR(SUMIFS([1]Population!R:R,[1]Population!J:J,'MASTER-2025'!A42),0)) -> 0 | AF42: =IFERROR(VLOOKUP($A42,'[1]Donor-Served OBs'!A:N,8,0),0) -> 0 | AG42: =ROUNDUP(IF(A42=0,0,IFERROR(VLOOKUP($A42,'[1]Donor''s Assigned Kilos'!A:N,6,0),0)),0) -> 0 | AH42: =IF(A42=0,0,IFERROR(SUMIFS([1]Population!P:P,[1]Population!J:J,'MASTER-2025'!A42),0)) -> 0 | AI42: =IFERROR(VLOOKUP($A42,'[1]Donor-Served OBs'!A:N,9,0),0) -> 0 | AJ42: =ROUNDUP(IF(A42=0,0,IFERROR(VLOOKUP($A42,'[1]Donor''s Assigned Kilos'!A:N,12,0),0)),0) -> 0 | AK42: =IF(A42=0,0,IFERROR(SUMIFS([1]Population!V:V,[1]Population!J:J,'MASTER-2025'!A42),0)) -> 0 | AL42: =IFERROR(VLOOKUP($A42,'[1]Donor-Served OBs'!A:N,16,0),0) -> 0 | AM42: =ROUNDUP(IF(A42=0,0,IFERROR(VLOOKUP($A42,'[1]Donor''s Assigned Kilos'!A:O,16,0),0)),0) -> 0 | AN42: =IF(A42=0,0,IFERROR(SUMIFS([1]Population!Z:Z,[1]Population!J:J,'MASTER-2025'!A42),0)) -> 0 | AO42: =IFERROR(VLOOKUP($A42,'[1]Donor-Served OBs'!A:N,11,0),0) -> 0 | AP42: =ROUNDUP(IF(A42=0,0,IFERROR(VLOOKUP($A42,'[1]Donor''s Assigned Kilos'!A:N,13,0),0)),0) -> 0 | AQ42: =IF(A42=0,0,IFERROR(SUMIFS([1]Population!W:W,[1]Population!J:J,'MASTER-2025'!A42),0)) -> 0 | AR42: =IFERROR(VLOOKUP($A42,'[1]Donor-Served OBs'!A:N,5,0),0) -> 0 | AS42: =ROUNDUP(IF(A42=0,0,IFERROR(VLOOKUP($A42,'[1]Donor''s Assigned Kilos'!A:N,10,0),0)),0) -> 0 | AT42: =IF(A42=0,0,IFERROR(SUMIFS([1]Population!T:T,[1]Population!J:J,'MASTER-2025'!A42),0)) -> 0 | AU42: =IFERROR(VLOOKUP($A42,'[1]Donor-Served OBs'!A:N,13,0),0) -> 0 | AV42: =ROUNDUP(IF(A42=0,0,IFERROR(VLOOKUP($A42,'[1]Donor''s Assigned Kilos'!A:N,14,0),0)),0) -> 0 | AW42: =IF(A42=0,0,IFERROR(SUMIFS([1]Population!X:X,[1]Population!J:J,'MASTER-2025'!A42),0)) -> 0 | AX42: =IFERROR(VLOOKUP($A42,'[1]Donor-Served OBs'!A:N,16,0),0) -> 0 | AY42: =ROUNDUP(IF(A42=0,0,IFERROR(VLOOKUP($A42,'[1]Donor''s Assigned Kilos'!A:O,16,0),0)),0) -> 0 | AZ42: =IF(A42=0,0,IFERROR(SUMIFS([1]Population!Y:Y,[1]Population!J:J,'MASTER-2025'!A42),0)) -> 0 | BA42: =+H42+K42+N42+Q42+T42+W42+Z42+AC42+AF42+AI42+AL42+AO42+AR42+AU42+AX42 -> 0 | BB42: =INT(I42+L42+O42+R42+U42+X42+AA42+AD42+AG42+AJ42+AM42+AP42+AS42+AV42+AY42) -> 0 | BC42: =ROUND(I42+L42+O42+R42+U42,0) -> 0 | BD42: =IF(A42=0,0,(+J42+M42+P42+S42+V42+Y42+AB42+AE42+AH42+AK42+AN42+AQ42+AT42+AW42+AZ42)) -> 0 | BE42: =IF(A42=0,0,SUMIFS([1]Population!C:C,[1]Population!A:A,'MASTER-2025'!A42)) -> #VALUE! | BF42: =IF(A42=0,0,SUMIFS([1]Population!D:D,[1]Population!A:A,'MASTER-2025'!A42)) -> #VALUE! | BG42: =IF(A42=0,0,SUMIFS([1]Population!E:E,[1]Population!A:A,'MASTER-2025'!A42)) -> #VALUE! | BH42: =IF(A42=0,0,SUMIFS([1]Population!F:F,[1]Population!A:A,'MASTER-2025'!A42)) -> #VALUE! | BI42: =+BF42+BG42+BH42 -> #VALUE! | BJ42: =+BK42-BI42-BH42-BG42-BF42-BE42 -> #VALUE! | BK42: =IF(A42=0,0,SUMIFS([1]Population!G:G,[1]Population!A:A,'MASTER-2025'!A42)) -> #VALUE! | BL42: {=IFERROR(VLOOKUP(A42,'[1]Now-OB-kg-POB-25'!A:AQ,{3,4,5,6,7,8,9,10,11,12,13,14},0),0)} -> 27 | BM42: 32 | BN42: 0 | BO42: 0 | BP42: 0 | BQ42: 0 | BR42: 0 | BS42: 0 | BT42: 0 | BU42: 0 | BV42: 0 | BW42: 0 | BX42: =SUM(BL42:BW42) -> 59 | BY42: {=IFERROR(VLOOKUP(A42,'[1]Now-OB-kg-POB-25'!A:AQ,{17,18,19,20,21,22,23,24,25,26,27,28},0),0)} -> 1198 | BZ42: 0 | CA42: 0 | CB42: 0 | CC42: 0 | CD42: 0 | CE42: 0 | CF42: 0 | CG42: 0 | CH42: 0 | CI42: 0 | CJ42: 0 | CK42: =SUM(BY42:CJ42) -> 1198 | CL42: {=IFERROR(VLOOKUP(A42,'[1]Now-OB-kg-POB-25'!A:AQ,{31,32,33,34,35,36,37,38,39,40,41,42},0),0)} -> 7518 | CM42: 6534 | CN42: 0 | CO42: 0 | CP42: 0 | CQ42: 0 | CR42: 0 | CS42: 0 | CT42: 0 | CU42: 0 | CV42: 0 | CW42: 0 | CX42: =SUM(CL42:CW42) -> 14052 | CY42: =IF(A42=0,0,IFERROR(VLOOKUP(A42,'[1]Info Donantes'!C:F,2,0),"Sin Contacto")) -> Sin Contacto | CZ42: =IF(A42=0,0,IFERROR(VLOOKUP(A42,'[1]Info Donantes'!C:F,3,0),"Sin Correo")) -> Sin Correo | DA42: =IF(A42=0,0,IFERROR(VLOOKUP(A42,'[1]Info Donantes'!C:F,4,0),"Sin Telefono")) -> Sin Telefono | DB42: Traceability Report - - Jacach S.A.
A43: Marketing Roots Inc. | B43: =INT(IFERROR(VLOOKUP(A43,'[1]Donor Summary'!C:F,3,0),0)) -> 0 | C43: =INT(ROUND(IFERROR(VLOOKUP(A43,'[1]Donor Summary'!C:F,4,0),0),1)) -> 0 | D43: =INT(ROUND(C43-B43,1)) -> 0 | E43: =IF(A43=0,"",TEXT((IFERROR(D43/C43,0)),"0.00%")) -> 0.00% | F43: =IF(A43=0,"",TEXT((IFERROR(B43/C43,0)),"0.0%")) -> 0.0% | G43: =INT(D43*3) -> 0 | I43: =IFERROR(VLOOKUP(A43,'[1]Lot All by Part'!T:Y,6,0),0) -> 0 | K43: =IFERROR(VLOOKUP($A43,'[1]Donor-Served OBs'!A:N,3,0),0) -> 0 | L43: =ROUNDUP(IF(A43=0,0,IFERROR(VLOOKUP($A43,'[1]Donor''s Assigned Kilos'!A:O,3,0),0)),0) -> 0 | M43: =IF(A43=0,0,IFERROR(SUMIFS([1]Population!M:M,[1]Population!J:J,'MASTER-2025'!A43),0)) -> 0 | N43: =IFERROR(VLOOKUP($A43,'[1]Donor-Served OBs'!A:N,4,0),0) -> 0 | O43: =ROUNDUP(IF(A43=0,0,IFERROR(VLOOKUP($A43,'[1]Donor''s Assigned Kilos'!A:O,4,0),0)),0) -> 0 | P43: =IF(A43=0,0,IFERROR(SUMIFS([1]Population!N:N,[1]Population!J:J,'MASTER-2025'!A43),0)) -> 0 | Q43: =IFERROR(VLOOKUP($A43,'[1]Donor-Served OBs'!A:N,2,0),0) -> 0 | R43: =ROUNDUP(ROUND(IF(A43=0,0,IFERROR(VLOOKUP($A43,'[1]Donor''s Assigned Kilos'!A:O,9,0),0)),1),0) -> 0 | S43: =IF(A43=0,0,IFERROR(SUMIFS([1]Population!S:S,[1]Population!J:J,'MASTER-2025'!A43),0)) -> 0 | T43: =IFERROR(VLOOKUP($A43,'[1]Donor-Served OBs'!A:N,12,0),0) -> 0 | U43: =ROUNDUP(IF(A43=0,0,IF(A43=0,0,IFERROR(VLOOKUP($A43,'[1]Donor''s Assigned Kilos'!A:O,7,0),0))),0) -> 0 | V43: =IF(A43=0,0,IFERROR(SUMIFS([1]Population!Q:Q,[1]Population!J:J,'MASTER-2025'!A43),0)) -> 0 | W43: =IFERROR(VLOOKUP($A43,'[1]Donor-Served OBs'!A:N,10,0),0) -> 0 | X43: =ROUNDUP(IF(A43=0,0,IFERROR(VLOOKUP($A43,'[1]Donor''s Assigned Kilos'!A:N,5,0),0)),0) -> 0 | Y43: =IF(A43=0,0,IFERROR(SUMIFS([1]Population!O:O,[1]Population!J:J,'MASTER-2025'!A43),0)) -> 0 | Z43: =IFERROR(VLOOKUP($A43,'[1]Donor-Served OBs'!A:N,6,0),0) -> 0 | AA43: =ROUNDUP(IF(A43=0,0,IFERROR(VLOOKUP($A43,'[1]Donor''s Assigned Kilos'!A:N,11,0),0)),0) -> 0 | AB43: =IF(A43=0,0,IFERROR(SUMIFS([1]Population!U:U,[1]Population!J:J,'MASTER-2025'!A43),0)) -> 0 | AC43: =IFERROR(VLOOKUP($A43,'[1]Donor-Served OBs'!A:N,7,0),0) -> 0 | AD43: =ROUNDUP(IF(A43=0,0,IFERROR(VLOOKUP($A43,'[1]Donor''s Assigned Kilos'!A:N,8,0),0)),0) -> 0 | AE43: =IF(A43=0,0,IFERROR(SUMIFS([1]Population!R:R,[1]Population!J:J,'MASTER-2025'!A43),0)) -> 0 | AF43: =IFERROR(VLOOKUP($A43,'[1]Donor-Served OBs'!A:N,8,0),0) -> 0 | AG43: =ROUNDUP(IF(A43=0,0,IFERROR(VLOOKUP($A43,'[1]Donor''s Assigned Kilos'!A:N,6,0),0)),0) -> 0 | AH43: =IF(A43=0,0,IFERROR(SUMIFS([1]Population!P:P,[1]Population!J:J,'MASTER-2025'!A43),0)) -> 0 | AI43: =IFERROR(VLOOKUP($A43,'[1]Donor-Served OBs'!A:N,9,0),0) -> 0 | AJ43: =ROUNDUP(IF(A43=0,0,IFERROR(VLOOKUP($A43,'[1]Donor''s Assigned Kilos'!A:N,12,0),0)),0) -> 0 | AK43: =IF(A43=0,0,IFERROR(SUMIFS([1]Population!V:V,[1]Population!J:J,'MASTER-2025'!A43),0)) -> 0 | AL43: =IFERROR(VLOOKUP($A43,'[1]Donor-Served OBs'!A:N,16,0),0) -> 0 | AM43: =ROUNDUP(IF(A43=0,0,IFERROR(VLOOKUP($A43,'[1]Donor''s Assigned Kilos'!A:O,16,0),0)),0) -> 0 | AN43: =IF(A43=0,0,IFERROR(SUMIFS([1]Population!Z:Z,[1]Population!J:J,'MASTER-2025'!A43),0)) -> 0 | AO43: =IFERROR(VLOOKUP($A43,'[1]Donor-Served OBs'!A:N,11,0),0) -> 0 | AP43: =ROUNDUP(IF(A43=0,0,IFERROR(VLOOKUP($A43,'[1]Donor''s Assigned Kilos'!A:N,13,0),0)),0) -> 0 | AQ43: =IF(A43=0,0,IFERROR(SUMIFS([1]Population!W:W,[1]Population!J:J,'MASTER-2025'!A43),0)) -> 0 | AR43: =IFERROR(VLOOKUP($A43,'[1]Donor-Served OBs'!A:N,5,0),0) -> 0 | AS43: =ROUNDUP(IF(A43=0,0,IFERROR(VLOOKUP($A43,'[1]Donor''s Assigned Kilos'!A:N,10,0),0)),0) -> 0 | AT43: =IF(A43=0,0,IFERROR(SUMIFS([1]Population!T:T,[1]Population!J:J,'MASTER-2025'!A43),0)) -> 0 | AU43: =IFERROR(VLOOKUP($A43,'[1]Donor-Served OBs'!A:N,13,0),0) -> 0 | AV43: =ROUNDUP(IF(A43=0,0,IFERROR(VLOOKUP($A43,'[1]Donor''s Assigned Kilos'!A:N,14,0),0)),0) -> 0 | AW43: =IF(A43=0,0,IFERROR(SUMIFS([1]Population!X:X,[1]Population!J:J,'MASTER-2025'!A43),0)) -> 0 | AX43: =IFERROR(VLOOKUP($A43,'[1]Donor-Served OBs'!A:N,16,0),0) -> 0 | AY43: =ROUNDUP(IF(A43=0,0,IFERROR(VLOOKUP($A43,'[1]Donor''s Assigned Kilos'!A:O,16,0),0)),0) -> 0 | AZ43: =IF(A43=0,0,IFERROR(SUMIFS([1]Population!Y:Y,[1]Population!J:J,'MASTER-2025'!A43),0)) -> 0 | BA43: =+H43+K43+N43+Q43+T43+W43+Z43+AC43+AF43+AI43+AL43+AO43+AR43+AU43+AX43 -> 0 | BB43: =INT(I43+L43+O43+R43+U43+X43+AA43+AD43+AG43+AJ43+AM43+AP43+AS43+AV43+AY43) -> 0 | BC43: =ROUND(I43+L43+O43+R43+U43,0) -> 0 | BD43: =IF(A43=0,0,(+J43+M43+P43+S43+V43+Y43+AB43+AE43+AH43+AK43+AN43+AQ43+AT43+AW43+AZ43)) -> 0 | BE43: =IF(A43=0,0,SUMIFS([1]Population!C:C,[1]Population!A:A,'MASTER-2025'!A43)) -> #VALUE! | BF43: =IF(A43=0,0,SUMIFS([1]Population!D:D,[1]Population!A:A,'MASTER-2025'!A43)) -> #VALUE! | BG43: =IF(A43=0,0,SUMIFS([1]Population!E:E,[1]Population!A:A,'MASTER-2025'!A43)) -> #VALUE! | BH43: =IF(A43=0,0,SUMIFS([1]Population!F:F,[1]Population!A:A,'MASTER-2025'!A43)) -> #VALUE! | BI43: =+BF43+BG43+BH43 -> #VALUE! | BJ43: =+BK43-BI43-BH43-BG43-BF43-BE43 -> #VALUE! | BK43: =IF(A43=0,0,SUMIFS([1]Population!G:G,[1]Population!A:A,'MASTER-2025'!A43)) -> #VALUE! | BL43: {=IFERROR(VLOOKUP(A43,'[1]Now-OB-kg-POB-25'!A:AQ,{3,4,5,6,7,8,9,10,11,12,13,14},0),0)} -> 0 | BM43: 0 | BN43: 0 | BO43: 0 | BP43: 0 | BQ43: 0 | BR43: 0 | BS43: 0 | BT43: 0 | BU43: 0 | BV43: 0 | BW43: 0 | BX43: =SUM(BL43:BW43) -> 0 | BY43: {=IFERROR(VLOOKUP(A43,'[1]Now-OB-kg-POB-25'!A:AQ,{17,18,19,20,21,22,23,24,25,26,27,28},0),0)} -> 0 | BZ43: 0 | CA43: 0 | CB43: 0 | CC43: 0 | CD43: 0 | CE43: 0 | CF43: 0 | CG43: 0 | CH43: 0 | CI43: 0 | CJ43: 0 | CK43: =SUM(BY43:CJ43) -> 0 | CL43: {=IFERROR(VLOOKUP(A43,'[1]Now-OB-kg-POB-25'!A:AQ,{31,32,33,34,35,36,37,38,39,40,41,42},0),0)} -> 0 | CM43: 0 | CN43: 0 | CO43: 0 | CP43: 0 | CQ43: 0 | CR43: 0 | CS43: 0 | CT43: 0 | CU43: 0 | CV43: 0 | CW43: 0 | CX43: =SUM(CL43:CW43) -> 0 | CY43: =IF(A43=0,0,IFERROR(VLOOKUP(A43,'[1]Info Donantes'!C:F,2,0),"Sin Contacto")) -> Sin Contacto | CZ43: =IF(A43=0,0,IFERROR(VLOOKUP(A43,'[1]Info Donantes'!C:F,3,0),"Sin Correo")) -> Sin Correo | DA43: =IF(A43=0,0,IFERROR(VLOOKUP(A43,'[1]Info Donantes'!C:F,4,0),"Sin Telefono")) -> Sin Telefono | DB43: Traceability Report - - Marketing Roots Inc.
A44: Vima Foods Panama S.A. | B44: =INT(IFERROR(VLOOKUP(A44,'[1]Donor Summary'!C:F,3,0),0)) -> 0 | C44: =INT(ROUND(IFERROR(VLOOKUP(A44,'[1]Donor Summary'!C:F,4,0),0),1)) -> 0 | D44: =INT(ROUND(C44-B44,1)) -> 0 | E44: =IF(A44=0,"",TEXT((IFERROR(D44/C44,0)),"0.00%")) -> 0.00% | F44: =IF(A44=0,"",TEXT((IFERROR(B44/C44,0)),"0.0%")) -> 0.0% | G44: =INT(D44*3) -> 0 | I44: =IFERROR(VLOOKUP(A44,'[1]Lot All by Part'!T:Y,6,0),0) -> 0 | K44: =IFERROR(VLOOKUP($A44,'[1]Donor-Served OBs'!A:N,3,0),0) -> 0 | L44: =ROUNDUP(IF(A44=0,0,IFERROR(VLOOKUP($A44,'[1]Donor''s Assigned Kilos'!A:O,3,0),0)),0) -> 0 | M44: =IF(A44=0,0,IFERROR(SUMIFS([1]Population!M:M,[1]Population!J:J,'MASTER-2025'!A44),0)) -> 0 | N44: =IFERROR(VLOOKUP($A44,'[1]Donor-Served OBs'!A:N,4,0),0) -> 0 | O44: =ROUNDUP(IF(A44=0,0,IFERROR(VLOOKUP($A44,'[1]Donor''s Assigned Kilos'!A:O,4,0),0)),0) -> 0 | P44: =IF(A44=0,0,IFERROR(SUMIFS([1]Population!N:N,[1]Population!J:J,'MASTER-2025'!A44),0)) -> 0 | Q44: =IFERROR(VLOOKUP($A44,'[1]Donor-Served OBs'!A:N,2,0),0) -> 0 | R44: =ROUNDUP(ROUND(IF(A44=0,0,IFERROR(VLOOKUP($A44,'[1]Donor''s Assigned Kilos'!A:O,9,0),0)),1),0) -> 0 | S44: =IF(A44=0,0,IFERROR(SUMIFS([1]Population!S:S,[1]Population!J:J,'MASTER-2025'!A44),0)) -> 0 | T44: =IFERROR(VLOOKUP($A44,'[1]Donor-Served OBs'!A:N,12,0),0) -> 0 | U44: =ROUNDUP(IF(A44=0,0,IF(A44=0,0,IFERROR(VLOOKUP($A44,'[1]Donor''s Assigned Kilos'!A:O,7,0),0))),0) -> 0 | V44: =IF(A44=0,0,IFERROR(SUMIFS([1]Population!Q:Q,[1]Population!J:J,'MASTER-2025'!A44),0)) -> 0 | W44: =IFERROR(VLOOKUP($A44,'[1]Donor-Served OBs'!A:N,10,0),0) -> 0 | X44: =ROUNDUP(IF(A44=0,0,IFERROR(VLOOKUP($A44,'[1]Donor''s Assigned Kilos'!A:N,5,0),0)),0) -> 0 | Y44: =IF(A44=0,0,IFERROR(SUMIFS([1]Population!O:O,[1]Population!J:J,'MASTER-2025'!A44),0)) -> 0 | Z44: =IFERROR(VLOOKUP($A44,'[1]Donor-Served OBs'!A:N,6,0),0) -> 0 | AA44: =ROUNDUP(IF(A44=0,0,IFERROR(VLOOKUP($A44,'[1]Donor''s Assigned Kilos'!A:N,11,0),0)),0) -> 0 | AB44: =IF(A44=0,0,IFERROR(SUMIFS([1]Population!U:U,[1]Population!J:J,'MASTER-2025'!A44),0)) -> 0 | AC44: =IFERROR(VLOOKUP($A44,'[1]Donor-Served OBs'!A:N,7,0),0) -> 0 | AD44: =ROUNDUP(IF(A44=0,0,IFERROR(VLOOKUP($A44,'[1]Donor''s Assigned Kilos'!A:N,8,0),0)),0) -> 0 | AE44: =IF(A44=0,0,IFERROR(SUMIFS([1]Population!R:R,[1]Population!J:J,'MASTER-2025'!A44),0)) -> 0 | AF44: =IFERROR(VLOOKUP($A44,'[1]Donor-Served OBs'!A:N,8,0),0) -> 0 | AG44: =ROUNDUP(IF(A44=0,0,IFERROR(VLOOKUP($A44,'[1]Donor''s Assigned Kilos'!A:N,6,0),0)),0) -> 0 | AH44: =IF(A44=0,0,IFERROR(SUMIFS([1]Population!P:P,[1]Population!J:J,'MASTER-2025'!A44),0)) -> 0 | AI44: =IFERROR(VLOOKUP($A44,'[1]Donor-Served OBs'!A:N,9,0),0) -> 0 | AJ44: =ROUNDUP(IF(A44=0,0,IFERROR(VLOOKUP($A44,'[1]Donor''s Assigned Kilos'!A:N,12,0),0)),0) -> 0 | AK44: =IF(A44=0,0,IFERROR(SUMIFS([1]Population!V:V,[1]Population!J:J,'MASTER-2025'!A44),0)) -> 0 | AL44: =IFERROR(VLOOKUP($A44,'[1]Donor-Served OBs'!A:N,16,0),0) -> 0 | AM44: =ROUNDUP(IF(A44=0,0,IFERROR(VLOOKUP($A44,'[1]Donor''s Assigned Kilos'!A:O,16,0),0)),0) -> 0 | AN44: =IF(A44=0,0,IFERROR(SUMIFS([1]Population!Z:Z,[1]Population!J:J,'MASTER-2025'!A44),0)) -> 0 | AO44: =IFERROR(VLOOKUP($A44,'[1]Donor-Served OBs'!A:N,11,0),0) -> 0 | AP44: =ROUNDUP(IF(A44=0,0,IFERROR(VLOOKUP($A44,'[1]Donor''s Assigned Kilos'!A:N,13,0),0)),0) -> 0 | AQ44: =IF(A44=0,0,IFERROR(SUMIFS([1]Population!W:W,[1]Population!J:J,'MASTER-2025'!A44),0)) -> 0 | AR44: =IFERROR(VLOOKUP($A44,'[1]Donor-Served OBs'!A:N,5,0),0) -> 0 | AS44: =ROUNDUP(IF(A44=0,0,IFERROR(VLOOKUP($A44,'[1]Donor''s Assigned Kilos'!A:N,10,0),0)),0) -> 0 | AT44: =IF(A44=0,0,IFERROR(SUMIFS([1]Population!T:T,[1]Population!J:J,'MASTER-2025'!A44),0)) -> 0 | AU44: =IFERROR(VLOOKUP($A44,'[1]Donor-Served OBs'!A:N,13,0),0) -> 0 | AV44: =ROUNDUP(IF(A44=0,0,IFERROR(VLOOKUP($A44,'[1]Donor''s Assigned Kilos'!A:N,14,0),0)),0) -> 0 | AW44: =IF(A44=0,0,IFERROR(SUMIFS([1]Population!X:X,[1]Population!J:J,'MASTER-2025'!A44),0)) -> 0 | AX44: =IFERROR(VLOOKUP($A44,'[1]Donor-Served OBs'!A:N,16,0),0) -> 0 | AY44: =ROUNDUP(IF(A44=0,0,IFERROR(VLOOKUP($A44,'[1]Donor''s Assigned Kilos'!A:O,16,0),0)),0) -> 0 | AZ44: =IF(A44=0,0,IFERROR(SUMIFS([1]Population!Y:Y,[1]Population!J:J,'MASTER-2025'!A44),0)) -> 0 | BA44: =+H44+K44+N44+Q44+T44+W44+Z44+AC44+AF44+AI44+AL44+AO44+AR44+AU44+AX44 -> 0 | BB44: =INT(I44+L44+O44+R44+U44+X44+AA44+AD44+AG44+AJ44+AM44+AP44+AS44+AV44+AY44) -> 0 | BC44: =ROUND(I44+L44+O44+R44+U44,0) -> 0 | BD44: =IF(A44=0,0,(+J44+M44+P44+S44+V44+Y44+AB44+AE44+AH44+AK44+AN44+AQ44+AT44+AW44+AZ44)) -> 0 | BE44: =IF(A44=0,0,SUMIFS([1]Population!C:C,[1]Population!A:A,'MASTER-2025'!A44)) -> #VALUE! | BF44: =IF(A44=0,0,SUMIFS([1]Population!D:D,[1]Population!A:A,'MASTER-2025'!A44)) -> #VALUE! | BG44: =IF(A44=0,0,SUMIFS([1]Population!E:E,[1]Population!A:A,'MASTER-2025'!A44)) -> #VALUE! | BH44: =IF(A44=0,0,SUMIFS([1]Population!F:F,[1]Population!A:A,'MASTER-2025'!A44)) -> #VALUE! | BI44: =+BF44+BG44+BH44 -> #VALUE! | BJ44: =+BK44-BI44-BH44-BG44-BF44-BE44 -> #VALUE! | BK44: =IF(A44=0,0,SUMIFS([1]Population!G:G,[1]Population!A:A,'MASTER-2025'!A44)) -> #VALUE! | BL44: {=IFERROR(VLOOKUP(A44,'[1]Now-OB-kg-POB-25'!A:AQ,{3,4,5,6,7,8,9,10,11,12,13,14},0),0)} -> 0 | BM44: 43 | BN44: 19 | BO44: 0 | BP44: 0 | BQ44: 0 | BR44: 0 | BS44: 0 | BT44: 0 | BU44: 0 | BV44: 0 | BW44: 0 | BX44: =SUM(BL44:BW44) -> 62 | BY44: {=IFERROR(VLOOKUP(A44,'[1]Now-OB-kg-POB-25'!A:AQ,{17,18,19,20,21,22,23,24,25,26,27,28},0),0)} -> 600 | BZ44: 0 | CA44: 39 | CB44: 0 | CC44: 0 | CD44: 0 | CE44: 0 | CF44: 0 | CG44: 0 | CH44: 0 | CI44: 0 | CJ44: 0 | CK44: =SUM(BY44:CJ44) -> 639 | CL44: {=IFERROR(VLOOKUP(A44,'[1]Now-OB-kg-POB-25'!A:AQ,{31,32,33,34,35,36,37,38,39,40,41,42},0),0)} -> 0 | CM44: 17158 | CN44: 4968 | CO44: 0 | CP44: 0 | CQ44: 0 | CR44: 0 | CS44: 0 | CT44: 0 | CU44: 0 | CV44: 0 | CW44: 0 | CX44: =SUM(CL44:CW44) -> 22126 | CY44: =IF(A44=0,0,IFERROR(VLOOKUP(A44,'[1]Info Donantes'!C:F,2,0),"Sin Contacto")) -> Sin Contacto | CZ44: =IF(A44=0,0,IFERROR(VLOOKUP(A44,'[1]Info Donantes'!C:F,3,0),"Sin Correo")) -> Sin Correo | DA44: =IF(A44=0,0,IFERROR(VLOOKUP(A44,'[1]Info Donantes'!C:F,4,0),"Sin Telefono")) -> Sin Telefono | DB44: Traceability Report - - Vima Foods Panama S.A.
A45: PRODUCTOS LUX, S.A (Proluxa) | B45: =INT(IFERROR(VLOOKUP(A45,'[1]Donor Summary'!C:F,3,0),0)) -> 0 | C45: =INT(ROUND(IFERROR(VLOOKUP(A45,'[1]Donor Summary'!C:F,4,0),0),1)) -> 0 | D45: =INT(ROUND(C45-B45,1)) -> 0 | E45: =IF(A45=0,"",TEXT((IFERROR(D45/C45,0)),"0.00%")) -> 0.00% | F45: =IF(A45=0,"",TEXT((IFERROR(B45/C45,0)),"0.0%")) -> 0.0% | G45: =INT(D45*3) -> 0 | I45: =IFERROR(VLOOKUP(A45,'[1]Lot All by Part'!T:Y,6,0),0) -> 0 | K45: =IFERROR(VLOOKUP($A45,'[1]Donor-Served OBs'!A:N,3,0),0) -> 0 | L45: =ROUNDUP(IF(A45=0,0,IFERROR(VLOOKUP($A45,'[1]Donor''s Assigned Kilos'!A:O,3,0),0)),0) -> 0 | M45: =IF(A45=0,0,IFERROR(SUMIFS([1]Population!M:M,[1]Population!J:J,'MASTER-2025'!A45),0)) -> 0 | N45: =IFERROR(VLOOKUP($A45,'[1]Donor-Served OBs'!A:N,4,0),0) -> 0 | O45: =ROUNDUP(IF(A45=0,0,IFERROR(VLOOKUP($A45,'[1]Donor''s Assigned Kilos'!A:O,4,0),0)),0) -> 0 | P45: =IF(A45=0,0,IFERROR(SUMIFS([1]Population!N:N,[1]Population!J:J,'MASTER-2025'!A45),0)) -> 0 | Q45: =IFERROR(VLOOKUP($A45,'[1]Donor-Served OBs'!A:N,2,0),0) -> 0 | R45: =ROUNDUP(ROUND(IF(A45=0,0,IFERROR(VLOOKUP($A45,'[1]Donor''s Assigned Kilos'!A:O,9,0),0)),1),0) -> 0 | S45: =IF(A45=0,0,IFERROR(SUMIFS([1]Population!S:S,[1]Population!J:J,'MASTER-2025'!A45),0)) -> 0 | T45: =IFERROR(VLOOKUP($A45,'[1]Donor-Served OBs'!A:N,12,0),0) -> 0 | U45: =ROUNDUP(IF(A45=0,0,IF(A45=0,0,IFERROR(VLOOKUP($A45,'[1]Donor''s Assigned Kilos'!A:O,7,0),0))),0) -> 0 | V45: =IF(A45=0,0,IFERROR(SUMIFS([1]Population!Q:Q,[1]Population!J:J,'MASTER-2025'!A45),0)) -> 0 | W45: =IFERROR(VLOOKUP($A45,'[1]Donor-Served OBs'!A:N,10,0),0) -> 0 | X45: =ROUNDUP(IF(A45=0,0,IFERROR(VLOOKUP($A45,'[1]Donor''s Assigned Kilos'!A:N,5,0),0)),0) -> 0 | Y45: =IF(A45=0,0,IFERROR(SUMIFS([1]Population!O:O,[1]Population!J:J,'MASTER-2025'!A45),0)) -> 0 | Z45: =IFERROR(VLOOKUP($A45,'[1]Donor-Served OBs'!A:N,6,0),0) -> 0 | AA45: =ROUNDUP(IF(A45=0,0,IFERROR(VLOOKUP($A45,'[1]Donor''s Assigned Kilos'!A:N,11,0),0)),0) -> 0 | AB45: =IF(A45=0,0,IFERROR(SUMIFS([1]Population!U:U,[1]Population!J:J,'MASTER-2025'!A45),0)) -> 0 | AC45: =IFERROR(VLOOKUP($A45,'[1]Donor-Served OBs'!A:N,7,0),0) -> 0 | AD45: =ROUNDUP(IF(A45=0,0,IFERROR(VLOOKUP($A45,'[1]Donor''s Assigned Kilos'!A:N,8,0),0)),0) -> 0 | AE45: =IF(A45=0,0,IFERROR(SUMIFS([1]Population!R:R,[1]Population!J:J,'MASTER-2025'!A45),0)) -> 0 | AF45: =IFERROR(VLOOKUP($A45,'[1]Donor-Served OBs'!A:N,8,0),0) -> 0 | AG45: =ROUNDUP(IF(A45=0,0,IFERROR(VLOOKUP($A45,'[1]Donor''s Assigned Kilos'!A:N,6,0),0)),0) -> 0 | AH45: =IF(A45=0,0,IFERROR(SUMIFS([1]Population!P:P,[1]Population!J:J,'MASTER-2025'!A45),0)) -> 0 | AI45: =IFERROR(VLOOKUP($A45,'[1]Donor-Served OBs'!A:N,9,0),0) -> 0 | AJ45: =ROUNDUP(IF(A45=0,0,IFERROR(VLOOKUP($A45,'[1]Donor''s Assigned Kilos'!A:N,12,0),0)),0) -> 0 | AK45: =IF(A45=0,0,IFERROR(SUMIFS([1]Population!V:V,[1]Population!J:J,'MASTER-2025'!A45),0)) -> 0 | AL45: =IFERROR(VLOOKUP($A45,'[1]Donor-Served OBs'!A:N,16,0),0) -> 0 | AM45: =ROUNDUP(IF(A45=0,0,IFERROR(VLOOKUP($A45,'[1]Donor''s Assigned Kilos'!A:O,16,0),0)),0) -> 0 | AN45: =IF(A45=0,0,IFERROR(SUMIFS([1]Population!Z:Z,[1]Population!J:J,'MASTER-2025'!A45),0)) -> 0 | AO45: =IFERROR(VLOOKUP($A45,'[1]Donor-Served OBs'!A:N,11,0),0) -> 0 | AP45: =ROUNDUP(IF(A45=0,0,IFERROR(VLOOKUP($A45,'[1]Donor''s Assigned Kilos'!A:N,13,0),0)),0) -> 0 | AQ45: =IF(A45=0,0,IFERROR(SUMIFS([1]Population!W:W,[1]Population!J:J,'MASTER-2025'!A45),0)) -> 0 | AR45: =IFERROR(VLOOKUP($A45,'[1]Donor-Served OBs'!A:N,5,0),0) -> 0 | AS45: =ROUNDUP(IF(A45=0,0,IFERROR(VLOOKUP($A45,'[1]Donor''s Assigned Kilos'!A:N,10,0),0)),0) -> 0 | AT45: =IF(A45=0,0,IFERROR(SUMIFS([1]Population!T:T,[1]Population!J:J,'MASTER-2025'!A45),0)) -> 0 | AU45: =IFERROR(VLOOKUP($A45,'[1]Donor-Served OBs'!A:N,13,0),0) -> 0 | AV45: =ROUNDUP(IF(A45=0,0,IFERROR(VLOOKUP($A45,'[1]Donor''s Assigned Kilos'!A:N,14,0),0)),0) -> 0 | AW45: =IF(A45=0,0,IFERROR(SUMIFS([1]Population!X:X,[1]Population!J:J,'MASTER-2025'!A45),0)) -> 0 | AX45: =IFERROR(VLOOKUP($A45,'[1]Donor-Served OBs'!A:N,16,0),0) -> 0 | AY45: =ROUNDUP(IF(A45=0,0,IFERROR(VLOOKUP($A45,'[1]Donor''s Assigned Kilos'!A:O,16,0),0)),0) -> 0 | AZ45: =IF(A45=0,0,IFERROR(SUMIFS([1]Population!Y:Y,[1]Population!J:J,'MASTER-2025'!A45),0)) -> 0 | BA45: =+H45+K45+N45+Q45+T45+W45+Z45+AC45+AF45+AI45+AL45+AO45+AR45+AU45+AX45 -> 0 | BB45: =INT(I45+L45+O45+R45+U45+X45+AA45+AD45+AG45+AJ45+AM45+AP45+AS45+AV45+AY45) -> 0 | BC45: =ROUND(I45+L45+O45+R45+U45,0) -> 0 | BD45: =IF(A45=0,0,(+J45+M45+P45+S45+V45+Y45+AB45+AE45+AH45+AK45+AN45+AQ45+AT45+AW45+AZ45)) -> 0 | BE45: =IF(A45=0,0,SUMIFS([1]Population!C:C,[1]Population!A:A,'MASTER-2025'!A45)) -> #VALUE! | BF45: =IF(A45=0,0,SUMIFS([1]Population!D:D,[1]Population!A:A,'MASTER-2025'!A45)) -> #VALUE! | BG45: =IF(A45=0,0,SUMIFS([1]Population!E:E,[1]Population!A:A,'MASTER-2025'!A45)) -> #VALUE! | BH45: =IF(A45=0,0,SUMIFS([1]Population!F:F,[1]Population!A:A,'MASTER-2025'!A45)) -> #VALUE! | BI45: =+BF45+BG45+BH45 -> #VALUE! | BJ45: =+BK45-BI45-BH45-BG45-BF45-BE45 -> #VALUE! | BK45: =IF(A45=0,0,SUMIFS([1]Population!G:G,[1]Population!A:A,'MASTER-2025'!A45)) -> #VALUE! | BL45: {=IFERROR(VLOOKUP(A45,'[1]Now-OB-kg-POB-25'!A:AQ,{3,4,5,6,7,8,9,10,11,12,13,14},0),0)} -> 0 | BM45: 45 | BN45: 60 | BO45: 0 | BP45: 0 | BQ45: 0 | BR45: 0 | BS45: 0 | BT45: 0 | BU45: 0 | BV45: 0 | BW45: 0 | BX45: =SUM(BL45:BW45) -> 105 | BY45: {=IFERROR(VLOOKUP(A45,'[1]Now-OB-kg-POB-25'!A:AQ,{17,18,19,20,21,22,23,24,25,26,27,28},0),0)} -> 1409 | BZ45: 987 | CA45: 818 | CB45: 0 | CC45: 0 | CD45: 0 | CE45: 0 | CF45: 0 | CG45: 0 | CH45: 0 | CI45: 0 | CJ45: 0 | CK45: =SUM(BY45:CJ45) -> 3214 | CL45: {=IFERROR(VLOOKUP(A45,'[1]Now-OB-kg-POB-25'!A:AQ,{31,32,33,34,35,36,37,38,39,40,41,42},0),0)} -> 0 | CM45: 12662 | CN45: 15214 | CO45: 0 | CP45: 0 | CQ45: 0 | CR45: 0 | CS45: 0 | CT45: 0 | CU45: 0 | CV45: 0 | CW45: 0 | CX45: =SUM(CL45:CW45) -> 27876 | CY45: =IF(A45=0,0,IFERROR(VLOOKUP(A45,'[1]Info Donantes'!C:F,2,0),"Sin Contacto")) -> Sin Contacto | CZ45: =IF(A45=0,0,IFERROR(VLOOKUP(A45,'[1]Info Donantes'!C:F,3,0),"Sin Correo")) -> Sin Correo | DA45: =IF(A45=0,0,IFERROR(VLOOKUP(A45,'[1]Info Donantes'!C:F,4,0),"Sin Telefono")) -> Sin Telefono | DB45: Traceability Report - - PRODUCTOS LUX, S.A (Proluxa)
A46: MARTIN BROWER | B46: =INT(IFERROR(VLOOKUP(A46,'[1]Donor Summary'!C:F,3,0),0)) -> 0 | C46: =INT(ROUND(IFERROR(VLOOKUP(A46,'[1]Donor Summary'!C:F,4,0),0),1)) -> 826 | D46: =INT(ROUND(C46-B46,1)) -> 826 | E46: =IF(A46=0,"",TEXT((IFERROR(D46/C46,0)),"0.00%")) -> 100.00% | F46: =IF(A46=0,"",TEXT((IFERROR(B46/C46,0)),"0.0%")) -> 0.0% | G46: =INT(D46*3) -> 2478 | I46: =IFERROR(VLOOKUP(A46,'[1]Lot All by Part'!T:Y,6,0),0) -> 0 | K46: =IFERROR(VLOOKUP($A46,'[1]Donor-Served OBs'!A:N,3,0),0) -> 13 | L46: =ROUNDUP(IF(A46=0,0,IFERROR(VLOOKUP($A46,'[1]Donor''s Assigned Kilos'!A:O,3,0),0)),0) -> 146 | M46: =IF(A46=0,0,IFERROR(SUMIFS([1]Population!M:M,[1]Population!J:J,'MASTER-2025'!A46),0)) -> 0 | N46: =IFERROR(VLOOKUP($A46,'[1]Donor-Served OBs'!A:N,4,0),0) -> 27 | O46: =ROUNDUP(IF(A46=0,0,IFERROR(VLOOKUP($A46,'[1]Donor''s Assigned Kilos'!A:O,4,0),0)),0) -> 241 | P46: =IF(A46=0,0,IFERROR(SUMIFS([1]Population!N:N,[1]Population!J:J,'MASTER-2025'!A46),0)) -> 0 | Q46: =IFERROR(VLOOKUP($A46,'[1]Donor-Served OBs'!A:N,2,0),0) -> 3 | R46: =ROUNDUP(ROUND(IF(A46=0,0,IFERROR(VLOOKUP($A46,'[1]Donor''s Assigned Kilos'!A:O,9,0),0)),1),0) -> 18 | S46: =IF(A46=0,0,IFERROR(SUMIFS([1]Population!S:S,[1]Population!J:J,'MASTER-2025'!A46),0)) -> 0 | T46: =IFERROR(VLOOKUP($A46,'[1]Donor-Served OBs'!A:N,12,0),0) -> 5 | U46: =ROUNDUP(IF(A46=0,0,IF(A46=0,0,IFERROR(VLOOKUP($A46,'[1]Donor''s Assigned Kilos'!A:O,7,0),0))),0) -> 49 | V46: =IF(A46=0,0,IFERROR(SUMIFS([1]Population!Q:Q,[1]Population!J:J,'MASTER-2025'!A46),0)) -> 0 | W46: =IFERROR(VLOOKUP($A46,'[1]Donor-Served OBs'!A:N,10,0),0) -> 7 | X46: =ROUNDUP(IF(A46=0,0,IFERROR(VLOOKUP($A46,'[1]Donor''s Assigned Kilos'!A:N,5,0),0)),0) -> 42 | Y46: =IF(A46=0,0,IFERROR(SUMIFS([1]Population!O:O,[1]Population!J:J,'MASTER-2025'!A46),0)) -> 0 | Z46: =IFERROR(VLOOKUP($A46,'[1]Donor-Served OBs'!A:N,6,0),0) -> 0 | AA46: =ROUNDUP(IF(A46=0,0,IFERROR(VLOOKUP($A46,'[1]Donor''s Assigned Kilos'!A:N,11,0),0)),0) -> 0 | AB46: =IF(A46=0,0,IFERROR(SUMIFS([1]Population!U:U,[1]Population!J:J,'MASTER-2025'!A46),0)) -> 0 | AC46: =IFERROR(VLOOKUP($A46,'[1]Donor-Served OBs'!A:N,7,0),0) -> 3 | AD46: =ROUNDUP(IF(A46=0,0,IFERROR(VLOOKUP($A46,'[1]Donor''s Assigned Kilos'!A:N,8,0),0)),0) -> 18 | AE46: =IF(A46=0,0,IFERROR(SUMIFS([1]Population!R:R,[1]Population!J:J,'MASTER-2025'!A46),0)) -> 0 | AF46: =IFERROR(VLOOKUP($A46,'[1]Donor-Served OBs'!A:N,8,0),0) -> 1 | AG46: =ROUNDUP(IF(A46=0,0,IFERROR(VLOOKUP($A46,'[1]Donor''s Assigned Kilos'!A:N,6,0),0)),0) -> 8 | AH46: =IF(A46=0,0,IFERROR(SUMIFS([1]Population!P:P,[1]Population!J:J,'MASTER-2025'!A46),0)) -> 0 | AI46: =IFERROR(VLOOKUP($A46,'[1]Donor-Served OBs'!A:N,9,0),0) -> 1 | AJ46: =ROUNDUP(IF(A46=0,0,IFERROR(VLOOKUP($A46,'[1]Donor''s Assigned Kilos'!A:N,12,0),0)),0) -> 6 | AK46: =IF(A46=0,0,IFERROR(SUMIFS([1]Population!V:V,[1]Population!J:J,'MASTER-2025'!A46),0)) -> 0 | AL46: =IFERROR(VLOOKUP($A46,'[1]Donor-Served OBs'!A:N,16,0),0) -> 0 | AM46: =ROUNDUP(IF(A46=0,0,IFERROR(VLOOKUP($A46,'[1]Donor''s Assigned Kilos'!A:O,16,0),0)),0) -> 0 | AN46: =IF(A46=0,0,IFERROR(SUMIFS([1]Population!Z:Z,[1]Population!J:J,'MASTER-2025'!A46),0)) -> 0 | AO46: =IFERROR(VLOOKUP($A46,'[1]Donor-Served OBs'!A:N,11,0),0) -> 0 | AP46: =ROUNDUP(IF(A46=0,0,IFERROR(VLOOKUP($A46,'[1]Donor''s Assigned Kilos'!A:N,13,0),0)),0) -> 0 | AQ46: =IF(A46=0,0,IFERROR(SUMIFS([1]Population!W:W,[1]Population!J:J,'MASTER-2025'!A46),0)) -> 0 | AR46: =IFERROR(VLOOKUP($A46,'[1]Donor-Served OBs'!A:N,5,0),0) -> 0 | AS46: =ROUNDUP(IF(A46=0,0,IFERROR(VLOOKUP($A46,'[1]Donor''s Assigned Kilos'!A:N,10,0),0)),0) -> 0 | AT46: =IF(A46=0,0,IFERROR(SUMIFS([1]Population!T:T,[1]Population!J:J,'MASTER-2025'!A46),0)) -> 0 | AU46: =IFERROR(VLOOKUP($A46,'[1]Donor-Served OBs'!A:N,13,0),0) -> 0 | AV46: =ROUNDUP(IF(A46=0,0,IFERROR(VLOOKUP($A46,'[1]Donor''s Assigned Kilos'!A:N,14,0),0)),0) -> 0 | AW46: =IF(A46=0,0,IFERROR(SUMIFS([1]Population!X:X,[1]Population!J:J,'MASTER-2025'!A46),0)) -> 0 | AX46: =IFERROR(VLOOKUP($A46,'[1]Donor-Served OBs'!A:N,16,0),0) -> 0 | AY46: =ROUNDUP(IF(A46=0,0,IFERROR(VLOOKUP($A46,'[1]Donor''s Assigned Kilos'!A:O,16,0),0)),0) -> 0 | AZ46: =IF(A46=0,0,IFERROR(SUMIFS([1]Population!Y:Y,[1]Population!J:J,'MASTER-2025'!A46),0)) -> 0 | BA46: =+H46+K46+N46+Q46+T46+W46+Z46+AC46+AF46+AI46+AL46+AO46+AR46+AU46+AX46 -> 60 | BB46: =INT(I46+L46+O46+R46+U46+X46+AA46+AD46+AG46+AJ46+AM46+AP46+AS46+AV46+AY46) -> 528 | BC46: =ROUND(I46+L46+O46+R46+U46,0) -> 454 | BD46: =IF(A46=0,0,(+J46+M46+P46+S46+V46+Y46+AB46+AE46+AH46+AK46+AN46+AQ46+AT46+AW46+AZ46)) -> 0 | BE46: =IF(A46=0,0,SUMIFS([1]Population!C:C,[1]Population!A:A,'MASTER-2025'!A46)) -> #VALUE! | BF46: =IF(A46=0,0,SUMIFS([1]Population!D:D,[1]Population!A:A,'MASTER-2025'!A46)) -> #VALUE! | BG46: =IF(A46=0,0,SUMIFS([1]Population!E:E,[1]Population!A:A,'MASTER-2025'!A46)) -> #VALUE! | BH46: =IF(A46=0,0,SUMIFS([1]Population!F:F,[1]Population!A:A,'MASTER-2025'!A46)) -> #VALUE! | BI46: =+BF46+BG46+BH46 -> #VALUE! | BJ46: =+BK46-BI46-BH46-BG46-BF46-BE46 -> #VALUE! | BK46: =IF(A46=0,0,SUMIFS([1]Population!G:G,[1]Population!A:A,'MASTER-2025'!A46)) -> #VALUE! | BL46: {=IFERROR(VLOOKUP(A46,'[1]Now-OB-kg-POB-25'!A:AQ,{3,4,5,6,7,8,9,10,11,12,13,14},0),0)} -> 0 | BM46: 0 | BN46: 0 | BO46: 0 | BP46: 0 | BQ46: 0 | BR46: 0 | BS46: 0 | BT46: 0 | BU46: 0 | BV46: 0 | BW46: 0 | BX46: =SUM(BL46:BW46) -> 0 | BY46: {=IFERROR(VLOOKUP(A46,'[1]Now-OB-kg-POB-25'!A:AQ,{17,18,19,20,21,22,23,24,25,26,27,28},0),0)} -> 0 | BZ46: 0 | CA46: 0 | CB46: 0 | CC46: 0 | CD46: 0 | CE46: 0 | CF46: 0 | CG46: 0 | CH46: 0 | CI46: 0 | CJ46: 0 | CK46: =SUM(BY46:CJ46) -> 0 | CL46: {=IFERROR(VLOOKUP(A46,'[1]Now-OB-kg-POB-25'!A:AQ,{31,32,33,34,35,36,37,38,39,40,41,42},0),0)} -> 0 | CM46: 0 | CN46: 0 | CO46: 0 | CP46: 0 | CQ46: 0 | CR46: 0 | CS46: 0 | CT46: 0 | CU46: 0 | CV46: 0 | CW46: 0 | CX46: =SUM(CL46:CW46) -> 0 | CY46: =IF(A46=0,0,IFERROR(VLOOKUP(A46,'[1]Info Donantes'!C:F,2,0),"Sin Contacto")) -> Sin Contacto | CZ46: =IF(A46=0,0,IFERROR(VLOOKUP(A46,'[1]Info Donantes'!C:F,3,0),"Sin Correo")) -> Sin Correo | DA46: =IF(A46=0,0,IFERROR(VLOOKUP(A46,'[1]Info Donantes'!C:F,4,0),"Sin Telefono")) -> Sin Telefono | DB46: Traceability Report - - MARTIN BROWER
... A59: KERRY PANAMA, S.A. | B59: =INT(IFERROR(VLOOKUP(A59,'[1]Donor Summary'!C:F,3,0),0)) -> 0 | C59: =INT(ROUND(IFERROR(VLOOKUP(A59,'[1]Donor Summary'!C:F,4,0),0),1)) -> 833 | D59: =INT(ROUND(C59-B59,1)) -> 833 | E59: =IF(A59=0,"",TEXT((IFERROR(D59/C59,0)),"0.00%")) -> 100.00% | F59: =IF(A59=0,"",TEXT((IFERROR(B59/C59,0)),"0.0%")) -> 0.0% | G59: =INT(D59*3) -> 2499 | I59: =IFERROR(VLOOKUP(A59,'[1]Lot All by Part'!T:Y,6,0),0) -> 0 | K59: =IFERROR(VLOOKUP($A59,'[1]Donor-Served OBs'!A:N,3,0),0) -> 1 | L59: =ROUNDUP(IF(A59=0,0,IFERROR(VLOOKUP($A59,'[1]Donor''s Assigned Kilos'!A:O,3,0),0)),0) -> 10 | M59: =IF(A59=0,0,IFERROR(SUMIFS([1]Population!M:M,[1]Population!J:J,'MASTER-2025'!A59),0)) -> 0 | N59: =IFERROR(VLOOKUP($A59,'[1]Donor-Served OBs'!A:N,4,0),0) -> 0 | O59: =ROUNDUP(IF(A59=0,0,IFERROR(VLOOKUP($A59,'[1]Donor''s Assigned Kilos'!A:O,4,0),0)),0) -> 0 | P59: =IF(A59=0,0,IFERROR(SUMIFS([1]Population!N:N,[1]Population!J:J,'MASTER-2025'!A59),0)) -> 0 | Q59: =IFERROR(VLOOKUP($A59,'[1]Donor-Served OBs'!A:N,2,0),0) -> 0 | R59: =ROUNDUP(ROUND(IF(A59=0,0,IFERROR(VLOOKUP($A59,'[1]Donor''s Assigned Kilos'!A:O,9,0),0)),1),0) -> 0 | S59: =IF(A59=0,0,IFERROR(SUMIFS([1]Population!S:S,[1]Population!J:J,'MASTER-2025'!A59),0)) -> 0 | T59: =IFERROR(VLOOKUP($A59,'[1]Donor-Served OBs'!A:N,12,0),0) -> 0 | U59: =ROUNDUP(IF(A59=0,0,IF(A59=0,0,IFERROR(VLOOKUP($A59,'[1]Donor''s Assigned Kilos'!A:O,7,0),0))),0) -> 0 | V59: =IF(A59=0,0,IFERROR(SUMIFS([1]Population!Q:Q,[1]Population!J:J,'MASTER-2025'!A59),0)) -> 0 | W59: =IFERROR(VLOOKUP($A59,'[1]Donor-Served OBs'!A:N,10,0),0) -> 0 | X59: =ROUNDUP(IF(A59=0,0,IFERROR(VLOOKUP($A59,'[1]Donor''s Assigned Kilos'!A:N,5,0),0)),0) -> 0 | Y59: =IF(A59=0,0,IFERROR(SUMIFS([1]Population!O:O,[1]Population!J:J,'MASTER-2025'!A59),0)) -> 0 | Z59: =IFERROR(VLOOKUP($A59,'[1]Donor-Served OBs'!A:N,6,0),0) -> 0 | AA59: =ROUNDUP(IF(A59=0,0,IFERROR(VLOOKUP($A59,'[1]Donor''s Assigned Kilos'!A:N,11,0),0)),0) -> 0 | AB59: =IF(A59=0,0,IFERROR(SUMIFS([1]Population!U:U,[1]Population!J:J,'MASTER-2025'!A59),0)) -> 0 | AC59: =IFERROR(VLOOKUP($A59,'[1]Donor-Served OBs'!A:N,7,0),0) -> 0 | AD59: =ROUNDUP(IF(A59=0,0,IFERROR(VLOOKUP($A59,'[1]Donor''s Assigned Kilos'!A:N,8,0),0)),0) -> 0 | AE59: =IF(A59=0,0,IFERROR(SUMIFS([1]Population!R:R,[1]Population!J:J,'MASTER-2025'!A59),0)) -> 0 | AF59: =IFERROR(VLOOKUP($A59,'[1]Donor-Served OBs'!A:N,8,0),0) -> 0 | AG59: =ROUNDUP(IF(A59=0,0,IFERROR(VLOOKUP($A59,'[1]Donor''s Assigned Kilos'!A:N,6,0),0)),0) -> 0 | AH59: =IF(A59=0,0,IFERROR(SUMIFS([1]Population!P:P,[1]Population!J:J,'MASTER-2025'!A59),0)) -> 0 | AI59: =IFERROR(VLOOKUP($A59,'[1]Donor-Served OBs'!A:N,9,0),0) -> 0 | AJ59: =ROUNDUP(IF(A59=0,0,IFERROR(VLOOKUP($A59,'[1]Donor''s Assigned Kilos'!A:N,12,0),0)),0) -> 0 | AK59: =IF(A59=0,0,IFERROR(SUMIFS([1]Population!V:V,[1]Population!J:J,'MASTER-2025'!A59),0)) -> 0 | AL59: =IFERROR(VLOOKUP($A59,'[1]Donor-Served OBs'!A:N,16,0),0) -> 0 | AM59: =ROUNDUP(IF(A59=0,0,IFERROR(VLOOKUP($A59,'[1]Donor''s Assigned Kilos'!A:O,16,0),0)),0) -> 0 | AN59: =IF(A59=0,0,IFERROR(SUMIFS([1]Population!Z:Z,[1]Population!J:J,'MASTER-2025'!A59),0)) -> 0 | AO59: =IFERROR(VLOOKUP($A59,'[1]Donor-Served OBs'!A:N,11,0),0) -> 0 | AP59: =ROUNDUP(IF(A59=0,0,IFERROR(VLOOKUP($A59,'[1]Donor''s Assigned Kilos'!A:N,13,0),0)),0) -> 0 | AQ59: =IF(A59=0,0,IFERROR(SUMIFS([1]Population!W:W,[1]Population!J:J,'MASTER-2025'!A59),0)) -> 0 | AR59: =IFERROR(VLOOKUP($A59,'[1]Donor-Served OBs'!A:N,5,0),0) -> 0 | AS59: =ROUNDUP(IF(A59=0,0,IFERROR(VLOOKUP($A59,'[1]Donor''s Assigned Kilos'!A:N,10,0),0)),0) -> 0 | AT59: =IF(A59=0,0,IFERROR(SUMIFS([1]Population!T:T,[1]Population!J:J,'MASTER-2025'!A59),0)) -> 0 | AU59: =IFERROR(VLOOKUP($A59,'[1]Donor-Served OBs'!A:N,13,0),0) -> 0 | AV59: =ROUNDUP(IF(A59=0,0,IFERROR(VLOOKUP($A59,'[1]Donor''s Assigned Kilos'!A:N,14,0),0)),0) -> 0 | AW59: =IF(A59=0,0,IFERROR(SUMIFS([1]Population!X:X,[1]Population!J:J,'MASTER-2025'!A59),0)) -> 0 | AX59: =IFERROR(VLOOKUP($A59,'[1]Donor-Served OBs'!A:N,16,0),0) -> 0 | AY59: =ROUNDUP(IF(A59=0,0,IFERROR(VLOOKUP($A59,'[1]Donor''s Assigned Kilos'!A:O,16,0),0)),0) -> 0 | AZ59: =IF(A59=0,0,IFERROR(SUMIFS([1]Population!Y:Y,[1]Population!J:J,'MASTER-2025'!A59),0)) -> 0 | BA59: =+H59+K59+N59+Q59+T59+W59+Z59+AC59+AF59+AI59+AL59+AO59+AR59+AU59+AX59 -> 1 | BB59: =INT(I59+L59+O59+R59+U59+X59+AA59+AD59+AG59+AJ59+AM59+AP59+AS59+AV59+AY59) -> 10 | BC59: =ROUND(I59+L59+O59+R59+U59,0) -> 10 | BD59: =IF(A59=0,0,(+J59+M59+P59+S59+V59+Y59+AB59+AE59+AH59+AK59+AN59+AQ59+AT59+AW59+AZ59)) -> 0 | BE59: =IF(A59=0,0,SUMIFS([1]Population!C:C,[1]Population!A:A,'MASTER-2025'!A59)) -> #VALUE! | BF59: =IF(A59=0,0,SUMIFS([1]Population!D:D,[1]Population!A:A,'MASTER-2025'!A59)) -> #VALUE! | BG59: =IF(A59=0,0,SUMIFS([1]Population!E:E,[1]Population!A:A,'MASTER-2025'!A59)) -> #VALUE! | BH59: =IF(A59=0,0,SUMIFS([1]Population!F:F,[1]Population!A:A,'MASTER-2025'!A59)) -> #VALUE! | BI59: =+BF59+BG59+BH59 -> #VALUE! | BJ59: =+BK59-BI59-BH59-BG59-BF59-BE59 -> #VALUE! | BK59: =IF(A59=0,0,SUMIFS([1]Population!G:G,[1]Population!A:A,'MASTER-2025'!A59)) -> #VALUE! | BL59: {=IFERROR(VLOOKUP(A59,'[1]Now-OB-kg-POB-25'!A:AQ,{3,4,5,6,7,8,9,10,11,12,13,14},0),0)} -> 0 | BM59: 42 | BN59: 1 | BO59: 0 | BP59: 0 | BQ59: 0 | BR59: 0 | BS59: 0 | BT59: 0 | BU59: 0 | BV59: 0 | BW59: 0 | BX59: =SUM(BL59:BW59) -> 43 | BY59: {=IFERROR(VLOOKUP(A59,'[1]Now-OB-kg-POB-25'!A:AQ,{17,18,19,20,21,22,23,24,25,26,27,28},0),0)} -> 0 | BZ59: 559 | CA59: 833 | CB59: 0 | CC59: 0 | CD59: 0 | CE59: 0 | CF59: 0 | CG59: 0 | CH59: 0 | CI59: 0 | CJ59: 0 | CK59: =SUM(BY59:CJ59) -> 1392 | CL59: {=IFERROR(VLOOKUP(A59,'[1]Now-OB-kg-POB-25'!A:AQ,{31,32,33,34,35,36,37,38,39,40,41,42},0),0)} -> 0 | CM59: 13212 | CN59: 400 | CO59: 0 | CP59: 0 | CQ59: 0 | CR59: 0 | CS59: 0 | CT59: 0 | CU59: 0 | CV59: 0 | CW59: 0 | CX59: =SUM(CL59:CW59) -> 13612 | CY59: =IF(A59=0,0,IFERROR(VLOOKUP(A59,'[1]Info Donantes'!C:F,2,0),"Sin Contacto")) -> Sin Contacto | CZ59: =IF(A59=0,0,IFERROR(VLOOKUP(A59,'[1]Info Donantes'!C:F,3,0),"Sin Correo")) -> Sin Correo | DA59: =IF(A59=0,0,IFERROR(VLOOKUP(A59,'[1]Info Donantes'!C:F,4,0),"Sin Telefono")) -> Sin Telefono | DB59: Traceability Report - - KERRY P
A60: LINA CORPORATION INC (LINA) | B60: =INT(IFERROR(VLOOKUP(A60,'[1]Donor Summary'!C:F,3,0),0)) -> 0 | C60: =INT(ROUND(IFERROR(VLOOKUP(A60,'[1]Donor Summary'!C:F,4,0),0),1)) -> 0 | D60: =INT(ROUND(C60-B60,1)) -> 0 | E60: =IF(A60=0,"",TEXT((IFERROR(D60/C60,0)),"0.00%")) -> 0.00% | F60: =IF(A60=0,"",TEXT((IFERROR(B60/C60,0)),"0.0%")) -> 0.0% | G60: =INT(D60*3) -> 0 | I60: =IFERROR(VLOOKUP(A60,'[1]Lot All by Part'!T:Y,6,0),0) -> 0 | K60: =IFERROR(VLOOKUP($A60,'[1]Donor-Served OBs'!A:N,3,0),0) -> 0 | L60: =ROUNDUP(IF(A60=0,0,IFERROR(VLOOKUP($A60,'[1]Donor''s Assigned Kilos'!A:O,3,0),0)),0) -> 0 | M60: =IF(A60=0,0,IFERROR(SUMIFS([1]Population!M:M,[1]Population!J:J,'MASTER-2025'!A60),0)) -> 0 | N60: =IFERROR(VLOOKUP($A60,'[1]Donor-Served OBs'!A:N,4,0),0) -> 0 | O60: =ROUNDUP(IF(A60=0,0,IFERROR(VLOOKUP($A60,'[1]Donor''s Assigned Kilos'!A:O,4,0),0)),0) -> 0 | P60: =IF(A60=0,0,IFERROR(SUMIFS([1]Population!N:N,[1]Population!J:J,'MASTER-2025'!A60),0)) -> 0 | Q60: =IFERROR(VLOOKUP($A60,'[1]Donor-Served OBs'!A:N,2,0),0) -> 0 | R60: =ROUNDUP(ROUND(IF(A60=0,0,IFERROR(VLOOKUP($A60,'[1]Donor''s Assigned Kilos'!A:O,9,0),0)),1),0) -> 0 | S60: =IF(A60=0,0,IFERROR(SUMIFS([1]Population!S:S,[1]Population!J:J,'MASTER-2025'!A60),0)) -> 0 | T60: =IFERROR(VLOOKUP($A60,'[1]Donor-Served OBs'!A:N,12,0),0) -> 0 | U60: =ROUNDUP(IF(A60=0,0,IF(A60=0,0,IFERROR(VLOOKUP($A60,'[1]Donor''s Assigned Kilos'!A:O,7,0),0))),0) -> 0 | V60: =IF(A60=0,0,IFERROR(SUMIFS([1]Population!Q:Q,[1]Population!J:J,'MASTER-2025'!A60),0)) -> 0 | W60: =IFERROR(VLOOKUP($A60,'[1]Donor-Served OBs'!A:N,10,0),0) -> 0 | X60: =ROUNDUP(IF(A60=0,0,IFERROR(VLOOKUP($A60,'[1]Donor''s Assigned Kilos'!A:N,5,0),0)),0) -> 0 | Y60: =IF(A60=0,0,IFERROR(SUMIFS([1]Population!O:O,[1]Population!J:J,'MASTER-2025'!A60),0)) -> 0 | Z60: =IFERROR(VLOOKUP($A60,'[1]Donor-Served OBs'!A:N,6,0),0) -> 0 | AA60: =ROUNDUP(IF(A60=0,0,IFERROR(VLOOKUP($A60,'[1]Donor''s Assigned Kilos'!A:N,11,0),0)),0) -> 0 | AB60: =IF(A60=0,0,IFERROR(SUMIFS([1]Population!U:U,[1]Population!J:J,'MASTER-2025'!A60),0)) -> 0 | AC60: =IFERROR(VLOOKUP($A60,'[1]Donor-Served OBs'!A:N,7,0),0) -> 0 | AD60: =ROUNDUP(IF(A60=0,0,IFERROR(VLOOKUP($A60,'[1]Donor''s Assigned Kilos'!A:N,8,0),0)),0) -> 0 | AE60: =IF(A60=0,0,IFERROR(SUMIFS([1]Population!R:R,[1]Population!J:J,'MASTER-2025'!A60),0)) -> 0 | AF60: =IFERROR(VLOOKUP($A60,'[1]Donor-Served OBs'!A:N,8,0),0) -> 0 | AG60: =ROUNDUP(IF(A60=0,0,IFERROR(VLOOKUP($A60,'[1]Donor''s Assigned Kilos'!A:N,6,0),0)),0) -> 0 | AH60: =IF(A60=0,0,IFERROR(SUMIFS([1]Population!P:P,[1]Population!J:J,'MASTER-2025'!A60),0)) -> 0 | AI60: =IFERROR(VLOOKUP($A60,'[1]Donor-Served OBs'!A:N,9,0),0) -> 0 | AJ60: =ROUNDUP(IF(A60=0,0,IFERROR(VLOOKUP($A60,'[1]Donor''s Assigned Kilos'!A:N,12,0),0)),0) -> 0 | AK60: =IF(A60=0,0,IFERROR(SUMIFS([1]Population!V:V,[1]Population!J:J,'MASTER-2025'!A60),0)) -> 0 | AL60: =IFERROR(VLOOKUP($A60,'[1]Donor-Served OBs'!A:N,16,0),0) -> 0 | AM60: =ROUNDUP(IF(A60=0,0,IFERROR(VLOOKUP($A60,'[1]Donor''s Assigned Kilos'!A:O,16,0),0)),0) -> 0 | AN60: =IF(A60=0,0,IFERROR(SUMIFS([1]Population!Z:Z,[1]Population!J:J,'MASTER-2025'!A60),0)) -> 0 | AO60: =IFERROR(VLOOKUP($A60,'[1]Donor-Served OBs'!A:N,11,0),0) -> 0 | AP60: =ROUNDUP(IF(A60=0,0,IFERROR(VLOOKUP($A60,'[1]Donor''s Assigned Kilos'!A:N,13,0),0)),0) -> 0 | AQ60: =IF(A60=0,0,IFERROR(SUMIFS([1]Population!W:W,[1]Population!J:J,'MASTER-2025'!A60),0)) -> 0 | AR60: =IFERROR(VLOOKUP($A60,'[1]Donor-Served OBs'!A:N,5,0),0) -> 0 | AS60: =ROUNDUP(IF(A60=0,0,IFERROR(VLOOKUP($A60,'[1]Donor''s Assigned Kilos'!A:N,10,0),0)),0) -> 0 | AT60: =IF(A60=0,0,IFERROR(SUMIFS([1]Population!T:T,[1]Population!J:J,'MASTER-2025'!A60),0)) -> 0 | AU60: =IFERROR(VLOOKUP($A60,'[1]Donor-Served OBs'!A:N,13,0),0) -> 0 | AV60: =ROUNDUP(IF(A60=0,0,IFERROR(VLOOKUP($A60,'[1]Donor''s Assigned Kilos'!A:N,14,0),0)),0) -> 0 | AW60: =IF(A60=0,0,IFERROR(SUMIFS([1]Population!X:X,[1]Population!J:J,'MASTER-2025'!A60),0)) -> 0 | AX60: =IFERROR(VLOOKUP($A60,'[1]Donor-Served OBs'!A:N,16,0),0) -> 0 | AY60: =ROUNDUP(IF(A60=0,0,IFERROR(VLOOKUP($A60,'[1]Donor''s Assigned Kilos'!A:O,16,0),0)),0) -> 0 | AZ60: =IF(A60=0,0,IFERROR(SUMIFS([1]Population!Y:Y,[1]Population!J:J,'MASTER-2025'!A60),0)) -> 0 | BA60: =+H60+K60+N60+Q60+T60+W60+Z60+AC60+AF60+AI60+AL60+AO60+AR60+AU60+AX60 -> 0 | BB60: =INT(I60+L60+O60+R60+U60+X60+AA60+AD60+AG60+AJ60+AM60+AP60+AS60+AV60+AY60) -> 0 | BC60: =ROUND(I60+L60+O60+R60+U60,0) -> 0 | BD60: =IF(A60=0,0,(+J60+M60+P60+S60+V60+Y60+AB60+AE60+AH60+AK60+AN60+AQ60+AT60+AW60+AZ60)) -> 0 | BE60: =IF(A60=0,0,SUMIFS([1]Population!C:C,[1]Population!A:A,'MASTER-2025'!A60)) -> #VALUE! | BF60: =IF(A60=0,0,SUMIFS([1]Population!D:D,[1]Population!A:A,'MASTER-2025'!A60)) -> #VALUE! | BG60: =IF(A60=0,0,SUMIFS([1]Population!E:E,[1]Population!A:A,'MASTER-2025'!A60)) -> #VALUE! | BH60: =IF(A60=0,0,SUMIFS([1]Population!F:F,[1]Population!A:A,'MASTER-2025'!A60)) -> #VALUE! | BI60: =+BF60+BG60+BH60 -> #VALUE! | BJ60: =+BK60-BI60-BH60-BG60-BF60-BE60 -> #VALUE! | BK60: =IF(A60=0,0,SUMIFS([1]Population!G:G,[1]Population!A:A,'MASTER-2025'!A60)) -> #VALUE! | BL60: {=IFERROR(VLOOKUP(A60,'[1]Now-OB-kg-POB-25'!A:AQ,{3,4,5,6,7,8,9,10,11,12,13,14},0),0)} -> 2 | BM60: 0 | BN60: 0 | BO60: 0 | BP60: 0 | BQ60: 0 | BR60: 0 | BS60: 0 | BT60: 0 | BU60: 0 | BV60: 0 | BW60: 0 | BX60: =SUM(BL60:BW60) -> 2 | BY60: {=IFERROR(VLOOKUP(A60,'[1]Now-OB-kg-POB-25'!A:AQ,{17,18,19,20,21,22,23,24,25,26,27,28},0),0)} -> 63 | BZ60: 0 | CA60: 0 | CB60: 0 | CC60: 0 | CD60: 0 | CE60: 0 | CF60: 0 | CG60: 0 | CH60: 0 | CI60: 0 | CJ60: 0 | CK60: =SUM(BY60:CJ60) -> 63 | CL60: {=IFERROR(VLOOKUP(A60,'[1]Now-OB-kg-POB-25'!A:AQ,{31,32,33,34,35,36,37,38,39,40,41,42},0),0)} -> 251 | CM60: 0 | CN60: 0 | CO60: 0 | CP60: 0 | CQ60: 0 | CR60: 0 | CS60: 0 | CT60: 0 | CU60: 0 | CV60: 0 | CW60: 0 | CX60: =SUM(CL60:CW60) -> 251 | CY60: =IF(A60=0,0,IFERROR(VLOOKUP(A60,'[1]Info Donantes'!C:F,2,0),"Sin Contacto")) -> Rogelio Garibaldo | CZ60: =IF(A60=0,0,IFERROR(VLOOKUP(A60,'[1]Info Donantes'!C:F,3,0),"Sin Correo")) -> rgaribaldo@thegroupg.com | DA60: =IF(A60=0,0,IFERROR(VLOOKUP(A60,'[1]Info Donantes'!C:F,4,0),"Sin Telefono")) -> 209 3790 ext 205 | DB60: =IF(A60=0,0,"Reporte de Trazabiidad"&" - "&'[1]Donor Summary'!$C$2&" - "&A60&"") -> Reporte de Trazabiidad - - LINA CORPORATION INC (LINA)
A61: MEDIA ITEMS, INC | B61: =INT(IFERROR(VLOOKUP(A61,'[1]Donor Summary'!C:F,3,0),0)) -> 0 | C61: =INT(ROUND(IFERROR(VLOOKUP(A61,'[1]Donor Summary'!C:F,4,0),0),1)) -> 0 | D61: =INT(ROUND(C61-B61,1)) -> 0 | E61: =IF(A61=0,"",TEXT((IFERROR(D61/C61,0)),"0.00%")) -> 0.00% | F61: =IF(A61=0,"",TEXT((IFERROR(B61/C61,0)),"0.0%")) -> 0.0% | G61: =INT(D61*3) -> 0 | I61: =IFERROR(VLOOKUP(A61,'[1]Lot All by Part'!T:Y,6,0),0) -> 0 | K61: =IFERROR(VLOOKUP($A61,'[1]Donor-Served OBs'!A:N,3,0),0) -> 0 | L61: =ROUNDUP(IF(A61=0,0,IFERROR(VLOOKUP($A61,'[1]Donor''s Assigned Kilos'!A:O,3,0),0)),0) -> 0 | M61: =IF(A61=0,0,IFERROR(SUMIFS([1]Population!M:M,[1]Population!J:J,'MASTER-2025'!A61),0)) -> 0 | N61: =IFERROR(VLOOKUP($A61,'[1]Donor-Served OBs'!A:N,4,0),0) -> 0 | O61: =ROUNDUP(IF(A61=0,0,IFERROR(VLOOKUP($A61,'[1]Donor''s Assigned Kilos'!A:O,4,0),0)),0) -> 0 | P61: =IF(A61=0,0,IFERROR(SUMIFS([1]Population!N:N,[1]Population!J:J,'MASTER-2025'!A61),0)) -> 0 | Q61: =IFERROR(VLOOKUP($A61,'[1]Donor-Served OBs'!A:N,2,0),0) -> 0 | R61: =ROUNDUP(ROUND(IF(A61=0,0,IFERROR(VLOOKUP($A61,'[1]Donor''s Assigned Kilos'!A:O,9,0),0)),1),0) -> 0 | S61: =IF(A61=0,0,IFERROR(SUMIFS([1]Population!S:S,[1]Population!J:J,'MASTER-2025'!A61),0)) -> 0 | T61: =IFERROR(VLOOKUP($A61,'[1]Donor-Served OBs'!A:N,12,0),0) -> 0 | U61: =ROUNDUP(IF(A61=0,0,IF(A61=0,0,IFERROR(VLOOKUP($A61,'[1]Donor''s Assigned Kilos'!A:O,7,0),0))),0) -> 0 | V61: =IF(A61=0,0,IFERROR(SUMIFS([1]Population!Q:Q,[1]Population!J:J,'MASTER-2025'!A61),0)) -> 0 | W61: =IFERROR(VLOOKUP($A61,'[1]Donor-Served OBs'!A:N,10,0),0) -> 0 | X61: =ROUNDUP(IF(A61=0,0,IFERROR(VLOOKUP($A61,'[1]Donor''s Assigned Kilos'!A:N,5,0),0)),0) -> 0 | Y61: =IF(A61=0,0,IFERROR(SUMIFS([1]Population!O:O,[1]Population!J:J,'MASTER-2025'!A61),0)) -> 0 | Z61: =IFERROR(VLOOKUP($A61,'[1]Donor-Served OBs'!A:N,6,0),0) -> 0 | AA61: =ROUNDUP(IF(A61=0,0,IFERROR(VLOOKUP($A61,'[1]Donor''s Assigned Kilos'!A:N,11,0),0)),0) -> 0 | AB61: =IF(A61=0,0,IFERROR(SUMIFS([1]Population!U:U,[1]Population!J:J,'MASTER-2025'!A61),0)) -> 0 | AC61: =IFERROR(VLOOKUP($A61,'[1]Donor-Served OBs'!A:N,7,0),0) -> 0 | AD61: =ROUNDUP(IF(A61=0,0,IFERROR(VLOOKUP($A61,'[1]Donor''s Assigned Kilos'!A:N,8,0),0)),0) -> 0 | AE61: =IF(A61=0,0,IFERROR(SUMIFS([1]Population!R:R,[1]Population!J:J,'MASTER-2025'!A61),0)) -> 0 | AF61: =IFERROR(VLOOKUP($A61,'[1]Donor-Served OBs'!A:N,8,0),0) -> 0 | AG61: =ROUNDUP(IF(A61=0,0,IFERROR(VLOOKUP($A61,'[1]Donor''s Assigned Kilos'!A:N,6,0),0)),0) -> 0 | AH61: =IF(A61=0,0,IFERROR(SUMIFS([1]Population!P:P,[1]Population!J:J,'MASTER-2025'!A61),0)) -> 0 | AI61: =IFERROR(VLOOKUP($A61,'[1]Donor-Served OBs'!A:N,9,0),0) -> 0 | AJ61: =ROUNDUP(IF(A61=0,0,IFERROR(VLOOKUP($A61,'[1]Donor''s Assigned Kilos'!A:N,12,0),0)),0) -> 0 | AK61: =IF(A61=0,0,IFERROR(SUMIFS([1]Population!V:V,[1]Population!J:J,'MASTER-2025'!A61),0)) -> 0 | AL61: =IFERROR(VLOOKUP($A61,'[1]Donor-Served OBs'!A:N,16,0),0) -> 0 | AM61: =ROUNDUP(IF(A61=0,0,IFERROR(VLOOKUP($A61,'[1]Donor''s Assigned Kilos'!A:O,16,0),0)),0) -> 0 | AN61: =IF(A61=0,0,IFERROR(SUMIFS([1]Population!Z:Z,[1]Population!J:J,'MASTER-2025'!A61),0)) -> 0 | AO61: =IFERROR(VLOOKUP($A61,'[1]Donor-Served OBs'!A:N,11,0),0) -> 0 | AP61: =ROUNDUP(IF(A61=0,0,IFERROR(VLOOKUP($A61,'[1]Donor''s Assigned Kilos'!A:N,13,0),0)),0) -> 0 | AQ61: =IF(A61=0,0,IFERROR(SUMIFS([1]Population!W:W,[1]Population!J:J,'MASTER-2025'!A61),0)) -> 0 | AR61: =IFERROR(VLOOKUP($A61,'[1]Donor-Served OBs'!A:N,5,0),0) -> 0 | AS61: =ROUNDUP(IF(A61=0,0,IFERROR(VLOOKUP($A61,'[1]Donor''s Assigned Kilos'!A:N,10,0),0)),0) -> 0 | AT61: =IF(A61=0,0,IFERROR(SUMIFS([1]Population!T:T,[1]Population!J:J,'MASTER-2025'!A61),0)) -> 0 | AU61: =IFERROR(VLOOKUP($A61,'[1]Donor-Served OBs'!A:N,13,0),0) -> 0 | AV61: =ROUNDUP(IF(A61=0,0,IFERROR(VLOOKUP($A61,'[1]Donor''s Assigned Kilos'!A:N,14,0),0)),0) -> 0 | AW61: =IF(A61=0,0,IFERROR(SUMIFS([1]Population!X:X,[1]Population!J:J,'MASTER-2025'!A61),0)) -> 0 | AX61: =IFERROR(VLOOKUP($A61,'[1]Donor-Served OBs'!A:N,16,0),0) -> 0 | AY61: =ROUNDUP(IF(A61=0,0,IFERROR(VLOOKUP($A61,'[1]Donor''s Assigned Kilos'!A:O,16,0),0)),0) -> 0 | AZ61: =IF(A61=0,0,IFERROR(SUMIFS([1]Population!Y:Y,[1]Population!J:J,'MASTER-2025'!A61),0)) -> 0 | BA61: =+H61+K61+N61+Q61+T61+W61+Z61+AC61+AF61+AI61+AL61+AO61+AR61+AU61+AX61 -> 0 | BB61: =INT(I61+L61+O61+R61+U61+X61+AA61+AD61+AG61+AJ61+AM61+AP61+AS61+AV61+AY61) -> 0 | BC61: =ROUND(I61+L61+O61+R61+U61,0) -> 0 | BD61: =IF(A61=0,0,(+J61+M61+P61+S61+V61+Y61+AB61+AE61+AH61+AK61+AN61+AQ61+AT61+AW61+AZ61)) -> 0 | BE61: =IF(A61=0,0,SUMIFS([1]Population!C:C,[1]Population!A:A,'MASTER-2025'!A61)) -> #VALUE! | BF61: =IF(A61=0,0,SUMIFS([1]Population!D:D,[1]Population!A:A,'MASTER-2025'!A61)) -> #VALUE! | BG61: =IF(A61=0,0,SUMIFS([1]Population!E:E,[1]Population!A:A,'MASTER-2025'!A61)) -> #VALUE! | BH61: =IF(A61=0,0,SUMIFS([1]Population!F:F,[1]Population!A:A,'MASTER-2025'!A61)) -> #VALUE! | BI61: =+BF61+BG61+BH61 -> #VALUE! | BJ61: =+BK61-BI61-BH61-BG61-BF61-BE61 -> #VALUE! | BK61: =IF(A61=0,0,SUMIFS([1]Population!G:G,[1]Population!A:A,'MASTER-2025'!A61)) -> #VALUE! | BL61: {=IFERROR(VLOOKUP(A61,'[1]Now-OB-kg-POB-25'!A:AQ,{3,4,5,6,7,8,9,10,11,12,13,14},0),0)} -> 35 | BM61: 1 | BN61: 0 | BO61: 0 | BP61: 0 | BQ61: 0 | BR61: 0 | BS61: 0 | BT61: 0 | BU61: 0 | BV61: 0 | BW61: 0 | BX61: =SUM(BL61:BW61) -> 36 | BY61: {=IFERROR(VLOOKUP(A61,'[1]Now-OB-kg-POB-25'!A:AQ,{17,18,19,20,21,22,23,24,25,26,27,28},0),0)} -> 950 | BZ61: 0 | CA61: 0 | CB61: 0 | CC61: 0 | CD61: 0 | CE61: 0 | CF61: 0 | CG61: 0 | CH61: 0 | CI61: 0 | CJ61: 0 | CK61: =SUM(BY61:CJ61) -> 950 | CL61: {=IFERROR(VLOOKUP(A61,'[1]Now-OB-kg-POB-25'!A:AQ,{31,32,33,34,35,36,37,38,39,40,41,42},0),0)} -> 12637 | CM61: 400 | CN61: 0 | CO61: 0 | CP61: 0 | CQ61: 0 | CR61: 0 | CS61: 0 | CT61: 0 | CU61: 0 | CV61: 0 | CW61: 0 | CX61: =SUM(CL61:CW61) -> 13037 | CY61: =IF(A61=0,0,IFERROR(VLOOKUP(A61,'[1]Info Donantes'!C:F,2,0),"Sin Contacto")) -> 0 | CZ61: =IF(A61=0,0,IFERROR(VLOOKUP(A61,'[1]Info Donantes'!C:F,3,0),"Sin Correo")) -> 0 | DA61: =IF(A61=0,0,IFERROR(VLOOKUP(A61,'[1]Info Donantes'!C:F,4,0),"Sin Telefono")) -> 303-1545 | DB61: =IF(A61=0,0,"Reporte de Trazabiidad"&" - "&'[1]Donor Summary'!$C$2&" - "&A61&"") -> Reporte de Trazabiidad - - MEDIA ITEMS, INC
A62: MELO FARMA, S.A. | B62: =INT(IFERROR(VLOOKUP(A62,'[1]Donor Summary'!C:F,3,0),0)) -> 0 | C62: =INT(ROUND(IFERROR(VLOOKUP(A62,'[1]Donor Summary'!C:F,4,0),0),1)) -> 64 | D62: =INT(ROUND(C62-B62,1)) -> 64 | E62: =IF(A62=0,"",TEXT((IFERROR(D62/C62,0)),"0.00%")) -> 100.00% | F62: =IF(A62=0,"",TEXT((IFERROR(B62/C62,0)),"0.0%")) -> 0.0% | G62: =INT(D62*3) -> 192 | I62: =IFERROR(VLOOKUP(A62,'[1]Lot All by Part'!T:Y,6,0),0) -> 0 | K62: =IFERROR(VLOOKUP($A62,'[1]Donor-Served OBs'!A:N,3,0),0) -> 7 | L62: =ROUNDUP(IF(A62=0,0,IFERROR(VLOOKUP($A62,'[1]Donor''s Assigned Kilos'!A:O,3,0),0)),0) -> 16 | M62: =IF(A62=0,0,IFERROR(SUMIFS([1]Population!M:M,[1]Population!J:J,'MASTER-2025'!A62),0)) -> 0 | N62: =IFERROR(VLOOKUP($A62,'[1]Donor-Served OBs'!A:N,4,0),0) -> 5 | O62: =ROUNDUP(IF(A62=0,0,IFERROR(VLOOKUP($A62,'[1]Donor''s Assigned Kilos'!A:O,4,0),0)),0) -> 29 | P62: =IF(A62=0,0,IFERROR(SUMIFS([1]Population!N:N,[1]Population!J:J,'MASTER-2025'!A62),0)) -> 0 | Q62: =IFERROR(VLOOKUP($A62,'[1]Donor-Served OBs'!A:N,2,0),0) -> 3 | R62: =ROUNDUP(ROUND(IF(A62=0,0,IFERROR(VLOOKUP($A62,'[1]Donor''s Assigned Kilos'!A:O,9,0),0)),1),0) -> 10 | S62: =IF(A62=0,0,IFERROR(SUMIFS([1]Population!S:S,[1]Population!J:J,'MASTER-2025'!A62),0)) -> 0 | T62: =IFERROR(VLOOKUP($A62,'[1]Donor-Served OBs'!A:N,12,0),0) -> 0 | U62: =ROUNDUP(IF(A62=0,0,IF(A62=0,0,IFERROR(VLOOKUP($A62,'[1]Donor''s Assigned Kilos'!A:O,7,0),0))),0) -> 0 | V62: =IF(A62=0,0,IFERROR(SUMIFS([1]Population!Q:Q,[1]Population!J:J,'MASTER-2025'!A62),0)) -> 0 | W62: =IFERROR(VLOOKUP($A62,'[1]Donor-Served OBs'!A:N,10,0),0) -> 3 | X62: =ROUNDUP(IF(A62=0,0,IFERROR(VLOOKUP($A62,'[1]Donor''s Assigned Kilos'!A:N,5,0),0)),0) -> 6 | Y62: =IF(A62=0,0,IFERROR(SUMIFS([1]Population!O:O,[1]Population!J:J,'MASTER-2025'!A62),0)) -> 0 | Z62: =IFERROR(VLOOKUP($A62,'[1]Donor-Served OBs'!A:N,6,0),0) -> 0 | AA62: =ROUNDUP(IF(A62=0,0,IFERROR(VLOOKUP($A62,'[1]Donor''s Assigned Kilos'!A:N,11,0),0)),0) -> 0 | AB62: =IF(A62=0,0,IFERROR(SUMIFS([1]Population!U:U,[1]Population!J:J,'MASTER-2025'!A62),0)) -> 0 | AC62: =IFERROR(VLOOKUP($A62,'[1]Donor-Served OBs'!A:N,7,0),0) -> 1 | AD62: =ROUNDUP(IF(A62=0,0,IFERROR(VLOOKUP($A62,'[1]Donor''s Assigned Kilos'!A:N,8,0),0)),0) -> 6 | AE62: =IF(A62=0,0,IFERROR(SUMIFS([1]Population!R:R,[1]Population!J:J,'MASTER-2025'!A62),0)) -> 0 | AF62: =IFERROR(VLOOKUP($A62,'[1]Donor-Served OBs'!A:N,8,0),0) -> 0 | AG62: =ROUNDUP(IF(A62=0,0,IFERROR(VLOOKUP($A62,'[1]Donor''s Assigned Kilos'!A:N,6,0),0)),0) -> 0 | AH62: =IF(A62=0,0,IFERROR(SUMIFS([1]Population!P:P,[1]Population!J:J,'MASTER-2025'!A62),0)) -> 0 | AI62: =IFERROR(VLOOKUP($A62,'[1]Donor-Served OBs'!A:N,9,0),0) -> 0 | AJ62: =ROUNDUP(IF(A62=0,0,IFERROR(VLOOKUP($A62,'[1]Donor''s Assigned Kilos'!A:N,12,0),0)),0) -> 0 | AK62: =IF(A62=0,0,IFERROR(SUMIFS([1]Population!V:V,[1]Population!J:J,'MASTER-2025'!A62),0)) -> 0 | AL62: =IFERROR(VLOOKUP($A62,'[1]Donor-Served OBs'!A:N,16,0),0) -> 0 | AM62: =ROUNDUP(IF(A62=0,0,IFERROR(VLOOKUP($A62,'[1]Donor''s Assigned Kilos'!A:O,16,0),0)),0) -> 0 | AN62: =IF(A62=0,0,IFERROR(SUMIFS([1]Population!Z:Z,[1]Population!J:J,'MASTER-2025'!A62),0)) -> 0 | AO62: =IFERROR(VLOOKUP($A62,'[1]Donor-Served OBs'!A:N,11,0),0) -> 0 | AP62: =ROUNDUP(IF(A62=0,0,IFERROR(VLOOKUP($A62,'[1]Donor''s Assigned Kilos'!A:N,13,0),0)),0) -> 0 | AQ62: =IF(A62=0,0,IFERROR(SUMIFS([1]Population!W:W,[1]Population!J:J,'MASTER-2025'!A62),0)) -> 0 | AR62: =IFERROR(VLOOKUP($A62,'[1]Donor-Served OBs'!A:N,5,0),0) -> 0 | AS62: =ROUNDUP(IF(A62=0,0,IFERROR(VLOOKUP($A62,'[1]Donor''s Assigned Kilos'!A:N,10,0),0)),0) -> 0 | AT62: =IF(A62=0,0,IFERROR(SUMIFS([1]Population!T:T,[1]Population!J:J,'MASTER-2025'!A62),0)) -> 0 | AU62: =IFERROR(VLOOKUP($A62,'[1]Donor-Served OBs'!A:N,13,0),0) -> 0 | AV62: =ROUNDUP(IF(A62=0,0,IFERROR(VLOOKUP($A62,'[1]Donor''s Assigned Kilos'!A:N,14,0),0)),0) -> 0 | AW62: =IF(A62=0,0,IFERROR(SUMIFS([1]Population!X:X,[1]Population!J:J,'MASTER-2025'!A62),0)) -> 0 | AX62: =IFERROR(VLOOKUP($A62,'[1]Donor-Served OBs'!A:N,16,0),0) -> 0 | AY62: =ROUNDUP(IF(A62=0,0,IFERROR(VLOOKUP($A62,'[1]Donor''s Assigned Kilos'!A:O,16,0),0)),0) -> 0 | AZ62: =IF(A62=0,0,IFERROR(SUMIFS([1]Population!Y:Y,[1]Population!J:J,'MASTER-2025'!A62),0)) -> 0 | BA62: =+H62+K62+N62+Q62+T62+W62+Z62+AC62+AF62+AI62+AL62+AO62+AR62+AU62+AX62 -> 19 | BB62: =INT(I62+L62+O62+R62+U62+X62+AA62+AD62+AG62+AJ62+AM62+AP62+AS62+AV62+AY62) -> 67 | BC62: =ROUND(I62+L62+O62+R62+U62,0) -> 55 | BD62: =IF(A62=0,0,(+J62+M62+P62+S62+V62+Y62+AB62+AE62+AH62+AK62+AN62+AQ62+AT62+AW62+AZ62)) -> 0 | BE62: =IF(A62=0,0,SUMIFS([1]Population!C:C,[1]Population!A:A,'MASTER-2025'!A62)) -> #VALUE! | BF62: =IF(A62=0,0,SUMIFS([1]Population!D:D,[1]Population!A:A,'MASTER-2025'!A62)) -> #VALUE! | BG62: =IF(A62=0,0,SUMIFS([1]Population!E:E,[1]Population!A:A,'MASTER-2025'!A62)) -> #VALUE! | BH62: =IF(A62=0,0,SUMIFS([1]Population!F:F,[1]Population!A:A,'MASTER-2025'!A62)) -> #VALUE! | BI62: =+BF62+BG62+BH62 -> #VALUE! | BJ62: =+BK62-BI62-BH62-BG62-BF62-BE62 -> #VALUE! | BK62: =IF(A62=0,0,SUMIFS([1]Population!G:G,[1]Population!A:A,'MASTER-2025'!A62)) -> #VALUE! | BL62: {=IFERROR(VLOOKUP(A62,'[1]Now-OB-kg-POB-25'!A:AQ,{3,4,5,6,7,8,9,10,11,12,13,14},0),0)} -> 0 | BM62: 0 | BN62: 19 | BO62: 0 | BP62: 0 | BQ62: 0 | BR62: 0 | BS62: 0 | BT62: 0 | BU62: 0 | BV62: 0 | BW62: 0 | BX62: =SUM(BL62:BW62) -> 19 | BY62: {=IFERROR(VLOOKUP(A62,'[1]Now-OB-kg-POB-25'!A:AQ,{17,18,19,20,21,22,23,24,25,26,27,28},0),0)} -> 0 | BZ62: 61 | CA62: 64 | CB62: 0 | CC62: 0 | CD62: 0 | CE62: 0 | CF62: 0 | CG62: 0 | CH62: 0 | CI62: 0 | CJ62: 0 | CK62: =SUM(BY62:CJ62) -> 125 | CL62: {=IFERROR(VLOOKUP(A62,'[1]Now-OB-kg-POB-25'!A:AQ,{31,32,33,34,35,36,37,38,39,40,41,42},0),0)} -> 0 | CM62: 0 | CN62: 3747 | CO62: 0 | CP62: 0 | CQ62: 0 | CR62: 0 | CS62: 0 | CT62: 0 | CU62: 0 | CV62: 0 | CW62: 0 | CX62: =SUM(CL62:CW62) -> 3747 | CY62: =IF(A62=0,0,IFERROR(VLOOKUP(A62,'[1]Info Donantes'!C:F,2,0),"Sin Contacto")) -> Sin Contacto | CZ62: =IF(A62=0,0,IFERROR(VLOOKUP(A62,'[1]Info Donantes'!C:F,3,0),"Sin Correo")) -> Sin Correo | DA62: =IF(A62=0,0,IFERROR(VLOOKUP(A62,'[1]Info Donantes'!C:F,4,0),"Sin Telefono")) -> Sin Telefono | DB62: =IF(A62=0,0,"Reporte de Trazabiidad"&" - "&'[1]Donor Summary'!$C$2&" - "&A62&"") -> Reporte de Trazabiidad - - MELO FARMA, S.A.
A63: MERCALIMENTOS PANAMA, S.A | B63: =INT(IFERROR(VLOOKUP(A63,'[1]Donor Summary'!C:F,3,0),0)) -> 0 | C63: =INT(ROUND(IFERROR(VLOOKUP(A63,'[1]Donor Summary'!C:F,4,0),0),1)) -> 3483 | D63: =INT(ROUND(C63-B63,1)) -> 3483 | E63: =IF(A63=0,"",TEXT((IFERROR(D63/C63,0)),"0.00%")) -> 100.00% | F63: =IF(A63=0,"",TEXT((IFERROR(B63/C63,0)),"0.0%")) -> 0.0% | G63: =INT(D63*3) -> 10449 | I63: =IFERROR(VLOOKUP(A63,'[1]Lot All by Part'!T:Y,6,0),0) -> 0 | K63: =IFERROR(VLOOKUP($A63,'[1]Donor-Served OBs'!A:N,3,0),0) -> 20 | L63: =ROUNDUP(IF(A63=0,0,IFERROR(VLOOKUP($A63,'[1]Donor''s Assigned Kilos'!A:O,3,0),0)),0) -> 897 | M63: =IF(A63=0,0,IFERROR(SUMIFS([1]Population!M:M,[1]Population!J:J,'MASTER-2025'!A63),0)) -> 0 | N63: =IFERROR(VLOOKUP($A63,'[1]Donor-Served OBs'!A:N,4,0),0) -> 32 | O63: =ROUNDUP(IF(A63=0,0,IFERROR(VLOOKUP($A63,'[1]Donor''s Assigned Kilos'!A:O,4,0),0)),0) -> 386 | P63: =IF(A63=0,0,IFERROR(SUMIFS([1]Population!N:N,[1]Population!J:J,'MASTER-2025'!A63),0)) -> 0 | Q63: =IFERROR(VLOOKUP($A63,'[1]Donor-Served OBs'!A:N,2,0),0) -> 5 | R63: =ROUNDUP(ROUND(IF(A63=0,0,IFERROR(VLOOKUP($A63,'[1]Donor''s Assigned Kilos'!A:O,9,0),0)),1),0) -> 40 | S63: =IF(A63=0,0,IFERROR(SUMIFS([1]Population!S:S,[1]Population!J:J,'MASTER-2025'!A63),0)) -> 0 | T63: =IFERROR(VLOOKUP($A63,'[1]Donor-Served OBs'!A:N,12,0),0) -> 4 | U63: =ROUNDUP(IF(A63=0,0,IF(A63=0,0,IFERROR(VLOOKUP($A63,'[1]Donor''s Assigned Kilos'!A:O,7,0),0))),0) -> 101 | V63: =IF(A63=0,0,IFERROR(SUMIFS([1]Population!Q:Q,[1]Population!J:J,'MASTER-2025'!A63),0)) -> 0 | W63: =IFERROR(VLOOKUP($A63,'[1]Donor-Served OBs'!A:N,10,0),0) -> 14 | X63: =ROUNDUP(IF(A63=0,0,IFERROR(VLOOKUP($A63,'[1]Donor''s Assigned Kilos'!A:N,5,0),0)),0) -> 147 | Y63: =IF(A63=0,0,IFERROR(SUMIFS([1]Population!O:O,[1]Population!J:J,'MASTER-2025'!A63),0)) -> 0 | Z63: =IFERROR(VLOOKUP($A63,'[1]Donor-Served OBs'!A:N,6,0),0) -> 0 | AA63: =ROUNDUP(IF(A63=0,0,IFERROR(VLOOKUP($A63,'[1]Donor''s Assigned Kilos'!A:N,11,0),0)),0) -> 0 | AB63: =IF(A63=0,0,IFERROR(SUMIFS([1]Population!U:U,[1]Population!J:J,'MASTER-2025'!A63),0)) -> 0 | AC63: =IFERROR(VLOOKUP($A63,'[1]Donor-Served OBs'!A:N,7,0),0) -> 5 | AD63: =ROUNDUP(IF(A63=0,0,IFERROR(VLOOKUP($A63,'[1]Donor''s Assigned Kilos'!A:N,8,0),0)),0) -> 92 | AE63: =IF(A63=0,0,IFERROR(SUMIFS([1]Population!R:R,[1]Population!J:J,'MASTER-2025'!A63),0)) -> 0 | AF63: =IFERROR(VLOOKUP($A63,'[1]Donor-Served OBs'!A:N,8,0),0) -> 2 | AG63: =ROUNDUP(IF(A63=0,0,IFERROR(VLOOKUP($A63,'[1]Donor''s Assigned Kilos'!A:N,6,0),0)),0) -> 13 | AH63: =IF(A63=0,0,IFERROR(SUMIFS([1]Population!P:P,[1]Population!J:J,'MASTER-2025'!A63),0)) -> 0 | AI63: =IFERROR(VLOOKUP($A63,'[1]Donor-Served OBs'!A:N,9,0),0) -> 1 | AJ63: =ROUNDUP(IF(A63=0,0,IFERROR(VLOOKUP($A63,'[1]Donor''s Assigned Kilos'!A:N,12,0),0)),0) -> 8 | AK63: =IF(A63=0,0,IFERROR(SUMIFS([1]Population!V:V,[1]Population!J:J,'MASTER-2025'!A63),0)) -> 0 | AL63: =IFERROR(VLOOKUP($A63,'[1]Donor-Served OBs'!A:N,16,0),0) -> 0 | AM63: =ROUNDUP(IF(A63=0,0,IFERROR(VLOOKUP($A63,'[1]Donor''s Assigned Kilos'!A:O,16,0),0)),0) -> 0 | AN63: =IF(A63=0,0,IFERROR(SUMIFS([1]Population!Z:Z,[1]Population!J:J,'MASTER-2025'!A63),0)) -> 0 | AO63: =IFERROR(VLOOKUP($A63,'[1]Donor-Served OBs'!A:N,11,0),0) -> 0 | AP63: =ROUNDUP(IF(A63=0,0,IFERROR(VLOOKUP($A63,'[1]Donor''s Assigned Kilos'!A:N,13,0),0)),0) -> 0 | AQ63: =IF(A63=0,0,IFERROR(SUMIFS([1]Population!W:W,[1]Population!J:J,'MASTER-2025'!A63),0)) -> 0 | AR63: =IFERROR(VLOOKUP($A63,'[1]Donor-Served OBs'!A:N,5,0),0) -> 4 | AS63: =ROUNDUP(IF(A63=0,0,IFERROR(VLOOKUP($A63,'[1]Donor''s Assigned Kilos'!A:N,10,0),0)),0) -> 30 | AT63: =IF(A63=0,0,IFERROR(SUMIFS([1]Population!T:T,[1]Population!J:J,'MASTER-2025'!A63),0)) -> 0 | AU63: =IFERROR(VLOOKUP($A63,'[1]Donor-Served OBs'!A:N,13,0),0) -> 0 | AV63: =ROUNDUP(IF(A63=0,0,IFERROR(VLOOKUP($A63,'[1]Donor''s Assigned Kilos'!A:N,14,0),0)),0) -> 0 | AW63: =IF(A63=0,0,IFERROR(SUMIFS([1]Population!X:X,[1]Population!J:J,'MASTER-2025'!A63),0)) -> 0 | AX63: =IFERROR(VLOOKUP($A63,'[1]Donor-Served OBs'!A:N,16,0),0) -> 0 | AY63: =ROUNDUP(IF(A63=0,0,IFERROR(VLOOKUP($A63,'[1]Donor''s Assigned Kilos'!A:O,16,0),0)),0) -> 0 | AZ63: =IF(A63=0,0,IFERROR(SUMIFS([1]Population!Y:Y,[1]Population!J:J,'MASTER-2025'!A63),0)) -> 0 | BA63: =+H63+K63+N63+Q63+T63+W63+Z63+AC63+AF63+AI63+AL63+AO63+AR63+AU63+AX63 -> 87 | BB63: =INT(I63+L63+O63+R63+U63+X63+AA63+AD63+AG63+AJ63+AM63+AP63+AS63+AV63+AY63) -> 1714 | BC63: =ROUND(I63+L63+O63+R63+U63,0) -> 1424 | BD63: =IF(A63=0,0,(+J63+M63+P63+S63+V63+Y63+AB63+AE63+AH63+AK63+AN63+AQ63+AT63+AW63+AZ63)) -> 0 | BE63: =IF(A63=0,0,SUMIFS([1]Population!C:C,[1]Population!A:A,'MASTER-2025'!A63)) -> #VALUE! | BF63: =IF(A63=0,0,SUMIFS([1]Population!D:D,[1]Population!A:A,'MASTER-2025'!A63)) -> #VALUE! | BG63: =IF(A63=0,0,SUMIFS([1]Population!E:E,[1]Population!A:A,'MASTER-2025'!A63)) -> #VALUE! | BH63: =IF(A63=0,0,SUMIFS([1]Population!F:F,[1]Population!A:A,'MASTER-2025'!A63)) -> #VALUE! | BI63: =+BF63+BG63+BH63 -> #VALUE! | BJ63: =+BK63-BI63-BH63-BG63-BF63-BE63 -> #VALUE! | BK63: =IF(A63=0,0,SUMIFS([1]Population!G:G,[1]Population!A:A,'MASTER-2025'!A63)) -> #VALUE! | BL63: {=IFERROR(VLOOKUP(A63,'[1]Now-OB-kg-POB-25'!A:AQ,{3,4,5,6,7,8,9,10,11,12,13,14},0),0)} -> 0 | BM63: 0 | BN63: 87 | BO63: 0 | BP63: 0 | BQ63: 0 | BR63: 0 | BS63: 0 | BT63: 0 | BU63: 0 | BV63: 0 | BW63: 0 | BX63: =SUM(BL63:BW63) -> 87 | BY63: {=IFERROR(VLOOKUP(A63,'[1]Now-OB-kg-POB-25'!A:AQ,{17,18,19,20,21,22,23,24,25,26,27,28},0),0)} -> 0 | BZ63: 0 | CA63: 3483 | CB63: 0 | CC63: 0 | CD63: 0 | CE63: 0 | CF63: 0 | CG63: 0 | CH63: 0 | CI63: 0 | CJ63: 0 | CK63: =SUM(BY63:CJ63) -> 3483 | CL63: {=IFERROR(VLOOKUP(A63,'[1]Now-OB-kg-POB-25'!A:AQ,{31,32,33,34,35,36,37,38,39,40,41,42},0),0)} -> 0 | CM63: 0 | CN63: 30032 | CO63: 0 | CP63: 0 | CQ63: 0 | CR63: 0 | CS63: 0 | CT63: 0 | CU63: 0 | CV63: 0 | CW63: 0 | CX63: =SUM(CL63:CW63) -> 30032 | CY63: =IF(A63=0,0,IFERROR(VLOOKUP(A63,'[1]Info Donantes'!C:F,2,0),"Sin Contacto")) -> Ricardo Larrea | CZ63: =IF(A63=0,0,IFERROR(VLOOKUP(A63,'[1]Info Donantes'!C:F,3,0),"Sin Correo")) -> ricardo@cialimentos.com | DA63: =IF(A63=0,0,IFERROR(VLOOKUP(A63,'[1]Info Donantes'!C:F,4,0),"Sin Telefono")) -> 291-0300/291-0415 | DB63: =IF(A63=0,0,"Reporte de Trazabiidad"&" - "&'[1]Donor Summary'!$C$2&" - "&A63&"") -> Reporte de Trazabiidad - - MERCALIMENTOS PANAMA, S.A
A64: NATHAN FOODS CORPORATION | B64: =INT(IFERROR(VLOOKUP(A64,'[1]Donor Summary'!C:F,3,0),0)) -> 0 | C64: =INT(ROUND(IFERROR(VLOOKUP(A64,'[1]Donor Summary'!C:F,4,0),0),1)) -> 0 | D64: =INT(ROUND(C64-B64,1)) -> 0 | E64: =IF(A64=0,"",TEXT((IFERROR(D64/C64,0)),"0.00%")) -> 0.00% | F64: =IF(A64=0,"",TEXT((IFERROR(B64/C64,0)),"0.0%")) -> 0.0% | G64: =INT(D64*3) -> 0 | I64: =IFERROR(VLOOKUP(A64,'[1]Lot All by Part'!T:Y,6,0),0) -> 0 | K64: =IFERROR(VLOOKUP($A64,'[1]Donor-Served OBs'!A:N,3,0),0) -> 0 | L64: =ROUNDUP(IF(A64=0,0,IFERROR(VLOOKUP($A64,'[1]Donor''s Assigned Kilos'!A:O,3,0),0)),0) -> 0 | M64: =IF(A64=0,0,IFERROR(SUMIFS([1]Population!M:M,[1]Population!J:J,'MASTER-2025'!A64),0)) -> 0 | N64: =IFERROR(VLOOKUP($A64,'[1]Donor-Served OBs'!A:N,4,0),0) -> 0 | O64: =ROUNDUP(IF(A64=0,0,IFERROR(VLOOKUP($A64,'[1]Donor''s Assigned Kilos'!A:O,4,0),0)),0) -> 0 | P64: =IF(A64=0,0,IFERROR(SUMIFS([1]Population!N:N,[1]Population!J:J,'MASTER-2025'!A64),0)) -> 0 | Q64: =IFERROR(VLOOKUP($A64,'[1]Donor-Served OBs'!A:N,2,0),0) -> 0 | R64: =ROUNDUP(ROUND(IF(A64=0,0,IFERROR(VLOOKUP($A64,'[1]Donor''s Assigned Kilos'!A:O,9,0),0)),1),0) -> 0 | S64: =IF(A64=0,0,IFERROR(SUMIFS([1]Population!S:S,[1]Population!J:J,'MASTER-2025'!A64),0)) -> 0 | T64: =IFERROR(VLOOKUP($A64,'[1]Donor-Served OBs'!A:N,12,0),0) -> 0 | U64: =ROUNDUP(IF(A64=0,0,IF(A64=0,0,IFERROR(VLOOKUP($A64,'[1]Donor''s Assigned Kilos'!A:O,7,0),0))),0) -> 0 | V64: =IF(A64=0,0,IFERROR(SUMIFS([1]Population!Q:Q,[1]Population!J:J,'MASTER-2025'!A64),0)) -> 0 | W64: =IFERROR(VLOOKUP($A64,'[1]Donor-Served OBs'!A:N,10,0),0) -> 0 | X64: =ROUNDUP(IF(A64=0,0,IFERROR(VLOOKUP($A64,'[1]Donor''s Assigned Kilos'!A:N,5,0),0)),0) -> 0 | Y64: =IF(A64=0,0,IFERROR(SUMIFS([1]Population!O:O,[1]Population!J:J,'MASTER-2025'!A64),0)) -> 0 | Z64: =IFERROR(VLOOKUP($A64,'[1]Donor-Served OBs'!A:N,6,0),0) -> 0 | AA64: =ROUNDUP(IF(A64=0,0,IFERROR(VLOOKUP($A64,'[1]Donor''s Assigned Kilos'!A:N,11,0),0)),0) -> 0 | AB64: =IF(A64=0,0,IFERROR(SUMIFS([1]Population!U:U,[1]Population!J:J,'MASTER-2025'!A64),0)) -> 0 | AC64: =IFERROR(VLOOKUP($A64,'[1]Donor-Served OBs'!A:N,7,0),0) -> 0 | AD64: =ROUNDUP(IF(A64=0,0,IFERROR(VLOOKUP($A64,'[1]Donor''s Assigned Kilos'!A:N,8,0),0)),0) -> 0 | AE64: =IF(A64=0,0,IFERROR(SUMIFS([1]Population!R:R,[1]Population!J:J,'MASTER-2025'!A64),0)) -> 0 | AF64: =IFERROR(VLOOKUP($A64,'[1]Donor-Served OBs'!A:N,8,0),0) -> 0 | AG64: =ROUNDUP(IF(A64=0,0,IFERROR(VLOOKUP($A64,'[1]Donor''s Assigned Kilos'!A:N,6,0),0)),0) -> 0 | AH64: =IF(A64=0,0,IFERROR(SUMIFS([1]Population!P:P,[1]Population!J:J,'MASTER-2025'!A64),0)) -> 0 | AI64: =IFERROR(VLOOKUP($A64,'[1]Donor-Served OBs'!A:N,9,0),0) -> 0 | AJ64: =ROUNDUP(IF(A64=0,0,IFERROR(VLOOKUP($A64,'[1]Donor''s Assigned Kilos'!A:N,12,0),0)),0) -> 0 | AK64: =IF(A64=0,0,IFERROR(SUMIFS([1]Population!V:V,[1]Population!J:J,'MASTER-2025'!A64),0)) -> 0 | AL64: =IFERROR(VLOOKUP($A64,'[1]Donor-Served OBs'!A:N,16,0),0) -> 0 | AM64: =ROUNDUP(IF(A64=0,0,IFERROR(VLOOKUP($A64,'[1]Donor''s Assigned Kilos'!A:O,16,0),0)),0) -> 0 | AN64: =IF(A64=0,0,IFERROR(SUMIFS([1]Population!Z:Z,[1]Population!J:J,'MASTER-2025'!A64),0)) -> 0 | AO64: =IFERROR(VLOOKUP($A64,'[1]Donor-Served OBs'!A:N,11,0),0) -> 0 | AP64: =ROUNDUP(IF(A64=0,0,IFERROR(VLOOKUP($A64,'[1]Donor''s Assigned Kilos'!A:N,13,0),0)),0) -> 0 | AQ64: =IF(A64=0,0,IFERROR(SUMIFS([1]Population!W:W,[1]Population!J:J,'MASTER-2025'!A64),0)) -> 0 | AR64: =IFERROR(VLOOKUP($A64,'[1]Donor-Served OBs'!A:N,5,0),0) -> 0 | AS64: =ROUNDUP(IF(A64=0,0,IFERROR(VLOOKUP($A64,'[1]Donor''s Assigned Kilos'!A:N,10,0),0)),0) -> 0 | AT64: =IF(A64=0,0,IFERROR(SUMIFS([1]Population!T:T,[1]Population!J:J,'MASTER-2025'!A64),0)) -> 0 | AU64: =IFERROR(VLOOKUP($A64,'[1]Donor-Served OBs'!A:N,13,0),0) -> 0 | AV64: =ROUNDUP(IF(A64=0,0,IFERROR(VLOOKUP($A64,'[1]Donor''s Assigned Kilos'!A:N,14,0),0)),0) -> 0 | AW64: =IF(A64=0,0,IFERROR(SUMIFS([1]Population!X:X,[1]Population!J:J,'MASTER-2025'!A64),0)) -> 0 | AX64: =IFERROR(VLOOKUP($A64,'[1]Donor-Served OBs'!A:N,16,0),0) -> 0 | AY64: =ROUNDUP(IF(A64=0,0,IFERROR(VLOOKUP($A64,'[1]Donor''s Assigned Kilos'!A:O,16,0),0)),0) -> 0 | AZ64: =IF(A64=0,0,IFERROR(SUMIFS([1]Population!Y:Y,[1]Population!J:J,'MASTER-2025'!A64),0)) -> 0 | BA64: =+H64+K64+N64+Q64+T64+W64+Z64+AC64+AF64+AI64+AL64+AO64+AR64+AU64+AX64 -> 0 | BB64: =INT(I64+L64+O64+R64+U64+X64+AA64+AD64+AG64+AJ64+AM64+AP64+AS64+AV64+AY64) -> 0 | BC64: =ROUND(I64+L64+O64+R64+U64,0) -> 0 | BD64: =IF(A64=0,0,(+J64+M64+P64+S64+V64+Y64+AB64+AE64+AH64+AK64+AN64+AQ64+AT64+AW64+AZ64)) -> 0 | BE64: =IF(A64=0,0,SUMIFS([1]Population!C:C,[1]Population!A:A,'MASTER-2025'!A64)) -> #VALUE! | BF64: =IF(A64=0,0,SUMIFS([1]Population!D:D,[1]Population!A:A,'MASTER-2025'!A64)) -> #VALUE! | BG64: =IF(A64=0,0,SUMIFS([1]Population!E:E,[1]Population!A:A,'MASTER-2025'!A64)) -> #VALUE! | BH64: =IF(A64=0,0,SUMIFS([1]Population!F:F,[1]Population!A:A,'MASTER-2025'!A64)) -> #VALUE! | BI64: =+BF64+BG64+BH64 -> #VALUE! | BJ64: =+BK64-BI64-BH64-BG64-BF64-BE64 -> #VALUE! | BK64: =IF(A64=0,0,SUMIFS([1]Population!G:G,[1]Population!A:A,'MASTER-2025'!A64)) -> #VALUE! | BL64: {=IFERROR(VLOOKUP(A64,'[1]Now-OB-kg-POB-25'!A:AQ,{3,4,5,6,7,8,9,10,11,12,13,14},0),0)} -> 0 | BM64: 0 | BN64: 0 | BO64: 0 | BP64: 0 | BQ64: 0 | BR64: 0 | BS64: 0 | BT64: 0 | BU64: 0 | BV64: 0 | BW64: 0 | BX64: =SUM(BL64:BW64) -> 0 | BY64: {=IFERROR(VLOOKUP(A64,'[1]Now-OB-kg-POB-25'!A:AQ,{17,18,19,20,21,22,23,24,25,26,27,28},0),0)} -> 0 | BZ64: 0 | CA64: 0 | CB64: 0 | CC64: 0 | CD64: 0 | CE64: 0 | CF64: 0 | CG64: 0 | CH64: 0 | CI64: 0 | CJ64: 0 | CK64: =SUM(BY64:CJ64) -> 0 | CL64: {=IFERROR(VLOOKUP(A64,'[1]Now-OB-kg-POB-25'!A:AQ,{31,32,33,34,35,36,37,38,39,40,41,42},0),0)} -> 0 | CM64: 0 | CN64: 0 | CO64: 0 | CP64: 0 | CQ64: 0 | CR64: 0 | CS64: 0 | CT64: 0 | CU64: 0 | CV64: 0 | CW64: 0 | CX64: =SUM(CL64:CW64) -> 0 | CY64: =IF(A64=0,0,IFERROR(VLOOKUP(A64,'[1]Info Donantes'!C:F,2,0),"Sin Contacto")) -> Clemente Ramos | CZ64: =IF(A64=0,0,IFERROR(VLOOKUP(A64,'[1]Info Donantes'!C:F,3,0),"Sin Correo")) -> logistica@nathanfoods.com | DA64: =IF(A64=0,0,IFERROR(VLOOKUP(A64,'[1]Info Donantes'!C:F,4,0),"Sin Telefono")) -> 0 | DB64: =IF(A64=0,0,"Reporte de Trazabiidad"&" - "&'[1]Donor Summary'!$C$2&" - "&A64&"") -> Reporte de Trazabiidad - - NATHAN FOODS CORPORATION
